Workbook

Sheet Léeme
B2: Growth OS — cómo funciona este fichero
B3: Este Excel es la interfaz de trabajo de un sistema cuya fuente de la verdad vive en el repositorio de GitHub (growth-os/data/*.yaml). El fichero se genera desde esos datos y se puede volver a importar, de modo que cada estado del portfolio queda versionado y es auditable.
B4: El ciclo de trabajo
B5: EL CICLO DE TRABAJO
B6: 1. Tú editas en Excel: estados, avances, gastos, fechas, KPIs, hitos. Sólo las columnas de fondo blanco.
B7: 2. Guardas el fichero en su carpeta de OneDrive/SharePoint.
B8: 3. Le dices al agente «sincroniza el Growth OS». El agente lee el Excel, actualiza los YAML del repo y hace commit: ahí queda el histórico.
B9: 4. Cuando hay cambios estructurales (nuevos departamentos, columnas, métricas o reglas de cálculo), el agente regenera el Excel y lo vuelve a subir.
B10: Reglas de oro
B11: REGLAS DE ORO
B12: No renombres las hojas ni las cabeceras de columna: el importador las busca por nombre.
B13: No escribas en las columnas marcadas con «ƒ» ni en las de fondo gris. Son fórmulas y se sobreescriben en cada regeneración.
... B46: Crítico / vencido / bloqueado

Sheet Dashboard
B2: Founderz · Growth OS | BJ2: =IF(AND(Proyectos!$A2<>"",OR(Proyectos!$H2="En riesgo",Proyectos!$H2="Bloqueado",Proyectos!$AB2>0,IF(Proyectos!$V2="",FALSE,Proyectos!$V2<-0.15))),BK2,"") | BK2: =IF(AND(Proyectos!$A2<>"",OR(Proyectos!$H2="En riesgo",Proyectos!$H2="Bloqueado",Proyectos!$AB2>0,IF(Proyectos!$V2="",FALSE,Proyectos!$V2<-0.15))),N(BK1)+1,N(BK1)) | BN2: =IF(AND(Hitos!$A2<>"",OR(Hitos!$L2="Vencido",Hitos!$L2="Esta semana",Hitos!$L2="Próximos 30 días")),BO2,"") | BO2: =IF(AND(Hitos!$A2<>"",OR(Hitos!$L2="Vencido",Hitos!$L2="Esta semana",Hitos!$L2="Próximos 30 días")),N(BO1)+1,N(BO1))
B3: Panel de dirección — portfolio de proyectos, KPIs e hitos. Todo lo que ves aquí se calcula desde las hojas Proyectos, KPIs y Hitos. | BJ3: =IF(AND(Proyectos!$A3<>"",OR(Proyectos!$H3="En riesgo",Proyectos!$H3="Bloqueado",Proyectos!$AB3>0,IF(Proyectos!$V3="",FALSE,Proyectos!$V3<-0.15))),BK3,"") | BK3: =IF(AND(Proyectos!$A3<>"",OR(Proyectos!$H3="En riesgo",Proyectos!$H3="Bloqueado",Proyectos!$AB3>0,IF(Proyectos!$V3="",FALSE,Proyectos!$V3<-0.15))),N(BK2)+1,N(BK2)) | BN3: =IF(AND(Hitos!$A3<>"",OR(Hitos!$L3="Vencido",Hitos!$L3="Esta semana",Hitos!$L3="Próximos 30 días")),BO3,"") | BO3: =IF(AND(Hitos!$A3<>"",OR(Hitos!$L3="Vencido",Hitos!$L3="Esta semana",Hitos!$L3="Próximos 30 días")),N(BO2)+1,N(BO2))
B4: ="Datos a fecha de "&TEXT(TODAY(),"dd/mm/yyyy") | BJ4: =IF(AND(Proyectos!$A4<>"",OR(Proyectos!$H4="En riesgo",Proyectos!$H4="Bloqueado",Proyectos!$AB4>0,IF(Proyectos!$V4="",FALSE,Proyectos!$V4<-0.15))),BK4,"") | BK4: =IF(AND(Proyectos!$A4<>"",OR(Proyectos!$H4="En riesgo",Proyectos!$H4="Bloqueado",Proyectos!$AB4>0,IF(Proyectos!$V4="",FALSE,Proyectos!$V4<-0.15))),N(BK3)+1,N(BK3)) | BN4: =IF(AND(Hitos!$A4<>"",OR(Hitos!$L4="Vencido",Hitos!$L4="Esta semana",Hitos!$L4="Próximos 30 días")),BO4,"") | BO4: =IF(AND(Hitos!$A4<>"",OR(Hitos!$L4="Vencido",Hitos!$L4="Esta semana",Hitos!$L4="Próximos 30 días")),N(BO3)+1,N(BO3))
BJ5: =IF(AND(Proyectos!$A5<>"",OR(Proyectos!$H5="En riesgo",Proyectos!$H5="Bloqueado",Proyectos!$AB5>0,IF(Proyectos!$V5="",FALSE,Proyectos!$V5<-0.15))),BK5,"") | BK5: =IF(AND(Proyectos!$A5<>"",OR(Proyectos!$H5="En riesgo",Proyectos!$H5="Bloqueado",Proyectos!$AB5>0,IF(Proyectos!$V5="",FALSE,Proyectos!$V5<-0.15))),N(BK4)+1,N(BK4)) | BN5: =IF(AND(Hitos!$A5<>"",OR(Hitos!$L5="Vencido",Hitos!$L5="Esta semana",Hitos!$L5="Próximos 30 días")),BO5,"") | BO5: =IF(AND(Hitos!$A5<>"",OR(Hitos!$L5="Vencido",Hitos!$L5="Esta semana",Hitos!$L5="Próximos 30 días")),N(BO4)+1,N(BO4))
B6: Proyectos totales | C6: Activos | D6: En riesgo o bloqueados | E6: Avance medio | F6: Presupuesto comprometido | G6: Gasto acumulado | H6: % presupuesto consumido | I6: Hitos vencidos | J6: KPIs en crítico | BJ6: =IF(AND(Proyectos!$A6<>"",OR(Proyectos!$H6="En riesgo",Proyectos!$H6="Bloqueado",Proyectos!$AB6>0,IF(Proyectos!$V6="",FALSE,Proyectos!$V6<-0.15))),BK6,"") | BK6: =IF(AND(Proyectos!$A6<>"",OR(Proyectos!$H6="En riesgo",Proyectos!$H6="Bloqueado",Proyectos!$AB6>0,IF(Proyectos!$V6="",FALSE,Proyectos!$V6<-0.15))),N(BK5)+1,N(BK5)) | BN6: =IF(AND(Hitos!$A6<>"",OR(Hitos!$L6="Vencido",Hitos!$L6="Esta semana",Hitos!$L6="Próximos 30 días")),BO6,"") | BO6: =IF(AND(Hitos!$A6<>"",OR(Hitos!$L6="Vencido",Hitos!$L6="Esta semana",Hitos!$L6="Próximos 30 días")),N(BO5)+1,N(BO5))
B7: =COUNTA(Proyectos!$A$2:$A$41) | C7: =COUNTIF(Proyectos!$H$2:$H$41,"En curso")+COUNTIF(Proyectos!$H$2:$H$41,"En riesgo")+COUNTIF(Proyectos!$H$2:$H$41,"Bloqueado") | D7: =COUNTIF(Proyectos!$H$2:$H$41,"En riesgo")+COUNTIF(Proyectos!$H$2:$H$41,"Bloqueado") | E7: =IFERROR(SUMPRODUCT((Proyectos!$A$2:$A$41<>"")*(Proyectos!$H$2:$H$41<>"Cancelado")*Proyectos!$L$2:$L$41)/SUMPRODUCT((Proyectos!$A$2:$A$41<>"")*(Proyectos!$H$2:$H$41<>"Cancelado")*1),"") | F7: =SUMPRODUCT((Proyectos!$H$2:$H$41<>"Cancelado")*Proyectos!$N$2:$N$41) | G7: =SUMPRODUCT((Proyectos!$H$2:$H$41<>"Cancelado")*Proyectos!$O$2:$O$41) | H7: =IFERROR(SUMPRODUCT((Proyectos!$H$2:$H$41<>"Cancelado")*Proyectos!$O$2:$O$41)/SUMPRODUCT((Proyectos!$H$2:$H$41<>"Cancelado")*Proyectos!$N$2:$N$41),"") | I7: =SUMPRODUCT((Hitos!$A$2:$A$81<>"")*(Hitos!$E$2:$E$81<>"")*(Hitos!$E$2:$E$81<TODAY())*(Hitos!$F$2:$F$81<>"Completado")*(Hitos!$F$2:$F$81<>"Cancelado")) | J7: =COUNTIF(KPIs!$O$2:$O$71,"Crítico") | BJ7: =IF(AND(Proyectos!$A7<>"",OR(Proyectos!$H7="En riesgo",Proyectos!$H7="Bloqueado",Proyectos!$AB7>0,IF(Proyectos!$V7="",FALSE,Proyectos!$V7<-0.15))),BK7,"") | BK7: =IF(AND(Proyectos!$A7<>"",OR(Proyectos!$H7="En riesgo",Proyectos!$H7="Bloqueado",Proyectos!$AB7>0,IF(Proyectos!$V7="",FALSE,Proyectos!$V7<-0.15))),N(BK6)+1,N(BK6)) | BN7: =IF(AND(Hitos!$A7<>"",OR(Hitos!$L7="Vencido",Hitos!$L7="Esta semana",Hitos!$L7="Próximos 30 días")),BO7,"") | BO7: =IF(AND(Hitos!$A7<>"",OR(Hitos!$L7="Vencido",Hitos!$L7="Esta semana",Hitos!$L7="Próximos 30 días")),N(BO6)+1,N(BO6))
BJ8: =IF(AND(Proyectos!$A8<>"",OR(Proyectos!$H8="En riesgo",Proyectos!$H8="Bloqueado",Proyectos!$AB8>0,IF(Proyectos!$V8="",FALSE,Proyectos!$V8<-0.15))),BK8,"") | BK8: =IF(AND(Proyectos!$A8<>"",OR(Proyectos!$H8="En riesgo",Proyectos!$H8="Bloqueado",Proyectos!$AB8>0,IF(Proyectos!$V8="",FALSE,Proyectos!$V8<-0.15))),N(BK7)+1,N(BK7)) | BN8: =IF(AND(Hitos!$A8<>"",OR(Hitos!$L8="Vencido",Hitos!$L8="Esta semana",Hitos!$L8="Próximos 30 días")),BO8,"") | BO8: =IF(AND(Hitos!$A8<>"",OR(Hitos!$L8="Vencido",Hitos!$L8="Esta semana",Hitos!$L8="Próximos 30 días")),N(BO7)+1,N(BO7))
BJ9: =IF(AND(Proyectos!$A9<>"",OR(Proyectos!$H9="En riesgo",Proyectos!$H9="Bloqueado",Proyectos!$AB9>0,IF(Proyectos!$V9="",FALSE,Proyectos!$V9<-0.15))),BK9,"") | BK9: =IF(AND(Proyectos!$A9<>"",OR(Proyectos!$H9="En riesgo",Proyectos!$H9="Bloqueado",Proyectos!$AB9>0,IF(Proyectos!$V9="",FALSE,Proyectos!$V9<-0.15))),N(BK8)+1,N(BK8)) | BN9: =IF(AND(Hitos!$A9<>"",OR(Hitos!$L9="Vencido",Hitos!$L9="Esta semana",Hitos!$L9="Próximos 30 días")),BO9,"") | BO9: =IF(AND(Hitos!$A9<>"",OR(Hitos!$L9="Vencido",Hitos!$L9="Esta semana",Hitos!$L9="Próximos 30 días")),N(BO8)+1,N(BO8))
B10: PORTFOLIO POR ESTADO | BJ10: =IF(AND(Proyectos!$A10<>"",OR(Proyectos!$H10="En riesgo",Proyectos!$H10="Bloqueado",Proyectos!$AB10>0,IF(Proyectos!$V10="",FALSE,Proyectos!$V10<-0.15))),BK10,"") | BK10: =IF(AND(Proyectos!$A10<>"",OR(Proyectos!$H10="En riesgo",Proyectos!$H10="Bloqueado",Proyectos!$AB10>0,IF(Proyectos!$V10="",FALSE,Proyectos!$V10<-0.15))),N(BK9)+1,N(BK9)) | BN10: =IF(AND(Hitos!$A10<>"",OR(Hitos!$L10="Vencido",Hitos!$L10="Esta semana",Hitos!$L10="Próximos 30 días")),BO10,"") | BO10: =IF(AND(Hitos!$A10<>"",OR(Hitos!$L10="Vencido",Hitos!$L10="Esta semana",Hitos!$L10="Próximos 30 días")),N(BO9)+1,N(BO9))
B11: Estado | C11: Proyectos | D11: % del total | E11: Presupuesto € | F11: Gasto € | G11: Avance medio | BJ11: =IF(AND(Proyectos!$A11<>"",OR(Proyectos!$H11="En riesgo",Proyectos!$H11="Bloqueado",Proyectos!$AB11>0,IF(Proyectos!$V11="",FALSE,Proyectos!$V11<-0.15))),BK11,"") | BK11: =IF(AND(Proyectos!$A11<>"",OR(Proyectos!$H11="En riesgo",Proyectos!$H11="Bloqueado",Proyectos!$AB11>0,IF(Proyectos!$V11="",FALSE,Proyectos!$V11<-0.15))),N(BK10)+1,N(BK10)) | BN11: =IF(AND(Hitos!$A11<>"",OR(Hitos!$L11="Vencido",Hitos!$L11="Esta semana",Hitos!$L11="Próximos 30 días")),BO11,"") | BO11: =IF(AND(Hitos!$A11<>"",OR(Hitos!$L11="Vencido",Hitos!$L11="Esta semana",Hitos!$L11="Próximos 30 días")),N(BO10)+1,N(BO10))
B12: Backlog | C12: =COUNTIF(Proyectos!$H$2:$H$41,$B12) | D12: =IFERROR($C12/SUM($C$12:$C$17),"") | E12: =SUMIF(Proyectos!$H$2:$H$41,$B12,Proyectos!$N$2:$N$41) | F12: =SUMIF(Proyectos!$H$2:$H$41,$B12,Proyectos!$O$2:$O$41) | G12: =IFERROR(AVERAGEIF(Proyectos!$H$2:$H$41,$B12,Proyectos!$L$2:$L$41),"") | BJ12: =IF(AND(Proyectos!$A12<>"",OR(Proyectos!$H12="En riesgo",Proyectos!$H12="Bloqueado",Proyectos!$AB12>0,IF(Proyectos!$V12="",FALSE,Proyectos!$V12<-0.15))),BK12,"") | BK12: =IF(AND(Proyectos!$A12<>"",OR(Proyectos!$H12="En riesgo",Proyectos!$H12="Bloqueado",Proyectos!$AB12>0,IF(Proyectos!$V12="",FALSE,Proyectos!$V12<-0.15))),N(BK11)+1,N(BK11)) | BN12: =IF(AND(Hitos!$A12<>"",OR(Hitos!$L12="Vencido",Hitos!$L12="Esta semana",Hitos!$L12="Próximos 30 días")),BO12,"") | BO12: =IF(AND(Hitos!$A12<>"",OR(Hitos!$L12="Vencido",Hitos!$L12="Esta semana",Hitos!$L12="Próximos 30 días")),N(BO11)+1,N(BO11))
B13: En curso | C13: =COUNTIF(Proyectos!$H$2:$H$41,$B13) | D13: =IFERROR($C13/SUM($C$12:$C$17),"") | E13: =SUMIF(Proyectos!$H$2:$H$41,$B13,Proyectos!$N$2:$N$41) | F13: =SUMIF(Proyectos!$H$2:$H$41,$B13,Proyectos!$O$2:$O$41) | G13: =IFERROR(AVERAGEIF(Proyectos!$H$2:$H$41,$B13,Proyectos!$L$2:$L$41),"") | BJ13: =IF(AND(Proyectos!$A13<>"",OR(Proyectos!$H13="En riesgo",Proyectos!$H13="Bloqueado",Proyectos!$AB13>0,IF(Proyectos!$V13="",FALSE,Proyectos!$V13<-0.15))),BK13,"") | BK13: =IF(AND(Proyectos!$A13<>"",OR(Proyectos!$H13="En riesgo",Proyectos!$H13="Bloqueado",Proyectos!$AB13>0,IF(Proyectos!$V13="",FALSE,Proyectos!$V13<-0.15))),N(BK12)+1,N(BK12)) | BN13: =IF(AND(Hitos!$A13<>"",OR(Hitos!$L13="Vencido",Hitos!$L13="Esta semana",Hitos!$L13="Próximos 30 días")),BO13,"") | BO13: =IF(AND(Hitos!$A13<>"",OR(Hitos!$L13="Vencido",Hitos!$L13="Esta semana",Hitos!$L13="Próximos 30 días")),N(BO12)+1,N(BO12))
B14: En riesgo | C14: =COUNTIF(Proyectos!$H$2:$H$41,$B14) | D14: =IFERROR($C14/SUM($C$12:$C$17),"") | E14: =SUMIF(Proyectos!$H$2:$H$41,$B14,Proyectos!$N$2:$N$41) | F14: =SUMIF(Proyectos!$H$2:$H$41,$B14,Proyectos!$O$2:$O$41) | G14: =IFERROR(AVERAGEIF(Proyectos!$H$2:$H$41,$B14,Proyectos!$L$2:$L$41),"") | BJ14: =IF(AND(Proyectos!$A14<>"",OR(Proyectos!$H14="En riesgo",Proyectos!$H14="Bloqueado",Proyectos!$AB14>0,IF(Proyectos!$V14="",FALSE,Proyectos!$V14<-0.15))),BK14,"") | BK14: =IF(AND(Proyectos!$A14<>"",OR(Proyectos!$H14="En riesgo",Proyectos!$H14="Bloqueado",Proyectos!$AB14>0,IF(Proyectos!$V14="",FALSE,Proyectos!$V14<-0.15))),N(BK13)+1,N(BK13)) | BN14: =IF(AND(Hitos!$A14<>"",OR(Hitos!$L14="Vencido",Hitos!$L14="Esta semana",Hitos!$L14="Próximos 30 días")),BO14,"") | BO14: =IF(AND(Hitos!$A14<>"",OR(Hitos!$L14="Vencido",Hitos!$L14="Esta semana",Hitos!$L14="Próximos 30 días")),N(BO13)+1,N(BO13))
B15: Bloqueado | C15: =COUNTIF(Proyectos!$H$2:$H$41,$B15) | D15: =IFERROR($C15/SUM($C$12:$C$17),"") | E15: =SUMIF(Proyectos!$H$2:$H$41,$B15,Proyectos!$N$2:$N$41) | F15: =SUMIF(Proyectos!$H$2:$H$41,$B15,Proyectos!$O$2:$O$41) | G15: =IFERROR(AVERAGEIF(Proyectos!$H$2:$H$41,$B15,Proyectos!$L$2:$L$41),"") | BJ15: =IF(AND(Proyectos!$A15<>"",OR(Proyectos!$H15="En riesgo",Proyectos!$H15="Bloqueado",Proyectos!$AB15>0,IF(Proyectos!$V15="",FALSE,Proyectos!$V15<-0.15))),BK15,"") | BK15: =IF(AND(Proyectos!$A15<>"",OR(Proyectos!$H15="En riesgo",Proyectos!$H15="Bloqueado",Proyectos!$AB15>0,IF(Proyectos!$V15="",FALSE,Proyectos!$V15<-0.15))),N(BK14)+1,N(BK14)) | BN15: =IF(AND(Hitos!$A15<>"",OR(Hitos!$L15="Vencido",Hitos!$L15="Esta semana",Hitos!$L15="Próximos 30 días")),BO15,"") | BO15: =IF(AND(Hitos!$A15<>"",OR(Hitos!$L15="Vencido",Hitos!$L15="Esta semana",Hitos!$L15="Próximos 30 días")),N(BO14)+1,N(BO14))
B16: Completado | C16: =COUNTIF(Proyectos!$H$2:$H$41,$B16) | D16: =IFERROR($C16/SUM($C$12:$C$17),"") | E16: =SUMIF(Proyectos!$H$2:$H$41,$B16,Proyectos!$N$2:$N$41) | F16: =SUMIF(Proyectos!$H$2:$H$41,$B16,Proyectos!$O$2:$O$41) | G16: =IFERROR(AVERAGEIF(Proyectos!$H$2:$H$41,$B16,Proyectos!$L$2:$L$41),"") | BJ16: =IF(AND(Proyectos!$A16<>"",OR(Proyectos!$H16="En riesgo",Proyectos!$H16="Bloqueado",Proyectos!$AB16>0,IF(Proyectos!$V16="",FALSE,Proyectos!$V16<-0.15))),BK16,"") | BK16: =IF(AND(Proyectos!$A16<>"",OR(Proyectos!$H16="En riesgo",Proyectos!$H16="Bloqueado",Proyectos!$AB16>0,IF(Proyectos!$V16="",FALSE,Proyectos!$V16<-0.15))),N(BK15)+1,N(BK15)) | BN16: =IF(AND(Hitos!$A16<>"",OR(Hitos!$L16="Vencido",Hitos!$L16="Esta semana",Hitos!$L16="Próximos 30 días")),BO16,"") | BO16: =IF(AND(Hitos!$A16<>"",OR(Hitos!$L16="Vencido",Hitos!$L16="Esta semana",Hitos!$L16="Próximos 30 días")),N(BO15)+1,N(BO15))
B17: Cancelado | C17: =COUNTIF(Proyectos!$H$2:$H$41,$B17) | D17: =IFERROR($C17/SUM($C$12:$C$17),"") | E17: =SUMIF(Proyectos!$H$2:$H$41,$B17,Proyectos!$N$2:$N$41) | F17: =SUMIF(Proyectos!$H$2:$H$41,$B17,Proyectos!$O$2:$O$41) | G17: =IFERROR(AVERAGEIF(Proyectos!$H$2:$H$41,$B17,Proyectos!$L$2:$L$41),"") | BJ17: =IF(AND(Proyectos!$A17<>"",OR(Proyectos!$H17="En riesgo",Proyectos!$H17="Bloqueado",Proyectos!$AB17>0,IF(Proyectos!$V17="",FALSE,Proyectos!$V17<-0.15))),BK17,"") | BK17: =IF(AND(Proyectos!$A17<>"",OR(Proyectos!$H17="En riesgo",Proyectos!$H17="Bloqueado",Proyectos!$AB17>0,IF(Proyectos!$V17="",FALSE,Proyectos!$V17<-0.15))),N(BK16)+1,N(BK16)) | BN17: =IF(AND(Hitos!$A17<>"",OR(Hitos!$L17="Vencido",Hitos!$L17="Esta semana",Hitos!$L17="Próximos 30 días")),BO17,"") | BO17: =IF(AND(Hitos!$A17<>"",OR(Hitos!$L17="Vencido",Hitos!$L17="Esta semana",Hitos!$L17="Próximos 30 días")),N(BO16)+1,N(BO16))
BJ18: =IF(AND(Proyectos!$A18<>"",OR(Proyectos!$H18="En riesgo",Proyectos!$H18="Bloqueado",Proyectos!$AB18>0,IF(Proyectos!$V18="",FALSE,Proyectos!$V18<-0.15))),BK18,"") | BK18: =IF(AND(Proyectos!$A18<>"",OR(Proyectos!$H18="En riesgo",Proyectos!$H18="Bloqueado",Proyectos!$AB18>0,IF(Proyectos!$V18="",FALSE,Proyectos!$V18<-0.15))),N(BK17)+1,N(BK17)) | BN18: =IF(AND(Hitos!$A18<>"",OR(Hitos!$L18="Vencido",Hitos!$L18="Esta semana",Hitos!$L18="Próximos 30 días")),BO18,"") | BO18: =IF(AND(Hitos!$A18<>"",OR(Hitos!$L18="Vencido",Hitos!$L18="Esta semana",Hitos!$L18="Próximos 30 días")),N(BO17)+1,N(BO17))
B19: PORTFOLIO POR DEPARTAMENTO | BJ19: =IF(AND(Proyectos!$A19<>"",OR(Proyectos!$H19="En riesgo",Proyectos!$H19="Bloqueado",Proyectos!$AB19>0,IF(Proyectos!$V19="",FALSE,Proyectos!$V19<-0.15))),BK19,"") | BK19: =IF(AND(Proyectos!$A19<>"",OR(Proyectos!$H19="En riesgo",Proyectos!$H19="Bloqueado",Proyectos!$AB19>0,IF(Proyectos!$V19="",FALSE,Proyectos!$V19<-0.15))),N(BK18)+1,N(BK18)) | BN19: =IF(AND(Hitos!$A19<>"",OR(Hitos!$L19="Vencido",Hitos!$L19="Esta semana",Hitos!$L19="Próximos 30 días")),BO19,"") | BO19: =IF(AND(Hitos!$A19<>"",OR(Hitos!$L19="Vencido",Hitos!$L19="Esta semana",Hitos!$L19="Próximos 30 días")),N(BO18)+1,N(BO18))
B20: Departamento | C20: Proyectos | D20: Activos | E20: Presupuesto € | F20: Gasto € | G20: % consumido | H20: Avance medio | I20: Hitos vencidos | J20: KPIs críticos | BJ20: =IF(AND(Proyectos!$A20<>"",OR(Proyectos!$H20="En riesgo",Proyectos!$H20="Bloqueado",Proyectos!$AB20>0,IF(Proyectos!$V20="",FALSE,Proyectos!$V20<-0.15))),BK20,"") | BK20: =IF(AND(Proyectos!$A20<>"",OR(Proyectos!$H20="En riesgo",Proyectos!$H20="Bloqueado",Proyectos!$AB20>0,IF(Proyectos!$V20="",FALSE,Proyectos!$V20<-0.15))),N(BK19)+1,N(BK19)) | BN20: =IF(AND(Hitos!$A20<>"",OR(Hitos!$L20="Vencido",Hitos!$L20="Esta semana",Hitos!$L20="Próximos 30 días")),BO20,"") | BO20: =IF(AND(Hitos!$A20<>"",OR(Hitos!$L20="Vencido",Hitos!$L20="Esta semana",Hitos!$L20="Próximos 30 días")),N(BO19)+1,N(BO19))
B21: Growth | C21: =COUNTIF(Proyectos!$C$2:$C$41,$B21) | D21: =COUNTIFS(Proyectos!$C$2:$C$41,$B21,Proyectos!$H$2:$H$41,"En curso")+COUNTIFS(Proyectos!$C$2:$C$41,$B21,Proyectos!$H$2:$H$41,"En riesgo")+COUNTIFS(Proyectos!$C$2:$C$41,$B21,Proyectos!$H$2:$H$41,"Bloqueado") | E21: =SUMIF(Proyectos!$C$2:$C$41,$B21,Proyectos!$N$2:$N$41) | F21: =SUMIF(Proyectos!$C$2:$C$41,$B21,Proyectos!$O$2:$O$41) | G21: =IFERROR(F21/E21,"") | H21: =IFERROR(AVERAGEIF(Proyectos!$C$2:$C$41,$B21,Proyectos!$L$2:$L$41),"") | I21: =SUMPRODUCT((Hitos!$I$2:$I$81=$B21)*(Hitos!$E$2:$E$81<>"")*(Hitos!$E$2:$E$81<TODAY())*(Hitos!$F$2:$F$81<>"Completado")*(Hitos!$F$2:$F$81<>"Cancelado")) | J21: =COUNTIFS(KPIs!$L$2:$L$71,$B21,KPIs!$O$2:$O$71,"Crítico") | BJ21: =IF(AND(Proyectos!$A21<>"",OR(Proyectos!$H21="En riesgo",Proyectos!$H21="Bloqueado",Proyectos!$AB21>0,IF(Proyectos!$V21="",FALSE,Proyectos!$V21<-0.15))),BK21,"") | BK21: =IF(AND(Proyectos!$A21<>"",OR(Proyectos!$H21="En riesgo",Proyectos!$H21="Bloqueado",Proyectos!$AB21>0,IF(Proyectos!$V21="",FALSE,Proyectos!$V21<-0.15))),N(BK20)+1,N(BK20)) | BN21: =IF(AND(Hitos!$A21<>"",OR(Hitos!$L21="Vencido",Hitos!$L21="Esta semana",Hitos!$L21="Próximos 30 días")),BO21,"") | BO21: =IF(AND(Hitos!$A21<>"",OR(Hitos!$L21="Vencido",Hitos!$L21="Esta semana",Hitos!$L21="Próximos 30 días")),N(BO20)+1,N(BO20))
BJ22: =IF(AND(Proyectos!$A22<>"",OR(Proyectos!$H22="En riesgo",Proyectos!$H22="Bloqueado",Proyectos!$AB22>0,IF(Proyectos!$V22="",FALSE,Proyectos!$V22<-0.15))),BK22,"") | BK22: =IF(AND(Proyectos!$A22<>"",OR(Proyectos!$H22="En riesgo",Proyectos!$H22="Bloqueado",Proyectos!$AB22>0,IF(Proyectos!$V22="",FALSE,Proyectos!$V22<-0.15))),N(BK21)+1,N(BK21)) | BN22: =IF(AND(Hitos!$A22<>"",OR(Hitos!$L22="Vencido",Hitos!$L22="Esta semana",Hitos!$L22="Próximos 30 días")),BO22,"") | BO22: =IF(AND(Hitos!$A22<>"",OR(Hitos!$L22="Vencido",Hitos!$L22="Esta semana",Hitos!$L22="Próximos 30 días")),N(BO21)+1,N(BO21))
B23: ZOOM POR SUBÁREA | BJ23: =IF(AND(Proyectos!$A23<>"",OR(Proyectos!$H23="En riesgo",Proyectos!$H23="Bloqueado",Proyectos!$AB23>0,IF(Proyectos!$V23="",FALSE,Proyectos!$V23<-0.15))),BK23,"") | BK23: =IF(AND(Proyectos!$A23<>"",OR(Proyectos!$H23="En riesgo",Proyectos!$H23="Bloqueado",Proyectos!$AB23>0,IF(Proyectos!$V23="",FALSE,Proyectos!$V23<-0.15))),N(BK22)+1,N(BK22)) | BN23: =IF(AND(Hitos!$A23<>"",OR(Hitos!$L23="Vencido",Hitos!$L23="Esta semana",Hitos!$L23="Próximos 30 días")),BO23,"") | BO23: =IF(AND(Hitos!$A23<>"",OR(Hitos!$L23="Vencido",Hitos!$L23="Esta semana",Hitos!$L23="Próximos 30 días")),N(BO22)+1,N(BO22))
B24: Departamento | C24: Subárea | D24: Proyectos | E24: Activos | F24: Presupuesto € | G24: Gasto € | H24: % consumido | I24: Avance medio | J24: Hitos vencidos | K24: KPIs críticos | BJ24: =IF(AND(Proyectos!$A24<>"",OR(Proyectos!$H24="En riesgo",Proyectos!$H24="Bloqueado",Proyectos!$AB24>0,IF(Proyectos!$V24="",FALSE,Proyectos!$V24<-0.15))),BK24,"") | BK24: =IF(AND(Proyectos!$A24<>"",OR(Proyectos!$H24="En riesgo",Proyectos!$H24="Bloqueado",Proyectos!$AB24>0,IF(Proyectos!$V24="",FALSE,Proyectos!$V24<-0.15))),N(BK23)+1,N(BK23)) | BN24: =IF(AND(Hitos!$A24<>"",OR(Hitos!$L24="Vencido",Hitos!$L24="Esta semana",Hitos!$L24="Próximos 30 días")),BO24,"") | BO24: =IF(AND(Hitos!$A24<>"",OR(Hitos!$L24="Vencido",Hitos!$L24="Esta semana",Hitos!$L24="Próximos 30 días")),N(BO23)+1,N(BO23))
B25: Growth | C25: Paid Media | D25: =COUNTIF(Proyectos!$D$2:$D$41,$C25) | E25: =COUNTIFS(Proyectos!$D$2:$D$41,$C25,Proyectos!$H$2:$H$41,"En curso")+COUNTIFS(Proyectos!$D$2:$D$41,$C25,Proyectos!$H$2:$H$41,"En riesgo")+COUNTIFS(Proyectos!$D$2:$D$41,$C25,Proyectos!$H$2:$H$41,"Bloqueado") | F25: =SUMIF(Proyectos!$D$2:$D$41,$C25,Proyectos!$N$2:$N$41) | G25: =SUMIF(Proyectos!$D$2:$D$41,$C25,Proyectos!$O$2:$O$41) | H25: =IFERROR(G25/F25,"") | I25: =IFERROR(AVERAGEIF(Proyectos!$D$2:$D$41,$C25,Proyectos!$L$2:$L$41),"") | J25: =SUMPRODUCT((Hitos!$J$2:$J$81=$C25)*(Hitos!$E$2:$E$81<>"")*(Hitos!$E$2:$E$81<TODAY())*(Hitos!$F$2:$F$81<>"Completado")*(Hitos!$F$2:$F$81<>"Cancelado")) | K25: =COUNTIFS(KPIs!$M$2:$M$71,$C25,KPIs!$O$2:$O$71,"Crítico") | BJ25: =IF(AND(Proyectos!$A25<>"",OR(Proyectos!$H25="En riesgo",Proyectos!$H25="Bloqueado",Proyectos!$AB25>0,IF(Proyectos!$V25="",FALSE,Proyectos!$V25<-0.15))),BK25,"") | BK25: =IF(AND(Proyectos!$A25<>"",OR(Proyectos!$H25="En riesgo",Proyectos!$H25="Bloqueado",Proyectos!$AB25>0,IF(Proyectos!$V25="",FALSE,Proyectos!$V25<-0.15))),N(BK24)+1,N(BK24)) | BN25: =IF(AND(Hitos!$A25<>"",OR(Hitos!$L25="Vencido",Hitos!$L25="Esta semana",Hitos!$L25="Próximos 30 días")),BO25,"") | BO25: =IF(AND(Hitos!$A25<>"",OR(Hitos!$L25="Vencido",Hitos!$L25="Esta semana",Hitos!$L25="Próximos 30 días")),N(BO24)+1,N(BO24))
B26: Growth | C26: SEO & Contenido | D26: =COUNTIF(Proyectos!$D$2:$D$41,$C26) | E26: =COUNTIFS(Proyectos!$D$2:$D$41,$C26,Proyectos!$H$2:$H$41,"En curso")+COUNTIFS(Proyectos!$D$2:$D$41,$C26,Proyectos!$H$2:$H$41,"En riesgo")+COUNTIFS(Proyectos!$D$2:$D$41,$C26,Proyectos!$H$2:$H$41,"Bloqueado") | F26: =SUMIF(Proyectos!$D$2:$D$41,$C26,Proyectos!$N$2:$N$41) | G26: =SUMIF(Proyectos!$D$2:$D$41,$C26,Proyectos!$O$2:$O$41) | H26: =IFERROR(G26/F26,"") | I26: =IFERROR(AVERAGEIF(Proyectos!$D$2:$D$41,$C26,Proyectos!$L$2:$L$41),"") | J26: =SUMPRODUCT((Hitos!$J$2:$J$81=$C26)*(Hitos!$E$2:$E$81<>"")*(Hitos!$E$2:$E$81<TODAY())*(Hitos!$F$2:$F$81<>"Completado")*(Hitos!$F$2:$F$81<>"Cancelado")) | K26: =COUNTIFS(KPIs!$M$2:$M$71,$C26,KPIs!$O$2:$O$71,"Crítico") | BJ26: =IF(AND(Proyectos!$A26<>"",OR(Proyectos!$H26="En riesgo",Proyectos!$H26="Bloqueado",Proyectos!$AB26>0,IF(Proyectos!$V26="",FALSE,Proyectos!$V26<-0.15))),BK26,"") | BK26: =IF(AND(Proyectos!$A26<>"",OR(Proyectos!$H26="En riesgo",Proyectos!$H26="Bloqueado",Proyectos!$AB26>0,IF(Proyectos!$V26="",FALSE,Proyectos!$V26<-0.15))),N(BK25)+1,N(BK25)) | BN26: =IF(AND(Hitos!$A26<>"",OR(Hitos!$L26="Vencido",Hitos!$L26="Esta semana",Hitos!$L26="Próximos 30 días")),BO26,"") | BO26: =IF(AND(Hitos!$A26<>"",OR(Hitos!$L26="Vencido",Hitos!$L26="Esta semana",Hitos!$L26="Próximos 30 días")),N(BO25)+1,N(BO25))
B27: Growth | C27: CRO & Web | D27: =COUNTIF(Proyectos!$D$2:$D$41,$C27) | E27: =COUNTIFS(Proyectos!$D$2:$D$41,$C27,Proyectos!$H$2:$H$41,"En curso")+COUNTIFS(Proyectos!$D$2:$D$41,$C27,Proyectos!$H$2:$H$41,"En riesgo")+COUNTIFS(Proyectos!$D$2:$D$41,$C27,Proyectos!$H$2:$H$41,"Bloqueado") | F27: =SUMIF(Proyectos!$D$2:$D$41,$C27,Proyectos!$N$2:$N$41) | G27: =SUMIF(Proyectos!$D$2:$D$41,$C27,Proyectos!$O$2:$O$41) | H27: =IFERROR(G27/F27,"") | I27: =IFERROR(AVERAGEIF(Proyectos!$D$2:$D$41,$C27,Proyectos!$L$2:$L$41),"") | J27: =SUMPRODUCT((Hitos!$J$2:$J$81=$C27)*(Hitos!$E$2:$E$81<>"")*(Hitos!$E$2:$E$81<TODAY())*(Hitos!$F$2:$F$81<>"Completado")*(Hitos!$F$2:$F$81<>"Cancelado")) | K27: =COUNTIFS(KPIs!$M$2:$M$71,$C27,KPIs!$O$2:$O$71,"Crítico") | BJ27: =IF(AND(Proyectos!$A27<>"",OR(Proyectos!$H27="En riesgo",Proyectos!$H27="Bloqueado",Proyectos!$AB27>0,IF(Proyectos!$V27="",FALSE,Proyectos!$V27<-0.15))),BK27,"") | BK27: =IF(AND(Proyectos!$A27<>"",OR(Proyectos!$H27="En riesgo",Proyectos!$H27="Bloqueado",Proyectos!$AB27>0,IF(Proyectos!$V27="",FALSE,Proyectos!$V27<-0.15))),N(BK26)+1,N(BK26)) | BN27: =IF(AND(Hitos!$A27<>"",OR(Hitos!$L27="Vencido",Hitos!$L27="Esta semana",Hitos!$L27="Próximos 30 días")),BO27,"") | BO27: =IF(AND(Hitos!$A27<>"",OR(Hitos!$L27="Vencido",Hitos!$L27="Esta semana",Hitos!$L27="Próximos 30 días")),N(BO26)+1,N(BO26))
B28: Growth | C28: Lifecycle & CRM | D28: =COUNTIF(Proyectos!$D$2:$D$41,$C28) | E28: =COUNTIFS(Proyectos!$D$2:$D$41,$C28,Proyectos!$H$2:$H$41,"En curso")+COUNTIFS(Proyectos!$D$2:$D$41,$C28,Proyectos!$H$2:$H$41,"En riesgo")+COUNTIFS(Proyectos!$D$2:$D$41,$C28,Proyectos!$H$2:$H$41,"Bloqueado") | F28: =SUMIF(Proyectos!$D$2:$D$41,$C28,Proyectos!$N$2:$N$41) | G28: =SUMIF(Proyectos!$D$2:$D$41,$C28,Proyectos!$O$2:$O$41) | H28: =IFERROR(G28/F28,"") | I28: =IFERROR(AVERAGEIF(Proyectos!$D$2:$D$41,$C28,Proyectos!$L$2:$L$41),"") | J28: =SUMPRODUCT((Hitos!$J$2:$J$81=$C28)*(Hitos!$E$2:$E$81<>"")*(Hitos!$E$2:$E$81<TODAY())*(Hitos!$F$2:$F$81<>"Completado")*(Hitos!$F$2:$F$81<>"Cancelado")) | K28: =COUNTIFS(KPIs!$M$2:$M$71,$C28,KPIs!$O$2:$O$71,"Crítico") | BJ28: =IF(AND(Proyectos!$A28<>"",OR(Proyectos!$H28="En riesgo",Proyectos!$H28="Bloqueado",Proyectos!$AB28>0,IF(Proyectos!$V28="",FALSE,Proyectos!$V28<-0.15))),BK28,"") | BK28: =IF(AND(Proyectos!$A28<>"",OR(Proyectos!$H28="En riesgo",Proyectos!$H28="Bloqueado",Proyectos!$AB28>0,IF(Proyectos!$V28="",FALSE,Proyectos!$V28<-0.15))),N(BK27)+1,N(BK27)) | BN28: =IF(AND(Hitos!$A28<>"",OR(Hitos!$L28="Vencido",Hitos!$L28="Esta semana",Hitos!$L28="Próximos 30 días")),BO28,"") | BO28: =IF(AND(Hitos!$A28<>"",OR(Hitos!$L28="Vencido",Hitos!$L28="Esta semana",Hitos!$L28="Próximos 30 días")),N(BO27)+1,N(BO27))
B29: Growth | C29: Partnerships & Afiliación | D29: =COUNTIF(Proyectos!$D$2:$D$41,$C29) | E29: =COUNTIFS(Proyectos!$D$2:$D$41,$C29,Proyectos!$H$2:$H$41,"En curso")+COUNTIFS(Proyectos!$D$2:$D$41,$C29,Proyectos!$H$2:$H$41,"En riesgo")+COUNTIFS(Proyectos!$D$2:$D$41,$C29,Proyectos!$H$2:$H$41,"Bloqueado") | F29: =SUMIF(Proyectos!$D$2:$D$41,$C29,Proyectos!$N$2:$N$41) | G29: =SUMIF(Proyectos!$D$2:$D$41,$C29,Proyectos!$O$2:$O$41) | H29: =IFERROR(G29/F29,"") | I29: =IFERROR(AVERAGEIF(Proyectos!$D$2:$D$41,$C29,Proyectos!$L$2:$L$41),"") | J29: =SUMPRODUCT((Hitos!$J$2:$J$81=$C29)*(Hitos!$E$2:$E$81<>"")*(Hitos!$E$2:$E$81<TODAY())*(Hitos!$F$2:$F$81<>"Completado")*(Hitos!$F$2:$F$81<>"Cancelado")) | K29: =COUNTIFS(KPIs!$M$2:$M$71,$C29,KPIs!$O$2:$O$71,"Crítico") | BJ29: =IF(AND(Proyectos!$A29<>"",OR(Proyectos!$H29="En riesgo",Proyectos!$H29="Bloqueado",Proyectos!$AB29>0,IF(Proyectos!$V29="",FALSE,Proyectos!$V29<-0.15))),BK29,"") | BK29: =IF(AND(Proyectos!$A29<>"",OR(Proyectos!$H29="En riesgo",Proyectos!$H29="Bloqueado",Proyectos!$AB29>0,IF(Proyectos!$V29="",FALSE,Proyectos!$V29<-0.15))),N(BK28)+1,N(BK28)) | BN29: =IF(AND(Hitos!$A29<>"",OR(Hitos!$L29="Vencido",Hitos!$L29="Esta semana",Hitos!$L29="Próximos 30 días")),BO29,"") | BO29: =IF(AND(Hitos!$A29<>"",OR(Hitos!$L29="Vencido",Hitos!$L29="Esta semana",Hitos!$L29="Próximos 30 días")),N(BO28)+1,N(BO28))
B30: Growth | C30: Brand & Social | D30: =COUNTIF(Proyectos!$D$2:$D$41,$C30) | E30: =COUNTIFS(Proyectos!$D$2:$D$41,$C30,Proyectos!$H$2:$H$41,"En curso")+COUNTIFS(Proyectos!$D$2:$D$41,$C30,Proyectos!$H$2:$H$41,"En riesgo")+COUNTIFS(Proyectos!$D$2:$D$41,$C30,Proyectos!$H$2:$H$41,"Bloqueado") | F30: =SUMIF(Proyectos!$D$2:$D$41,$C30,Proyectos!$N$2:$N$41) | G30: =SUMIF(Proyectos!$D$2:$D$41,$C30,Proyectos!$O$2:$O$41) | H30: =IFERROR(G30/F30,"") | I30: =IFERROR(AVERAGEIF(Proyectos!$D$2:$D$41,$C30,Proyectos!$L$2:$L$41),"") | J30: =SUMPRODUCT((Hitos!$J$2:$J$81=$C30)*(Hitos!$E$2:$E$81<>"")*(Hitos!$E$2:$E$81<TODAY())*(Hitos!$F$2:$F$81<>"Completado")*(Hitos!$F$2:$F$81<>"Cancelado")) | K30: =COUNTIFS(KPIs!$M$2:$M$71,$C30,KPIs!$O$2:$O$71,"Crítico") | BJ30: =IF(AND(Proyectos!$A30<>"",OR(Proyectos!$H30="En riesgo",Proyectos!$H30="Bloqueado",Proyectos!$AB30>0,IF(Proyectos!$V30="",FALSE,Proyectos!$V30<-0.15))),BK30,"") | BK30: =IF(AND(Proyectos!$A30<>"",OR(Proyectos!$H30="En riesgo",Proyectos!$H30="Bloqueado",Proyectos!$AB30>0,IF(Proyectos!$V30="",FALSE,Proyectos!$V30<-0.15))),N(BK29)+1,N(BK29)) | BN30: =IF(AND(Hitos!$A30<>"",OR(Hitos!$L30="Vencido",Hitos!$L30="Esta semana",Hitos!$L30="Próximos 30 días")),BO30,"") | BO30: =IF(AND(Hitos!$A30<>"",OR(Hitos!$L30="Vencido",Hitos!$L30="Esta semana",Hitos!$L30="Próximos 30 días")),N(BO29)+1,N(BO29))
B31: Growth | C31: Data & Analytics | D31: =COUNTIF(Proyectos!$D$2:$D$41,$C31) | E31: =COUNTIFS(Proyectos!$D$2:$D$41,$C31,Proyectos!$H$2:$H$41,"En curso")+COUNTIFS(Proyectos!$D$2:$D$41,$C31,Proyectos!$H$2:$H$41,"En riesgo")+COUNTIFS(Proyectos!$D$2:$D$41,$C31,Proyectos!$H$2:$H$41,"Bloqueado") | F31: =SUMIF(Proyectos!$D$2:$D$41,$C31,Proyectos!$N$2:$N$41) | G31: =SUMIF(Proyectos!$D$2:$D$41,$C31,Proyectos!$O$2:$O$41) | H31: =IFERROR(G31/F31,"") | I31: =IFERROR(AVERAGEIF(Proyectos!$D$2:$D$41,$C31,Proyectos!$L$2:$L$41),"") | J31: =SUMPRODUCT((Hitos!$J$2:$J$81=$C31)*(Hitos!$E$2:$E$81<>"")*(Hitos!$E$2:$E$81<TODAY())*(Hitos!$F$2:$F$81<>"Completado")*(Hitos!$F$2:$F$81<>"Cancelado")) | K31: =COUNTIFS(KPIs!$M$2:$M$71,$C31,KPIs!$O$2:$O$71,"Crítico") | BJ31: =IF(AND(Proyectos!$A31<>"",OR(Proyectos!$H31="En riesgo",Proyectos!$H31="Bloqueado",Proyectos!$AB31>0,IF(Proyectos!$V31="",FALSE,Proyectos!$V31<-0.15))),BK31,"") | BK31: =IF(AND(Proyectos!$A31<>"",OR(Proyectos!$H31="En riesgo",Proyectos!$H31="Bloqueado",Proyectos!$AB31>0,IF(Proyectos!$V31="",FALSE,Proyectos!$V31<-0.15))),N(BK30)+1,N(BK30)) | BN31: =IF(AND(Hitos!$A31<>"",OR(Hitos!$L31="Vencido",Hitos!$L31="Esta semana",Hitos!$L31="Próximos 30 días")),BO31,"") | BO31: =IF(AND(Hitos!$A31<>"",OR(Hitos!$L31="Vencido",Hitos!$L31="Esta semana",Hitos!$L31="Próximos 30 días")),N(BO30)+1,N(BO30))
BJ32: =IF(AND(Proyectos!$A32<>"",OR(Proyectos!$H32="En riesgo",Proyectos!$H32="Bloqueado",Proyectos!$AB32>0,IF(Proyectos!$V32="",FALSE,Proyectos!$V32<-0.15))),BK32,"") | BK32: =IF(AND(Proyectos!$A32<>"",OR(Proyectos!$H32="En riesgo",Proyectos!$H32="Bloqueado",Proyectos!$AB32>0,IF(Proyectos!$V32="",FALSE,Proyectos!$V32<-0.15))),N(BK31)+1,N(BK31)) | BN32: =IF(AND(Hitos!$A32<>"",OR(Hitos!$L32="Vencido",Hitos!$L32="Esta semana",Hitos!$L32="Próximos 30 días")),BO32,"") | BO32: =IF(AND(Hitos!$A32<>"",OR(Hitos!$L32="Vencido",Hitos!$L32="Esta semana",Hitos!$L32="Próximos 30 días")),N(BO31)+1,N(BO31))
B33: PROYECTOS QUE REQUIEREN ATENCIÓN | F33: En riesgo · bloqueados · con hitos vencidos · desviados >15pp | BJ33: =IF(AND(Proyectos!$A33<>"",OR(Proyectos!$H33="En riesgo",Proyectos!$H33="Bloqueado",Proyectos!$AB33>0,IF(Proyectos!$V33="",FALSE,Proyectos!$V33<-0.15))),BK33,"") | BK33: =IF(AND(Proyectos!$A33<>"",OR(Proyectos!$H33="En riesgo",Proyectos!$H33="Bloqueado",Proyectos!$AB33>0,IF(Proyectos!$V33="",FALSE,Proyectos!$V33<-0.15))),N(BK32)+1,N(BK32)) | BN33: =IF(AND(Hitos!$A33<>"",OR(Hitos!$L33="Vencido",Hitos!$L33="Esta semana",Hitos!$L33="Próximos 30 días")),BO33,"") | BO33: =IF(AND(Hitos!$A33<>"",OR(Hitos!$L33="Vencido",Hitos!$L33="Esta semana",Hitos!$L33="Próximos 30 días")),N(BO32)+1,N(BO32))
B34: ID | C34: Proyecto | D34: Subárea | E34: Owner | F34: Prioridad | G34: Estado | H34: Fin previsto | I34: Avance | J34: Desviación | K34: Semáforo | L34: Hitos vencidos | M34: % KPIs | BJ34: =IF(AND(Proyectos!$A34<>"",OR(Proyectos!$H34="En riesgo",Proyectos!$H34="Bloqueado",Proyectos!$AB34>0,IF(Proyectos!$V34="",FALSE,Proyectos!$V34<-0.15))),BK34,"") | BK34: =IF(AND(Proyectos!$A34<>"",OR(Proyectos!$H34="En riesgo",Proyectos!$H34="Bloqueado",Proyectos!$AB34>0,IF(Proyectos!$V34="",FALSE,Proyectos!$V34<-0.15))),N(BK33)+1,N(BK33)) | BN34: =IF(AND(Hitos!$A34<>"",OR(Hitos!$L34="Vencido",Hitos!$L34="Esta semana",Hitos!$L34="Próximos 30 días")),BO34,"") | BO34: =IF(AND(Hitos!$A34<>"",OR(Hitos!$L34="Vencido",Hitos!$L34="Esta semana",Hitos!$L34="Próximos 30 días")),N(BO33)+1,N(BO33))
B35: =IF($BH35="","",INDEX(Proyectos!$A$2:$A$41,$BH35)) | C35: =IF($BH35="","",INDEX(Proyectos!$B$2:$B$41,$BH35)) | D35: =IF($BH35="","",INDEX(Proyectos!$D$2:$D$41,$BH35)) | E35: =IF($BH35="","",INDEX(Proyectos!$E$2:$E$41,$BH35)) | F35: =IF($BH35="","",INDEX(Proyectos!$G$2:$G$41,$BH35)) | G35: =IF($BH35="","",INDEX(Proyectos!$H$2:$H$41,$BH35)) | H35: =IF($BH35="","",INDEX(Proyectos!$K$2:$K$41,$BH35)) | I35: =IF($BH35="","",INDEX(Proyectos!$L$2:$L$41,$BH35)) | J35: =IF($BH35="","",INDEX(Proyectos!$V$2:$V$41,$BH35)) | K35: =IF($BH35="","",INDEX(Proyectos!$W$2:$W$41,$BH35)) | L35: =IF($BH35="","",INDEX(Proyectos!$AB$2:$AB$41,$BH35)) | M35: =IF($BH35="","",INDEX(Proyectos!$Y$2:$Y$41,$BH35)) | BH35: =IFERROR(MATCH(1,$BJ$2:$BJ$41,0),"") | BJ35: =IF(AND(Proyectos!$A35<>"",OR(Proyectos!$H35="En riesgo",Proyectos!$H35="Bloqueado",Proyectos!$AB35>0,IF(Proyectos!$V35="",FALSE,Proyectos!$V35<-0.15))),BK35,"") | BK35: =IF(AND(Proyectos!$A35<>"",OR(Proyectos!$H35="En riesgo",Proyectos!$H35="Bloqueado",Proyectos!$AB35>0,IF(Proyectos!$V35="",FALSE,Proyectos!$V35<-0.15))),N(BK34)+1,N(BK34)) | BN35: =IF(AND(Hitos!$A35<>"",OR(Hitos!$L35="Vencido",Hitos!$L35="Esta semana",Hitos!$L35="Próximos 30 días")),BO35,"") | BO35: =IF(AND(Hitos!$A35<>"",OR(Hitos!$L35="Vencido",Hitos!$L35="Esta semana",Hitos!$L35="Próximos 30 días")),N(BO34)+1,N(BO34))
B36: =IF($BH36="","",INDEX(Proyectos!$A$2:$A$41,$BH36)) | C36: =IF($BH36="","",INDEX(Proyectos!$B$2:$B$41,$BH36)) | D36: =IF($BH36="","",INDEX(Proyectos!$D$2:$D$41,$BH36)) | E36: =IF($BH36="","",INDEX(Proyectos!$E$2:$E$41,$BH36)) | F36: =IF($BH36="","",INDEX(Proyectos!$G$2:$G$41,$BH36)) | G36: =IF($BH36="","",INDEX(Proyectos!$H$2:$H$41,$BH36)) | H36: =IF($BH36="","",INDEX(Proyectos!$K$2:$K$41,$BH36)) | I36: =IF($BH36="","",INDEX(Proyectos!$L$2:$L$41,$BH36)) | J36: =IF($BH36="","",INDEX(Proyectos!$V$2:$V$41,$BH36)) | K36: =IF($BH36="","",INDEX(Proyectos!$W$2:$W$41,$BH36)) | L36: =IF($BH36="","",INDEX(Proyectos!$AB$2:$AB$41,$BH36)) | M36: =IF($BH36="","",INDEX(Proyectos!$Y$2:$Y$41,$BH36)) | BH36: =IFERROR(MATCH(2,$BJ$2:$BJ$41,0),"") | BJ36: =IF(AND(Proyectos!$A36<>"",OR(Proyectos!$H36="En riesgo",Proyectos!$H36="Bloqueado",Proyectos!$AB36>0,IF(Proyectos!$V36="",FALSE,Proyectos!$V36<-0.15))),BK36,"") | BK36: =IF(AND(Proyectos!$A36<>"",OR(Proyectos!$H36="En riesgo",Proyectos!$H36="Bloqueado",Proyectos!$AB36>0,IF(Proyectos!$V36="",FALSE,Proyectos!$V36<-0.15))),N(BK35)+1,N(BK35)) | BN36: =IF(AND(Hitos!$A36<>"",OR(Hitos!$L36="Vencido",Hitos!$L36="Esta semana",Hitos!$L36="Próximos 30 días")),BO36,"") | BO36: =IF(AND(Hitos!$A36<>"",OR(Hitos!$L36="Vencido",Hitos!$L36="Esta semana",Hitos!$L36="Próximos 30 días")),N(BO35)+1,N(BO35))
B37: =IF($BH37="","",INDEX(Proyectos!$A$2:$A$41,$BH37)) | C37: =IF($BH37="","",INDEX(Proyectos!$B$2:$B$41,$BH37)) | D37: =IF($BH37="","",INDEX(Proyectos!$D$2:$D$41,$BH37)) | E37: =IF($BH37="","",INDEX(Proyectos!$E$2:$E$41,$BH37)) | F37: =IF($BH37="","",INDEX(Proyectos!$G$2:$G$41,$BH37)) | G37: =IF($BH37="","",INDEX(Proyectos!$H$2:$H$41,$BH37)) | H37: =IF($BH37="","",INDEX(Proyectos!$K$2:$K$41,$BH37)) | I37: =IF($BH37="","",INDEX(Proyectos!$L$2:$L$41,$BH37)) | J37: =IF($BH37="","",INDEX(Proyectos!$V$2:$V$41,$BH37)) | K37: =IF($BH37="","",INDEX(Proyectos!$W$2:$W$41,$BH37)) | L37: =IF($BH37="","",INDEX(Proyectos!$AB$2:$AB$41,$BH37)) | M37: =IF($BH37="","",INDEX(Proyectos!$Y$2:$Y$41,$BH37)) | BH37: =IFERROR(MATCH(3,$BJ$2:$BJ$41,0),"") | BJ37: =IF(AND(Proyectos!$A37<>"",OR(Proyectos!$H37="En riesgo",Proyectos!$H37="Bloqueado",Proyectos!$AB37>0,IF(Proyectos!$V37="",FALSE,Proyectos!$V37<-0.15))),BK37,"") | BK37: =IF(AND(Proyectos!$A37<>"",OR(Proyectos!$H37="En riesgo",Proyectos!$H37="Bloqueado",Proyectos!$AB37>0,IF(Proyectos!$V37="",FALSE,Proyectos!$V37<-0.15))),N(BK36)+1,N(BK36)) | BN37: =IF(AND(Hitos!$A37<>"",OR(Hitos!$L37="Vencido",Hitos!$L37="Esta semana",Hitos!$L37="Próximos 30 días")),BO37,"") | BO37: =IF(AND(Hitos!$A37<>"",OR(Hitos!$L37="Vencido",Hitos!$L37="Esta semana",Hitos!$L37="Próximos 30 días")),N(BO36)+1,N(BO36))
B38: =IF($BH38="","",INDEX(Proyectos!$A$2:$A$41,$BH38)) | C38: =IF($BH38="","",INDEX(Proyectos!$B$2:$B$41,$BH38)) | D38: =IF($BH38="","",INDEX(Proyectos!$D$2:$D$41,$BH38)) | E38: =IF($BH38="","",INDEX(Proyectos!$E$2:$E$41,$BH38)) | F38: =IF($BH38="","",INDEX(Proyectos!$G$2:$G$41,$BH38)) | G38: =IF($BH38="","",INDEX(Proyectos!$H$2:$H$41,$BH38)) | H38: =IF($BH38="","",INDEX(Proyectos!$K$2:$K$41,$BH38)) | I38: =IF($BH38="","",INDEX(Proyectos!$L$2:$L$41,$BH38)) | J38: =IF($BH38="","",INDEX(Proyectos!$V$2:$V$41,$BH38)) | K38: =IF($BH38="","",INDEX(Proyectos!$W$2:$W$41,$BH38)) | L38: =IF($BH38="","",INDEX(Proyectos!$AB$2:$AB$41,$BH38)) | M38: =IF($BH38="","",INDEX(Proyectos!$Y$2:$Y$41,$BH38)) | BH38: =IFERROR(MATCH(4,$BJ$2:$BJ$41,0),"") | BJ38: =IF(AND(Proyectos!$A38<>"",OR(Proyectos!$H38="En riesgo",Proyectos!$H38="Bloqueado",Proyectos!$AB38>0,IF(Proyectos!$V38="",FALSE,Proyectos!$V38<-0.15))),BK38,"") | BK38: =IF(AND(Proyectos!$A38<>"",OR(Proyectos!$H38="En riesgo",Proyectos!$H38="Bloqueado",Proyectos!$AB38>0,IF(Proyectos!$V38="",FALSE,Proyectos!$V38<-0.15))),N(BK37)+1,N(BK37)) | BN38: =IF(AND(Hitos!$A38<>"",OR(Hitos!$L38="Vencido",Hitos!$L38="Esta semana",Hitos!$L38="Próximos 30 días")),BO38,"") | BO38: =IF(AND(Hitos!$A38<>"",OR(Hitos!$L38="Vencido",Hitos!$L38="Esta semana",Hitos!$L38="Próximos 30 días")),N(BO37)+1,N(BO37))
B39: =IF($BH39="","",INDEX(Proyectos!$A$2:$A$41,$BH39)) | C39: =IF($BH39="","",INDEX(Proyectos!$B$2:$B$41,$BH39)) | D39: =IF($BH39="","",INDEX(Proyectos!$D$2:$D$41,$BH39)) | E39: =IF($BH39="","",INDEX(Proyectos!$E$2:$E$41,$BH39)) | F39: =IF($BH39="","",INDEX(Proyectos!$G$2:$G$41,$BH39)) | G39: =IF($BH39="","",INDEX(Proyectos!$H$2:$H$41,$BH39)) | H39: =IF($BH39="","",INDEX(Proyectos!$K$2:$K$41,$BH39)) | I39: =IF($BH39="","",INDEX(Proyectos!$L$2:$L$41,$BH39)) | J39: =IF($BH39="","",INDEX(Proyectos!$V$2:$V$41,$BH39)) | K39: =IF($BH39="","",INDEX(Proyectos!$W$2:$W$41,$BH39)) | L39: =IF($BH39="","",INDEX(Proyectos!$AB$2:$AB$41,$BH39)) | M39: =IF($BH39="","",INDEX(Proyectos!$Y$2:$Y$41,$BH39)) | BH39: =IFERROR(MATCH(5,$BJ$2:$BJ$41,0),"") | BJ39: =IF(AND(Proyectos!$A39<>"",OR(Proyectos!$H39="En riesgo",Proyectos!$H39="Bloqueado",Proyectos!$AB39>0,IF(Proyectos!$V39="",FALSE,Proyectos!$V39<-0.15))),BK39,"") | BK39: =IF(AND(Proyectos!$A39<>"",OR(Proyectos!$H39="En riesgo",Proyectos!$H39="Bloqueado",Proyectos!$AB39>0,IF(Proyectos!$V39="",FALSE,Proyectos!$V39<-0.15))),N(BK38)+1,N(BK38)) | BN39: =IF(AND(Hitos!$A39<>"",OR(Hitos!$L39="Vencido",Hitos!$L39="Esta semana",Hitos!$L39="Próximos 30 días")),BO39,"") | BO39: =IF(AND(Hitos!$A39<>"",OR(Hitos!$L39="Vencido",Hitos!$L39="Esta semana",Hitos!$L39="Próximos 30 días")),N(BO38)+1,N(BO38))
B40: =IF($BH40="","",INDEX(Proyectos!$A$2:$A$41,$BH40)) | C40: =IF($BH40="","",INDEX(Proyectos!$B$2:$B$41,$BH40)) | D40: =IF($BH40="","",INDEX(Proyectos!$D$2:$D$41,$BH40)) | E40: =IF($BH40="","",INDEX(Proyectos!$E$2:$E$41,$BH40)) | F40: =IF($BH40="","",INDEX(Proyectos!$G$2:$G$41,$BH40)) | G40: =IF($BH40="","",INDEX(Proyectos!$H$2:$H$41,$BH40)) | H40: =IF($BH40="","",INDEX(Proyectos!$K$2:$K$41,$BH40)) | I40: =IF($BH40="","",INDEX(Proyectos!$L$2:$L$41,$BH40)) | J40: =IF($BH40="","",INDEX(Proyectos!$V$2:$V$41,$BH40)) | K40: =IF($BH40="","",INDEX(Proyectos!$W$2:$W$41,$BH40)) | L40: =IF($BH40="","",INDEX(Proyectos!$AB$2:$AB$41,$BH40)) | M40: =IF($BH40="","",INDEX(Proyectos!$Y$2:$Y$41,$BH40)) | BH40: =IFERROR(MATCH(6,$BJ$2:$BJ$41,0),"") | BJ40: =IF(AND(Proyectos!$A40<>"",OR(Proyectos!$H40="En riesgo",Proyectos!$H40="Bloqueado",Proyectos!$AB40>0,IF(Proyectos!$V40="",FALSE,Proyectos!$V40<-0.15))),BK40,"") | BK40: =IF(AND(Proyectos!$A40<>"",OR(Proyectos!$H40="En riesgo",Proyectos!$H40="Bloqueado",Proyectos!$AB40>0,IF(Proyectos!$V40="",FALSE,Proyectos!$V40<-0.15))),N(BK39)+1,N(BK39)) | BN40: =IF(AND(Hitos!$A40<>"",OR(Hitos!$L40="Vencido",Hitos!$L40="Esta semana",Hitos!$L40="Próximos 30 días")),BO40,"") | BO40: =IF(AND(Hitos!$A40<>"",OR(Hitos!$L40="Vencido",Hitos!$L40="Esta semana",Hitos!$L40="Próximos 30 días")),N(BO39)+1,N(BO39))
B41: =IF($BH41="","",INDEX(Proyectos!$A$2:$A$41,$BH41)) | C41: =IF($BH41="","",INDEX(Proyectos!$B$2:$B$41,$BH41)) | D41: =IF($BH41="","",INDEX(Proyectos!$D$2:$D$41,$BH41)) | E41: =IF($BH41="","",INDEX(Proyectos!$E$2:$E$41,$BH41)) | F41: =IF($BH41="","",INDEX(Proyectos!$G$2:$G$41,$BH41)) | G41: =IF($BH41="","",INDEX(Proyectos!$H$2:$H$41,$BH41)) | H41: =IF($BH41="","",INDEX(Proyectos!$K$2:$K$41,$BH41)) | I41: =IF($BH41="","",INDEX(Proyectos!$L$2:$L$41,$BH41)) | J41: =IF($BH41="","",INDEX(Proyectos!$V$2:$V$41,$BH41)) | K41: =IF($BH41="","",INDEX(Proyectos!$W$2:$W$41,$BH41)) | L41: =IF($BH41="","",INDEX(Proyectos!$AB$2:$AB$41,$BH41)) | M41: =IF($BH41="","",INDEX(Proyectos!$Y$2:$Y$41,$BH41)) | BH41: =IFERROR(MATCH(7,$BJ$2:$BJ$41,0),"") | BJ41: =IF(AND(Proyectos!$A41<>"",OR(Proyectos!$H41="En riesgo",Proyectos!$H41="Bloqueado",Proyectos!$AB41>0,IF(Proyectos!$V41="",FALSE,Proyectos!$V41<-0.15))),BK41,"") | BK41: =IF(AND(Proyectos!$A41<>"",OR(Proyectos!$H41="En riesgo",Proyectos!$H41="Bloqueado",Proyectos!$AB41>0,IF(Proyectos!$V41="",FALSE,Proyectos!$V41<-0.15))),N(BK40)+1,N(BK40)) | BN41: =IF(AND(Hitos!$A41<>"",OR(Hitos!$L41="Vencido",Hitos!$L41="Esta semana",Hitos!$L41="Próximos 30 días")),BO41,"") | BO41: =IF(AND(Hitos!$A41<>"",OR(Hitos!$L41="Vencido",Hitos!$L41="Esta semana",Hitos!$L41="Próximos 30 días")),N(BO40)+1,N(BO40))
B42: =IF($BH42="","",INDEX(Proyectos!$A$2:$A$41,$BH42)) | C42: =IF($BH42="","",INDEX(Proyectos!$B$2:$B$41,$BH42)) | D42: =IF($BH42="","",INDEX(Proyectos!$D$2:$D$41,$BH42)) | E42: =IF($BH42="","",INDEX(Proyectos!$E$2:$E$41,$BH42)) | F42: =IF($BH42="","",INDEX(Proyectos!$G$2:$G$41,$BH42)) | G42: =IF($BH42="","",INDEX(Proyectos!$H$2:$H$41,$BH42)) | H42: =IF($BH42="","",INDEX(Proyectos!$K$2:$K$41,$BH42)) | I42: =IF($BH42="","",INDEX(Proyectos!$L$2:$L$41,$BH42)) | J42: =IF($BH42="","",INDEX(Proyectos!$V$2:$V$41,$BH42)) | K42: =IF($BH42="","",INDEX(Proyectos!$W$2:$W$41,$BH42)) | L42: =IF($BH42="","",INDEX(Proyectos!$AB$2:$AB$41,$BH42)) | M42: =IF($BH42="","",INDEX(Proyectos!$Y$2:$Y$41,$BH42)) | BH42: =IFERROR(MATCH(8,$BJ$2:$BJ$41,0),"") | BN42: =IF(AND(Hitos!$A42<>"",OR(Hitos!$L42="Vencido",Hitos!$L42="Esta semana",Hitos!$L42="Próximos 30 días")),BO42,"") | BO42: =IF(AND(Hitos!$A42<>"",OR(Hitos!$L42="Vencido",Hitos!$L42="Esta semana",Hitos!$L42="Próximos 30 días")),N(BO41)+1,N(BO41))
B43: =IF($BH43="","",INDEX(Proyectos!$A$2:$A$41,$BH43)) | C43: =IF($BH43="","",INDEX(Proyectos!$B$2:$B$41,$BH43)) | D43: =IF($BH43="","",INDEX(Proyectos!$D$2:$D$41,$BH43)) | E43: =IF($BH43="","",INDEX(Proyectos!$E$2:$E$41,$BH43)) | F43: =IF($BH43="","",INDEX(Proyectos!$G$2:$G$41,$BH43)) | G43: =IF($BH43="","",INDEX(Proyectos!$H$2:$H$41,$BH43)) | H43: =IF($BH43="","",INDEX(Proyectos!$K$2:$K$41,$BH43)) | I43: =IF($BH43="","",INDEX(Proyectos!$L$2:$L$41,$BH43)) | J43: =IF($BH43="","",INDEX(Proyectos!$V$2:$V$41,$BH43)) | K43: =IF($BH43="","",INDEX(Proyectos!$W$2:$W$41,$BH43)) | L43: =IF($BH43="","",INDEX(Proyectos!$AB$2:$AB$41,$BH43)) | M43: =IF($BH43="","",INDEX(Proyectos!$Y$2:$Y$41,$BH43)) | BH43: =IFERROR(MATCH(9,$BJ$2:$BJ$41,0),"") | BN43: =IF(AND(Hitos!$A43<>"",OR(Hitos!$L43="Vencido",Hitos!$L43="Esta semana",Hitos!$L43="Próximos 30 días")),BO43,"") | BO43: =IF(AND(Hitos!$A43<>"",OR(Hitos!$L43="Vencido",Hitos!$L43="Esta semana",Hitos!$L43="Próximos 30 días")),N(BO42)+1,N(BO42))
B44: =IF($BH44="","",INDEX(Proyectos!$A$2:$A$41,$BH44)) | C44: =IF($BH44="","",INDEX(Proyectos!$B$2:$B$41,$BH44)) | D44: =IF($BH44="","",INDEX(Proyectos!$D$2:$D$41,$BH44)) | E44: =IF($BH44="","",INDEX(Proyectos!$E$2:$E$41,$BH44)) | F44: =IF($BH44="","",INDEX(Proyectos!$G$2:$G$41,$BH44)) | G44: =IF($BH44="","",INDEX(Proyectos!$H$2:$H$41,$BH44)) | H44: =IF($BH44="","",INDEX(Proyectos!$K$2:$K$41,$BH44)) | I44: =IF($BH44="","",INDEX(Proyectos!$L$2:$L$41,$BH44)) | J44: =IF($BH44="","",INDEX(Proyectos!$V$2:$V$41,$BH44)) | K44: =IF($BH44="","",INDEX(Proyectos!$W$2:$W$41,$BH44)) | L44: =IF($BH44="","",INDEX(Proyectos!$AB$2:$AB$41,$BH44)) | M44: =IF($BH44="","",INDEX(Proyectos!$Y$2:$Y$41,$BH44)) | BH44: =IFERROR(MATCH(10,$BJ$2:$BJ$41,0),"") | BN44: =IF(AND(Hitos!$A44<>"",OR(Hitos!$L44="Vencido",Hitos!$L44="Esta semana",Hitos!$L44="Próximos 30 días")),BO44,"") | BO44: =IF(AND(Hitos!$A44<>"",OR(Hitos!$L44="Vencido",Hitos!$L44="Esta semana",Hitos!$L44="Próximos 30 días")),N(BO43)+1,N(BO43))
B45: =IF($BH45="","",INDEX(Proyectos!$A$2:$A$41,$BH45)) | C45: =IF($BH45="","",INDEX(Proyectos!$B$2:$B$41,$BH45)) | D45: =IF($BH45="","",INDEX(Proyectos!$D$2:$D$41,$BH45)) | E45: =IF($BH45="","",INDEX(Proyectos!$E$2:$E$41,$BH45)) | F45: =IF($BH45="","",INDEX(Proyectos!$G$2:$G$41,$BH45)) | G45: =IF($BH45="","",INDEX(Proyectos!$H$2:$H$41,$BH45)) | H45: =IF($BH45="","",INDEX(Proyectos!$K$2:$K$41,$BH45)) | I45: =IF($BH45="","",INDEX(Proyectos!$L$2:$L$41,$BH45)) | J45: =IF($BH45="","",INDEX(Proyectos!$V$2:$V$41,$BH45)) | K45: =IF($BH45="","",INDEX(Proyectos!$W$2:$W$41,$BH45)) | L45: =IF($BH45="","",INDEX(Proyectos!$AB$2:$AB$41,$BH45)) | M45: =IF($BH45="","",INDEX(Proyectos!$Y$2:$Y$41,$BH45)) | BH45: =IFERROR(MATCH(11,$BJ$2:$BJ$41,0),"") | BN45: =IF(AND(Hitos!$A45<>"",OR(Hitos!$L45="Vencido",Hitos!$L45="Esta semana",Hitos!$L45="Próximos 30 días")),BO45,"") | BO45: =IF(AND(Hitos!$A45<>"",OR(Hitos!$L45="Vencido",Hitos!$L45="Esta semana",Hitos!$L45="Próximos 30 días")),N(BO44)+1,N(BO44))
B46: =IF($BH46="","",INDEX(Proyectos!$A$2:$A$41,$BH46)) | C46: =IF($BH46="","",INDEX(Proyectos!$B$2:$B$41,$BH46)) | D46: =IF($BH46="","",INDEX(Proyectos!$D$2:$D$41,$BH46)) | E46: =IF($BH46="","",INDEX(Proyectos!$E$2:$E$41,$BH46)) | F46: =IF($BH46="","",INDEX(Proyectos!$G$2:$G$41,$BH46)) | G46: =IF($BH46="","",INDEX(Proyectos!$H$2:$H$41,$BH46)) | H46: =IF($BH46="","",INDEX(Proyectos!$K$2:$K$41,$BH46)) | I46: =IF($BH46="","",INDEX(Proyectos!$L$2:$L$41,$BH46)) | J46: =IF($BH46="","",INDEX(Proyectos!$V$2:$V$41,$BH46)) | K46: =IF($BH46="","",INDEX(Proyectos!$W$2:$W$41,$BH46)) | L46: =IF($BH46="","",INDEX(Proyectos!$AB$2:$AB$41,$BH46)) | M46: =IF($BH46="","",INDEX(Proyectos!$Y$2:$Y$41,$BH46)) | BH46: =IFERROR(MATCH(12,$BJ$2:$BJ$41,0),"") | BN46: =IF(AND(Hitos!$A46<>"",OR(Hitos!$L46="Vencido",Hitos!$L46="Esta semana",Hitos!$L46="Próximos 30 días")),BO46,"") | BO46: =IF(AND(Hitos!$A46<>"",OR(Hitos!$L46="Vencido",Hitos!$L46="Esta semana",Hitos!$L46="Próximos 30 días")),N(BO45)+1,N(BO45))
B47: =IF($BH47="","",INDEX(Proyectos!$A$2:$A$41,$BH47)) | C47: =IF($BH47="","",INDEX(Proyectos!$B$2:$B$41,$BH47)) | D47: =IF($BH47="","",INDEX(Proyectos!$D$2:$D$41,$BH47)) | E47: =IF($BH47="","",INDEX(Proyectos!$E$2:$E$41,$BH47)) | F47: =IF($BH47="","",INDEX(Proyectos!$G$2:$G$41,$BH47)) | G47: =IF($BH47="","",INDEX(Proyectos!$H$2:$H$41,$BH47)) | H47: =IF($BH47="","",INDEX(Proyectos!$K$2:$K$41,$BH47)) | I47: =IF($BH47="","",INDEX(Proyectos!$L$2:$L$41,$BH47)) | J47: =IF($BH47="","",INDEX(Proyectos!$V$2:$V$41,$BH47)) | K47: =IF($BH47="","",INDEX(Proyectos!$W$2:$W$41,$BH47)) | L47: =IF($BH47="","",INDEX(Proyectos!$AB$2:$AB$41,$BH47)) | M47: =IF($BH47="","",INDEX(Proyectos!$Y$2:$Y$41,$BH47)) | BH47: =IFERROR(MATCH(13,$BJ$2:$BJ$41,0),"") | BN47: =IF(AND(Hitos!$A47<>"",OR(Hitos!$L47="Vencido",Hitos!$L47="Esta semana",Hitos!$L47="Próximos 30 días")),BO47,"") | BO47: =IF(AND(Hitos!$A47<>"",OR(Hitos!$L47="Vencido",Hitos!$L47="Esta semana",Hitos!$L47="Próximos 30 días")),N(BO46)+1,N(BO46))
B48: =IF($BH48="","",INDEX(Proyectos!$A$2:$A$41,$BH48)) | C48: =IF($BH48="","",INDEX(Proyectos!$B$2:$B$41,$BH48)) | D48: =IF($BH48="","",INDEX(Proyectos!$D$2:$D$41,$BH48)) | E48: =IF($BH48="","",INDEX(Proyectos!$E$2:$E$41,$BH48)) | F48: =IF($BH48="","",INDEX(Proyectos!$G$2:$G$41,$BH48)) | G48: =IF($BH48="","",INDEX(Proyectos!$H$2:$H$41,$BH48)) | H48: =IF($BH48="","",INDEX(Proyectos!$K$2:$K$41,$BH48)) | I48: =IF($BH48="","",INDEX(Proyectos!$L$2:$L$41,$BH48)) | J48: =IF($BH48="","",INDEX(Proyectos!$V$2:$V$41,$BH48)) | K48: =IF($BH48="","",INDEX(Proyectos!$W$2:$W$41,$BH48)) | L48: =IF($BH48="","",INDEX(Proyectos!$AB$2:$AB$41,$BH48)) | M48: =IF($BH48="","",INDEX(Proyectos!$Y$2:$Y$41,$BH48)) | BH48: =IFERROR(MATCH(14,$BJ$2:$BJ$41,0),"") | BN48: =IF(AND(Hitos!$A48<>"",OR(Hitos!$L48="Vencido",Hitos!$L48="Esta semana",Hitos!$L48="Próximos 30 días")),BO48,"") | BO48: =IF(AND(Hitos!$A48<>"",OR(Hitos!$L48="Vencido",Hitos!$L48="Esta semana",Hitos!$L48="Próximos 30 días")),N(BO47)+1,N(BO47))
B49: =IF($BH49="","",INDEX(Proyectos!$A$2:$A$41,$BH49)) | C49: =IF($BH49="","",INDEX(Proyectos!$B$2:$B$41,$BH49)) | D49: =IF($BH49="","",INDEX(Proyectos!$D$2:$D$41,$BH49)) | E49: =IF($BH49="","",INDEX(Proyectos!$E$2:$E$41,$BH49)) | F49: =IF($BH49="","",INDEX(Proyectos!$G$2:$G$41,$BH49)) | G49: =IF($BH49="","",INDEX(Proyectos!$H$2:$H$41,$BH49)) | H49: =IF($BH49="","",INDEX(Proyectos!$K$2:$K$41,$BH49)) | I49: =IF($BH49="","",INDEX(Proyectos!$L$2:$L$41,$BH49)) | J49: =IF($BH49="","",INDEX(Proyectos!$V$2:$V$41,$BH49)) | K49: =IF($BH49="","",INDEX(Proyectos!$W$2:$W$41,$BH49)) | L49: =IF($BH49="","",INDEX(Proyectos!$AB$2:$AB$41,$BH49)) | M49: =IF($BH49="","",INDEX(Proyectos!$Y$2:$Y$41,$BH49)) | BH49: =IFERROR(MATCH(15,$BJ$2:$BJ$41,0),"") | BN49: =IF(AND(Hitos!$A49<>"",OR(Hitos!$L49="Vencido",Hitos!$L49="Esta semana",Hitos!$L49="Próximos 30 días")),BO49,"") | BO49: =IF(AND(Hitos!$A49<>"",OR(Hitos!$L49="Vencido",Hitos!$L49="Esta semana",Hitos!$L49="Próximos 30 días")),N(BO48)+1,N(BO48))
B50: =IF($BH50="","",INDEX(Proyectos!$A$2:$A$41,$BH50)) | C50: =IF($BH50="","",INDEX(Proyectos!$B$2:$B$41,$BH50)) | D50: =IF($BH50="","",INDEX(Proyectos!$D$2:$D$41,$BH50)) | E50: =IF($BH50="","",INDEX(Proyectos!$E$2:$E$41,$BH50)) | F50: =IF($BH50="","",INDEX(Proyectos!$G$2:$G$41,$BH50)) | G50: =IF($BH50="","",INDEX(Proyectos!$H$2:$H$41,$BH50)) | H50: =IF($BH50="","",INDEX(Proyectos!$K$2:$K$41,$BH50)) | I50: =IF($BH50="","",INDEX(Proyectos!$L$2:$L$41,$BH50)) | J50: =IF($BH50="","",INDEX(Proyectos!$V$2:$V$41,$BH50)) | K50: =IF($BH50="","",INDEX(Proyectos!$W$2:$W$41,$BH50)) | L50: =IF($BH50="","",INDEX(Proyectos!$AB$2:$AB$41,$BH50)) | M50: =IF($BH50="","",INDEX(Proyectos!$Y$2:$Y$41,$BH50)) | BH50: =IFERROR(MATCH(16,$BJ$2:$BJ$41,0),"") | BN50: =IF(AND(Hitos!$A50<>"",OR(Hitos!$L50="Vencido",Hitos!$L50="Esta semana",Hitos!$L50="Próximos 30 días")),BO50,"") | BO50: =IF(AND(Hitos!$A50<>"",OR(Hitos!$L50="Vencido",Hitos!$L50="Esta semana",Hitos!$L50="Próximos 30 días")),N(BO49)+1,N(BO49))
B51: =IF($BH51="","",INDEX(Proyectos!$A$2:$A$41,$BH51)) | C51: =IF($BH51="","",INDEX(Proyectos!$B$2:$B$41,$BH51)) | D51: =IF($BH51="","",INDEX(Proyectos!$D$2:$D$41,$BH51)) | E51: =IF($BH51="","",INDEX(Proyectos!$E$2:$E$41,$BH51)) | F51: =IF($BH51="","",INDEX(Proyectos!$G$2:$G$41,$BH51)) | G51: =IF($BH51="","",INDEX(Proyectos!$H$2:$H$41,$BH51)) | H51: =IF($BH51="","",INDEX(Proyectos!$K$2:$K$41,$BH51)) | I51: =IF($BH51="","",INDEX(Proyectos!$L$2:$L$41,$BH51)) | J51: =IF($BH51="","",INDEX(Proyectos!$V$2:$V$41,$BH51)) | K51: =IF($BH51="","",INDEX(Proyectos!$W$2:$W$41,$BH51)) | L51: =IF($BH51="","",INDEX(Proyectos!$AB$2:$AB$41,$BH51)) | M51: =IF($BH51="","",INDEX(Proyectos!$Y$2:$Y$41,$BH51)) | BH51: =IFERROR(MATCH(17,$BJ$2:$BJ$41,0),"") | BN51: =IF(AND(Hitos!$A51<>"",OR(Hitos!$L51="Vencido",Hitos!$L51="Esta semana",Hitos!$L51="Próximos 30 días")),BO51,"") | BO51: =IF(AND(Hitos!$A51<>"",OR(Hitos!$L51="Vencido",Hitos!$L51="Esta semana",Hitos!$L51="Próximos 30 días")),N(BO50)+1,N(BO50))
B52: =IF($BH52="","",INDEX(Proyectos!$A$2:$A$41,$BH52)) | C52: =IF($BH52="","",INDEX(Proyectos!$B$2:$B$41,$BH52)) | D52: =IF($BH52="","",INDEX(Proyectos!$D$2:$D$41,$BH52)) | E52: =IF($BH52="","",INDEX(Proyectos!$E$2:$E$41,$BH52)) | F52: =IF($BH52="","",INDEX(Proyectos!$G$2:$G$41,$BH52)) | G52: =IF($BH52="","",INDEX(Proyectos!$H$2:$H$41,$BH52)) | H52: =IF($BH52="","",INDEX(Proyectos!$K$2:$K$41,$BH52)) | I52: =IF($BH52="","",INDEX(Proyectos!$L$2:$L$41,$BH52)) | J52: =IF($BH52="","",INDEX(Proyectos!$V$2:$V$41,$BH52)) | K52: =IF($BH52="","",INDEX(Proyectos!$W$2:$W$41,$BH52)) | L52: =IF($BH52="","",INDEX(Proyectos!$AB$2:$AB$41,$BH52)) | M52: =IF($BH52="","",INDEX(Proyectos!$Y$2:$Y$41,$BH52)) | BH52: =IFERROR(MATCH(18,$BJ$2:$BJ$41,0),"") | BN52: =IF(AND(Hitos!$A52<>"",OR(Hitos!$L52="Vencido",Hitos!$L52="Esta semana",Hitos!$L52="Próximos 30 días")),BO52,"") | BO52: =IF(AND(Hitos!$A52<>"",OR(Hitos!$L52="Vencido",Hitos!$L52="Esta semana",Hitos!$L52="Próximos 30 días")),N(BO51)+1,N(BO51))
B53: =IF($BH53="","",INDEX(Proyectos!$A$2:$A$41,$BH53)) | C53: =IF($BH53="","",INDEX(Proyectos!$B$2:$B$41,$BH53)) | D53: =IF($BH53="","",INDEX(Proyectos!$D$2:$D$41,$BH53)) | E53: =IF($BH53="","",INDEX(Proyectos!$E$2:$E$41,$BH53)) | F53: =IF($BH53="","",INDEX(Proyectos!$G$2:$G$41,$BH53)) | G53: =IF($BH53="","",INDEX(Proyectos!$H$2:$H$41,$BH53)) | H53: =IF($BH53="","",INDEX(Proyectos!$K$2:$K$41,$BH53)) | I53: =IF($BH53="","",INDEX(Proyectos!$L$2:$L$41,$BH53)) | J53: =IF($BH53="","",INDEX(Proyectos!$V$2:$V$41,$BH53)) | K53: =IF($BH53="","",INDEX(Proyectos!$W$2:$W$41,$BH53)) | L53: =IF($BH53="","",INDEX(Proyectos!$AB$2:$AB$41,$BH53)) | M53: =IF($BH53="","",INDEX(Proyectos!$Y$2:$Y$41,$BH53)) | BH53: =IFERROR(MATCH(19,$BJ$2:$BJ$41,0),"") | BN53: =IF(AND(Hitos!$A53<>"",OR(Hitos!$L53="Vencido",Hitos!$L53="Esta semana",Hitos!$L53="Próximos 30 días")),BO53,"") | BO53: =IF(AND(Hitos!$A53<>"",OR(Hitos!$L53="Vencido",Hitos!$L53="Esta semana",Hitos!$L53="Próximos 30 días")),N(BO52)+1,N(BO52))
B54: =IF($BH54="","",INDEX(Proyectos!$A$2:$A$41,$BH54)) | C54: =IF($BH54="","",INDEX(Proyectos!$B$2:$B$41,$BH54)) | D54: =IF($BH54="","",INDEX(Proyectos!$D$2:$D$41,$BH54)) | E54: =IF($BH54="","",INDEX(Proyectos!$E$2:$E$41,$BH54)) | F54: =IF($BH54="","",INDEX(Proyectos!$G$2:$G$41,$BH54)) | G54: =IF($BH54="","",INDEX(Proyectos!$H$2:$H$41,$BH54)) | H54: =IF($BH54="","",INDEX(Proyectos!$K$2:$K$41,$BH54)) | I54: =IF($BH54="","",INDEX(Proyectos!$L$2:$L$41,$BH54)) | J54: =IF($BH54="","",INDEX(Proyectos!$V$2:$V$41,$BH54)) | K54: =IF($BH54="","",INDEX(Proyectos!$W$2:$W$41,$BH54)) | L54: =IF($BH54="","",INDEX(Proyectos!$AB$2:$AB$41,$BH54)) | M54: =IF($BH54="","",INDEX(Proyectos!$Y$2:$Y$41,$BH54)) | BH54: =IFERROR(MATCH(20,$BJ$2:$BJ$41,0),"") | BN54: =IF(AND(Hitos!$A54<>"",OR(Hitos!$L54="Vencido",Hitos!$L54="Esta semana",Hitos!$L54="Próximos 30 días")),BO54,"") | BO54: =IF(AND(Hitos!$A54<>"",OR(Hitos!$L54="Vencido",Hitos!$L54="Esta semana",Hitos!$L54="Próximos 30 días")),N(BO53)+1,N(BO53))
BN55: =IF(AND(Hitos!$A55<>"",OR(Hitos!$L55="Vencido",Hitos!$L55="Esta semana",Hitos!$L55="Próximos 30 días")),BO55,"") | BO55: =IF(AND(Hitos!$A55<>"",OR(Hitos!$L55="Vencido",Hitos!$L55="Esta semana",Hitos!$L55="Próximos 30 días")),N(BO54)+1,N(BO54))
B56: HITOS VENCIDOS Y DE LOS PRÓXIMOS 30 DÍAS | BN56: =IF(AND(Hitos!$A56<>"",OR(Hitos!$L56="Vencido",Hitos!$L56="Esta semana",Hitos!$L56="Próximos 30 días")),BO56,"") | BO56: =IF(AND(Hitos!$A56<>"",OR(Hitos!$L56="Vencido",Hitos!$L56="Esta semana",Hitos!$L56="Próximos 30 días")),N(BO55)+1,N(BO55))
B57: Fecha objetivo | C57: Alerta | D57: Hito | E57: Proyecto | F57: Subárea | G57: Responsable | H57: Estado | BN57: =IF(AND(Hitos!$A57<>"",OR(Hitos!$L57="Vencido",Hitos!$L57="Esta semana",Hitos!$L57="Próximos 30 días")),BO57,"") | BO57: =IF(AND(Hitos!$A57<>"",OR(Hitos!$L57="Vencido",Hitos!$L57="Esta semana",Hitos!$L57="Próximos 30 días")),N(BO56)+1,N(BO56))
B58: =IF($BL58="","",INDEX(Hitos!$E$2:$E$81,$BL58)) | C58: =IF($BL58="","",INDEX(Hitos!$L$2:$L$81,$BL58)) | D58: =IF($BL58="","",INDEX(Hitos!$C$2:$C$81,$BL58)) | E58: =IF($BL58="","",INDEX(Hitos!$H$2:$H$81,$BL58)) | F58: =IF($BL58="","",INDEX(Hitos!$J$2:$J$81,$BL58)) | G58: =IF($BL58="","",INDEX(Hitos!$D$2:$D$81,$BL58)) | H58: =IF($BL58="","",INDEX(Hitos!$F$2:$F$81,$BL58)) | BL58: =IFERROR(MATCH(1,$BN$2:$BN$81,0),"") | BN58: =IF(AND(Hitos!$A58<>"",OR(Hitos!$L58="Vencido",Hitos!$L58="Esta semana",Hitos!$L58="Próximos 30 días")),BO58,"") | BO58: =IF(AND(Hitos!$A58<>"",OR(Hitos!$L58="Vencido",Hitos!$L58="Esta semana",Hitos!$L58="Próximos 30 días")),N(BO57)+1,N(BO57))
B59: =IF($BL59="","",INDEX(Hitos!$E$2:$E$81,$BL59)) | C59: =IF($BL59="","",INDEX(Hitos!$L$2:$L$81,$BL59)) | D59: =IF($BL59="","",INDEX(Hitos!$C$2:$C$81,$BL59)) | E59: =IF($BL59="","",INDEX(Hitos!$H$2:$H$81,$BL59)) | F59: =IF($BL59="","",INDEX(Hitos!$J$2:$J$81,$BL59)) | G59: =IF($BL59="","",INDEX(Hitos!$D$2:$D$81,$BL59)) | H59: =IF($BL59="","",INDEX(Hitos!$F$2:$F$81,$BL59)) | BL59: =IFERROR(MATCH(2,$BN$2:$BN$81,0),"") | BN59: =IF(AND(Hitos!$A59<>"",OR(Hitos!$L59="Vencido",Hitos!$L59="Esta semana",Hitos!$L59="Próximos 30 días")),BO59,"") | BO59: =IF(AND(Hitos!$A59<>"",OR(Hitos!$L59="Vencido",Hitos!$L59="Esta semana",Hitos!$L59="Próximos 30 días")),N(BO58)+1,N(BO58))
B60: =IF($BL60="","",INDEX(Hitos!$E$2:$E$81,$BL60)) | C60: =IF($BL60="","",INDEX(Hitos!$L$2:$L$81,$BL60)) | D60: =IF($BL60="","",INDEX(Hitos!$C$2:$C$81,$BL60)) | E60: =IF($BL60="","",INDEX(Hitos!$H$2:$H$81,$BL60)) | F60: =IF($BL60="","",INDEX(Hitos!$J$2:$J$81,$BL60)) | G60: =IF($BL60="","",INDEX(Hitos!$D$2:$D$81,$BL60)) | H60: =IF($BL60="","",INDEX(Hitos!$F$2:$F$81,$BL60)) | BL60: =IFERROR(MATCH(3,$BN$2:$BN$81,0),"") | BN60: =IF(AND(Hitos!$A60<>"",OR(Hitos!$L60="Vencido",Hitos!$L60="Esta semana",Hitos!$L60="Próximos 30 días")),BO60,"") | BO60: =IF(AND(Hitos!$A60<>"",OR(Hitos!$L60="Vencido",Hitos!$L60="Esta semana",Hitos!$L60="Próximos 30 días")),N(BO59)+1,N(BO59))
B61: =IF($BL61="","",INDEX(Hitos!$E$2:$E$81,$BL61)) | C61: =IF($BL61="","",INDEX(Hitos!$L$2:$L$81,$BL61)) | D61: =IF($BL61="","",INDEX(Hitos!$C$2:$C$81,$BL61)) | E61: =IF($BL61="","",INDEX(Hitos!$H$2:$H$81,$BL61)) | F61: =IF($BL61="","",INDEX(Hitos!$J$2:$J$81,$BL61)) | G61: =IF($BL61="","",INDEX(Hitos!$D$2:$D$81,$BL61)) | H61: =IF($BL61="","",INDEX(Hitos!$F$2:$F$81,$BL61)) | BL61: =IFERROR(MATCH(4,$BN$2:$BN$81,0),"") | BN61: =IF(AND(Hitos!$A61<>"",OR(Hitos!$L61="Vencido",Hitos!$L61="Esta semana",Hitos!$L61="Próximos 30 días")),BO61,"") | BO61: =IF(AND(Hitos!$A61<>"",OR(Hitos!$L61="Vencido",Hitos!$L61="Esta semana",Hitos!$L61="Próximos 30 días")),N(BO60)+1,N(BO60))
B62: =IF($BL62="","",INDEX(Hitos!$E$2:$E$81,$BL62)) | C62: =IF($BL62="","",INDEX(Hitos!$L$2:$L$81,$BL62)) | D62: =IF($BL62="","",INDEX(Hitos!$C$2:$C$81,$BL62)) | E62: =IF($BL62="","",INDEX(Hitos!$H$2:$H$81,$BL62)) | F62: =IF($BL62="","",INDEX(Hitos!$J$2:$J$81,$BL62)) | G62: =IF($BL62="","",INDEX(Hitos!$D$2:$D$81,$BL62)) | H62: =IF($BL62="","",INDEX(Hitos!$F$2:$F$81,$BL62)) | BL62: =IFERROR(MATCH(5,$BN$2:$BN$81,0),"") | BN62: =IF(AND(Hitos!$A62<>"",OR(Hitos!$L62="Vencido",Hitos!$L62="Esta semana",Hitos!$L62="Próximos 30 días")),BO62,"") | BO62: =IF(AND(Hitos!$A62<>"",OR(Hitos!$L62="Vencido",Hitos!$L62="Esta semana",Hitos!$L62="Próximos 30 días")),N(BO61)+1,N(BO61))
B63: =IF($BL63="","",INDEX(Hitos!$E$2:$E$81,$BL63)) | C63: =IF($BL63="","",INDEX(Hitos!$L$2:$L$81,$BL63)) | D63: =IF($BL63="","",INDEX(Hitos!$C$2:$C$81,$BL63)) | E63: =IF($BL63="","",INDEX(Hitos!$H$2:$H$81,$BL63)) | F63: =IF($BL63="","",INDEX(Hitos!$J$2:$J$81,$BL63)) | G63: =IF($BL63="","",INDEX(Hitos!$D$2:$D$81,$BL63)) | H63: =IF($BL63="","",INDEX(Hitos!$F$2:$F$81,$BL63)) | BL63: =IFERROR(MATCH(6,$BN$2:$BN$81,0),"") | BN63: =IF(AND(Hitos!$A63<>"",OR(Hitos!$L63="Vencido",Hitos!$L63="Esta semana",Hitos!$L63="Próximos 30 días")),BO63,"") | BO63: =IF(AND(Hitos!$A63<>"",OR(Hitos!$L63="Vencido",Hitos!$L63="Esta semana",Hitos!$L63="Próximos 30 días")),N(BO62)+1,N(BO62))
B64: =IF($BL64="","",INDEX(Hitos!$E$2:$E$81,$BL64)) | C64: =IF($BL64="","",INDEX(Hitos!$L$2:$L$81,$BL64)) | D64: =IF($BL64="","",INDEX(Hitos!$C$2:$C$81,$BL64)) | E64: =IF($BL64="","",INDEX(Hitos!$H$2:$H$81,$BL64)) | F64: =IF($BL64="","",INDEX(Hitos!$J$2:$J$81,$BL64)) | G64: =IF($BL64="","",INDEX(Hitos!$D$2:$D$81,$BL64)) | H64: =IF($BL64="","",INDEX(Hitos!$F$2:$F$81,$BL64)) | BL64: =IFERROR(MATCH(7,$BN$2:$BN$81,0),"") | BN64: =IF(AND(Hitos!$A64<>"",OR(Hitos!$L64="Vencido",Hitos!$L64="Esta semana",Hitos!$L64="Próximos 30 días")),BO64,"") | BO64: =IF(AND(Hitos!$A64<>"",OR(Hitos!$L64="Vencido",Hitos!$L64="Esta semana",Hitos!$L64="Próximos 30 días")),N(BO63)+1,N(BO63))
B65: =IF($BL65="","",INDEX(Hitos!$E$2:$E$81,$BL65)) | C65: =IF($BL65="","",INDEX(Hitos!$L$2:$L$81,$BL65)) | D65: =IF($BL65="","",INDEX(Hitos!$C$2:$C$81,$BL65)) | E65: =IF($BL65="","",INDEX(Hitos!$H$2:$H$81,$BL65)) | F65: =IF($BL65="","",INDEX(Hitos!$J$2:$J$81,$BL65)) | G65: =IF($BL65="","",INDEX(Hitos!$D$2:$D$81,$BL65)) | H65: =IF($BL65="","",INDEX(Hitos!$F$2:$F$81,$BL65)) | BL65: =IFERROR(MATCH(8,$BN$2:$BN$81,0),"") | BN65: =IF(AND(Hitos!$A65<>"",OR(Hitos!$L65="Vencido",Hitos!$L65="Esta semana",Hitos!$L65="Próximos 30 días")),BO65,"") | BO65: =IF(AND(Hitos!$A65<>"",OR(Hitos!$L65="Vencido",Hitos!$L65="Esta semana",Hitos!$L65="Próximos 30 días")),N(BO64)+1,N(BO64))
B66: =IF($BL66="","",INDEX(Hitos!$E$2:$E$81,$BL66)) | C66: =IF($BL66="","",INDEX(Hitos!$L$2:$L$81,$BL66)) | D66: =IF($BL66="","",INDEX(Hitos!$C$2:$C$81,$BL66)) | E66: =IF($BL66="","",INDEX(Hitos!$H$2:$H$81,$BL66)) | F66: =IF($BL66="","",INDEX(Hitos!$J$2:$J$81,$BL66)) | G66: =IF($BL66="","",INDEX(Hitos!$D$2:$D$81,$BL66)) | H66: =IF($BL66="","",INDEX(Hitos!$F$2:$F$81,$BL66)) | BL66: =IFERROR(MATCH(9,$BN$2:$BN$81,0),"") | BN66: =IF(AND(Hitos!$A66<>"",OR(Hitos!$L66="Vencido",Hitos!$L66="Esta semana",Hitos!$L66="Próximos 30 días")),BO66,"") | BO66: =IF(AND(Hitos!$A66<>"",OR(Hitos!$L66="Vencido",Hitos!$L66="Esta semana",Hitos!$L66="Próximos 30 días")),N(BO65)+1,N(BO65))
B67: =IF($BL67="","",INDEX(Hitos!$E$2:$E$81,$BL67)) | C67: =IF($BL67="","",INDEX(Hitos!$L$2:$L$81,$BL67)) | D67: =IF($BL67="","",INDEX(Hitos!$C$2:$C$81,$BL67)) | E67: =IF($BL67="","",INDEX(Hitos!$H$2:$H$81,$BL67)) | F67: =IF($BL67="","",INDEX(Hitos!$J$2:$J$81,$BL67)) | G67: =IF($BL67="","",INDEX(Hitos!$D$2:$D$81,$BL67)) | H67: =IF($BL67="","",INDEX(Hitos!$F$2:$F$81,$BL67)) | BL67: =IFERROR(MATCH(10,$BN$2:$BN$81,0),"") | BN67: =IF(AND(Hitos!$A67<>"",OR(Hitos!$L67="Vencido",Hitos!$L67="Esta semana",Hitos!$L67="Próximos 30 días")),BO67,"") | BO67: =IF(AND(Hitos!$A67<>"",OR(Hitos!$L67="Vencido",Hitos!$L67="Esta semana",Hitos!$L67="Próximos 30 días")),N(BO66)+1,N(BO66))
B68: =IF($BL68="","",INDEX(Hitos!$E$2:$E$81,$BL68)) | C68: =IF($BL68="","",INDEX(Hitos!$L$2:$L$81,$BL68)) | D68: =IF($BL68="","",INDEX(Hitos!$C$2:$C$81,$BL68)) | E68: =IF($BL68="","",INDEX(Hitos!$H$2:$H$81,$BL68)) | F68: =IF($BL68="","",INDEX(Hitos!$J$2:$J$81,$BL68)) | G68: =IF($BL68="","",INDEX(Hitos!$D$2:$D$81,$BL68)) | H68: =IF($BL68="","",INDEX(Hitos!$F$2:$F$81,$BL68)) | BL68: =IFERROR(MATCH(11,$BN$2:$BN$81,0),"") | BN68: =IF(AND(Hitos!$A68<>"",OR(Hitos!$L68="Vencido",Hitos!$L68="Esta semana",Hitos!$L68="Próximos 30 días")),BO68,"") | BO68: =IF(AND(Hitos!$A68<>"",OR(Hitos!$L68="Vencido",Hitos!$L68="Esta semana",Hitos!$L68="Próximos 30 días")),N(BO67)+1,N(BO67))
B69: =IF($BL69="","",INDEX(Hitos!$E$2:$E$81,$BL69)) | C69: =IF($BL69="","",INDEX(Hitos!$L$2:$L$81,$BL69)) | D69: =IF($BL69="","",INDEX(Hitos!$C$2:$C$81,$BL69)) | E69: =IF($BL69="","",INDEX(Hitos!$H$2:$H$81,$BL69)) | F69: =IF($BL69="","",INDEX(Hitos!$J$2:$J$81,$BL69)) | G69: =IF($BL69="","",INDEX(Hitos!$D$2:$D$81,$BL69)) | H69: =IF($BL69="","",INDEX(Hitos!$F$2:$F$81,$BL69)) | BL69: =IFERROR(MATCH(12,$BN$2:$BN$81,0),"") | BN69: =IF(AND(Hitos!$A69<>"",OR(Hitos!$L69="Vencido",Hitos!$L69="Esta semana",Hitos!$L69="Próximos 30 días")),BO69,"") | BO69: =IF(AND(Hitos!$A69<>"",OR(Hitos!$L69="Vencido",Hitos!$L69="Esta semana",Hitos!$L69="Próximos 30 días")),N(BO68)+1,N(BO68))
B70: =IF($BL70="","",INDEX(Hitos!$E$2:$E$81,$BL70)) | C70: =IF($BL70="","",INDEX(Hitos!$L$2:$L$81,$BL70)) | D70: =IF($BL70="","",INDEX(Hitos!$C$2:$C$81,$BL70)) | E70: =IF($BL70="","",INDEX(Hitos!$H$2:$H$81,$BL70)) | F70: =IF($BL70="","",INDEX(Hitos!$J$2:$J$81,$BL70)) | G70: =IF($BL70="","",INDEX(Hitos!$D$2:$D$81,$BL70)) | H70: =IF($BL70="","",INDEX(Hitos!$F$2:$F$81,$BL70)) | BL70: =IFERROR(MATCH(13,$BN$2:$BN$81,0),"") | BN70: =IF(AND(Hitos!$A70<>"",OR(Hitos!$L70="Vencido",Hitos!$L70="Esta semana",Hitos!$L70="Próximos 30 días")),BO70,"") | BO70: =IF(AND(Hitos!$A70<>"",OR(Hitos!$L70="Vencido",Hitos!$L70="Esta semana",Hitos!$L70="Próximos 30 días")),N(BO69)+1,N(BO69))
B71: =IF($BL71="","",INDEX(Hitos!$E$2:$E$81,$BL71)) | C71: =IF($BL71="","",INDEX(Hitos!$L$2:$L$81,$BL71)) | D71: =IF($BL71="","",INDEX(Hitos!$C$2:$C$81,$BL71)) | E71: =IF($BL71="","",INDEX(Hitos!$H$2:$H$81,$BL71)) | F71: =IF($BL71="","",INDEX(Hitos!$J$2:$J$81,$BL71)) | G71: =IF($BL71="","",INDEX(Hitos!$D$2:$D$81,$BL71)) | H71: =IF($BL71="","",INDEX(Hitos!$F$2:$F$81,$BL71)) | BL71: =IFERROR(MATCH(14,$BN$2:$BN$81,0),"") | BN71: =IF(AND(Hitos!$A71<>"",OR(Hitos!$L71="Vencido",Hitos!$L71="Esta semana",Hitos!$L71="Próximos 30 días")),BO71,"") | BO71: =IF(AND(Hitos!$A71<>"",OR(Hitos!$L71="Vencido",Hitos!$L71="Esta semana",Hitos!$L71="Próximos 30 días")),N(BO70)+1,N(BO70))
B72: =IF($BL72="","",INDEX(Hitos!$E$2:$E$81,$BL72)) | C72: =IF($BL72="","",INDEX(Hitos!$L$2:$L$81,$BL72)) | D72: =IF($BL72="","",INDEX(Hitos!$C$2:$C$81,$BL72)) | E72: =IF($BL72="","",INDEX(Hitos!$H$2:$H$81,$BL72)) | F72: =IF($BL72="","",INDEX(Hitos!$J$2:$J$81,$BL72)) | G72: =IF($BL72="","",INDEX(Hitos!$D$2:$D$81,$BL72)) | H72: =IF($BL72="","",INDEX(Hitos!$F$2:$F$81,$BL72)) | BL72: =IFERROR(MATCH(15,$BN$2:$BN$81,0),"") | BN72: =IF(AND(Hitos!$A72<>"",OR(Hitos!$L72="Vencido",Hitos!$L72="Esta semana",Hitos!$L72="Próximos 30 días")),BO72,"") | BO72: =IF(AND(Hitos!$A72<>"",OR(Hitos!$L72="Vencido",Hitos!$L72="Esta semana",Hitos!$L72="Próximos 30 días")),N(BO71)+1,N(BO71))
B73: =IF($BL73="","",INDEX(Hitos!$E$2:$E$81,$BL73)) | C73: =IF($BL73="","",INDEX(Hitos!$L$2:$L$81,$BL73)) | D73: =IF($BL73="","",INDEX(Hitos!$C$2:$C$81,$BL73)) | E73: =IF($BL73="","",INDEX(Hitos!$H$2:$H$81,$BL73)) | F73: =IF($BL73="","",INDEX(Hitos!$J$2:$J$81,$BL73)) | G73: =IF($BL73="","",INDEX(Hitos!$D$2:$D$81,$BL73)) | H73: =IF($BL73="","",INDEX(Hitos!$F$2:$F$81,$BL73)) | BL73: =IFERROR(MATCH(16,$BN$2:$BN$81,0),"") | BN73: =IF(AND(Hitos!$A73<>"",OR(Hitos!$L73="Vencido",Hitos!$L73="Esta semana",Hitos!$L73="Próximos 30 días")),BO73,"") | BO73: =IF(AND(Hitos!$A73<>"",OR(Hitos!$L73="Vencido",Hitos!$L73="Esta semana",Hitos!$L73="Próximos 30 días")),N(BO72)+1,N(BO72))
B74: =IF($BL74="","",INDEX(Hitos!$E$2:$E$81,$BL74)) | C74: =IF($BL74="","",INDEX(Hitos!$L$2:$L$81,$BL74)) | D74: =IF($BL74="","",INDEX(Hitos!$C$2:$C$81,$BL74)) | E74: =IF($BL74="","",INDEX(Hitos!$H$2:$H$81,$BL74)) | F74: =IF($BL74="","",INDEX(Hitos!$J$2:$J$81,$BL74)) | G74: =IF($BL74="","",INDEX(Hitos!$D$2:$D$81,$BL74)) | H74: =IF($BL74="","",INDEX(Hitos!$F$2:$F$81,$BL74)) | BL74: =IFERROR(MATCH(17,$BN$2:$BN$81,0),"") | BN74: =IF(AND(Hitos!$A74<>"",OR(Hitos!$L74="Vencido",Hitos!$L74="Esta semana",Hitos!$L74="Próximos 30 días")),BO74,"") | BO74: =IF(AND(Hitos!$A74<>"",OR(Hitos!$L74="Vencido",Hitos!$L74="Esta semana",Hitos!$L74="Próximos 30 días")),N(BO73)+1,N(BO73))
B75: =IF($BL75="","",INDEX(Hitos!$E$2:$E$81,$BL75)) | C75: =IF($BL75="","",INDEX(Hitos!$L$2:$L$81,$BL75)) | D75: =IF($BL75="","",INDEX(Hitos!$C$2:$C$81,$BL75)) | E75: =IF($BL75="","",INDEX(Hitos!$H$2:$H$81,$BL75)) | F75: =IF($BL75="","",INDEX(Hitos!$J$2:$J$81,$BL75)) | G75: =IF($BL75="","",INDEX(Hitos!$D$2:$D$81,$BL75)) | H75: =IF($BL75="","",INDEX(Hitos!$F$2:$F$81,$BL75)) | BL75: =IFERROR(MATCH(18,$BN$2:$BN$81,0),"") | BN75: =IF(AND(Hitos!$A75<>"",OR(Hitos!$L75="Vencido",Hitos!$L75="Esta semana",Hitos!$L75="Próximos 30 días")),BO75,"") | BO75: =IF(AND(Hitos!$A75<>"",OR(Hitos!$L75="Vencido",Hitos!$L75="Esta semana",Hitos!$L75="Próximos 30 días")),N(BO74)+1,N(BO74))
B76: =IF($BL76="","",INDEX(Hitos!$E$2:$E$81,$BL76)) | C76: =IF($BL76="","",INDEX(Hitos!$L$2:$L$81,$BL76)) | D76: =IF($BL76="","",INDEX(Hitos!$C$2:$C$81,$BL76)) | E76: =IF($BL76="","",INDEX(Hitos!$H$2:$H$81,$BL76)) | F76: =IF($BL76="","",INDEX(Hitos!$J$2:$J$81,$BL76)) | G76: =IF($BL76="","",INDEX(Hitos!$D$2:$D$81,$BL76)) | H76: =IF($BL76="","",INDEX(Hitos!$F$2:$F$81,$BL76)) | BL76: =IFERROR(MATCH(19,$BN$2:$BN$81,0),"") | BN76: =IF(AND(Hitos!$A76<>"",OR(Hitos!$L76="Vencido",Hitos!$L76="Esta semana",Hitos!$L76="Próximos 30 días")),BO76,"") | BO76: =IF(AND(Hitos!$A76<>"",OR(Hitos!$L76="Vencido",Hitos!$L76="Esta semana",Hitos!$L76="Próximos 30 días")),N(BO75)+1,N(BO75))
B77: =IF($BL77="","",INDEX(Hitos!$E$2:$E$81,$BL77)) | C77: =IF($BL77="","",INDEX(Hitos!$L$2:$L$81,$BL77)) | D77: =IF($BL77="","",INDEX(Hitos!$C$2:$C$81,$BL77)) | E77: =IF($BL77="","",INDEX(Hitos!$H$2:$H$81,$BL77)) | F77: =IF($BL77="","",INDEX(Hitos!$J$2:$J$81,$BL77)) | G77: =IF($BL77="","",INDEX(Hitos!$D$2:$D$81,$BL77)) | H77: =IF($BL77="","",INDEX(Hitos!$F$2:$F$81,$BL77)) | BL77: =IFERROR(MATCH(20,$BN$2:$BN$81,0),"") | BN77: =IF(AND(Hitos!$A77<>"",OR(Hitos!$L77="Vencido",Hitos!$L77="Esta semana",Hitos!$L77="Próximos 30 días")),BO77,"") | BO77: =IF(AND(Hitos!$A77<>"",OR(Hitos!$L77="Vencido",Hitos!$L77="Esta semana",Hitos!$L77="Próximos 30 días")),N(BO76)+1,N(BO76))
B78: =IF($BL78="","",INDEX(Hitos!$E$2:$E$81,$BL78)) | C78: =IF($BL78="","",INDEX(Hitos!$L$2:$L$81,$BL78)) | D78: =IF($BL78="","",INDEX(Hitos!$C$2:$C$81,$BL78)) | E78: =IF($BL78="","",INDEX(Hitos!$H$2:$H$81,$BL78)) | F78: =IF($BL78="","",INDEX(Hitos!$J$2:$J$81,$BL78)) | G78: =IF($BL78="","",INDEX(Hitos!$D$2:$D$81,$BL78)) | H78: =IF($BL78="","",INDEX(Hitos!$F$2:$F$81,$BL78)) | BL78: =IFERROR(MATCH(21,$BN$2:$BN$81,0),"") | BN78: =IF(AND(Hitos!$A78<>"",OR(Hitos!$L78="Vencido",Hitos!$L78="Esta semana",Hitos!$L78="Próximos 30 días")),BO78,"") | BO78: =IF(AND(Hitos!$A78<>"",OR(Hitos!$L78="Vencido",Hitos!$L78="Esta semana",Hitos!$L78="Próximos 30 días")),N(BO77)+1,N(BO77))
B79: =IF($BL79="","",INDEX(Hitos!$E$2:$E$81,$BL79)) | C79: =IF($BL79="","",INDEX(Hitos!$L$2:$L$81,$BL79)) | D79: =IF($BL79="","",INDEX(Hitos!$C$2:$C$81,$BL79)) | E79: =IF($BL79="","",INDEX(Hitos!$H$2:$H$81,$BL79)) | F79: =IF($BL79="","",INDEX(Hitos!$J$2:$J$81,$BL79)) | G79: =IF($BL79="","",INDEX(Hitos!$D$2:$D$81,$BL79)) | H79: =IF($BL79="","",INDEX(Hitos!$F$2:$F$81,$BL79)) | BL79: =IFERROR(MATCH(22,$BN$2:$BN$81,0),"") | BN79: =IF(AND(Hitos!$A79<>"",OR(Hitos!$L79="Vencido",Hitos!$L79="Esta semana",Hitos!$L79="Próximos 30 días")),BO79,"") | BO79: =IF(AND(Hitos!$A79<>"",OR(Hitos!$L79="Vencido",Hitos!$L79="Esta semana",Hitos!$L79="Próximos 30 días")),N(BO78)+1,N(BO78))
B80: =IF($BL80="","",INDEX(Hitos!$E$2:$E$81,$BL80)) | C80: =IF($BL80="","",INDEX(Hitos!$L$2:$L$81,$BL80)) | D80: =IF($BL80="","",INDEX(Hitos!$C$2:$C$81,$BL80)) | E80: =IF($BL80="","",INDEX(Hitos!$H$2:$H$81,$BL80)) | F80: =IF($BL80="","",INDEX(Hitos!$J$2:$J$81,$BL80)) | G80: =IF($BL80="","",INDEX(Hitos!$D$2:$D$81,$BL80)) | H80: =IF($BL80="","",INDEX(Hitos!$F$2:$F$81,$BL80)) | BL80: =IFERROR(MATCH(23,$BN$2:$BN$81,0),"") | BN80: =IF(AND(Hitos!$A80<>"",OR(Hitos!$L80="Vencido",Hitos!$L80="Esta semana",Hitos!$L80="Próximos 30 días")),BO80,"") | BO80: =IF(AND(Hitos!$A80<>"",OR(Hitos!$L80="Vencido",Hitos!$L80="Esta semana",Hitos!$L80="Próximos 30 días")),N(BO79)+1,N(BO79))
B81: =IF($BL81="","",INDEX(Hitos!$E$2:$E$81,$BL81)) | C81: =IF($BL81="","",INDEX(Hitos!$L$2:$L$81,$BL81)) | D81: =IF($BL81="","",INDEX(Hitos!$C$2:$C$81,$BL81)) | E81: =IF($BL81="","",INDEX(Hitos!$H$2:$H$81,$BL81)) | F81: =IF($BL81="","",INDEX(Hitos!$J$2:$J$81,$BL81)) | G81: =IF($BL81="","",INDEX(Hitos!$D$2:$D$81,$BL81)) | H81: =IF($BL81="","",INDEX(Hitos!$F$2:$F$81,$BL81)) | BL81: =IFERROR(MATCH(24,$BN$2:$BN$81,0),"") | BN81: =IF(AND(Hitos!$A81<>"",OR(Hitos!$L81="Vencido",Hitos!$L81="Esta semana",Hitos!$L81="Próximos 30 días")),BO81,"") | BO81: =IF(AND(Hitos!$A81<>"",OR(Hitos!$L81="Vencido",Hitos!$L81="Esta semana",Hitos!$L81="Próximos 30 días")),N(BO80)+1,N(BO80))
B82: =IF($BL82="","",INDEX(Hitos!$E$2:$E$81,$BL82)) | C82: =IF($BL82="","",INDEX(Hitos!$L$2:$L$81,$BL82)) | D82: =IF($BL82="","",INDEX(Hitos!$C$2:$C$81,$BL82)) | E82: =IF($BL82="","",INDEX(Hitos!$H$2:$H$81,$BL82)) | F82: =IF($BL82="","",INDEX(Hitos!$J$2:$J$81,$BL82)) | G82: =IF($BL82="","",INDEX(Hitos!$D$2:$D$81,$BL82)) | H82: =IF($BL82="","",INDEX(Hitos!$F$2:$F$81,$BL82)) | BL82: =IFERROR(MATCH(25,$BN$2:$BN$81,0),"")

Sheet Zoom departamento
B2: Zoom por departamento | BJ2: =IF(AND(Proyectos!$A2<>"",OR($C$5="(Todos)",Proyectos!$C2=$C$5),OR($C$6="(Todas)",Proyectos!$D2=$C$6),OR($C$7="(Todos)",Proyectos!$H2=$C$7)),BK2,"") | BK2: =IF(AND(Proyectos!$A2<>"",OR($C$5="(Todos)",Proyectos!$C2=$C$5),OR($C$6="(Todas)",Proyectos!$D2=$C$6),OR($C$7="(Todos)",Proyectos!$H2=$C$7)),N(BK1)+1,N(BK1)) | BN2: =IF(AND(KPIs!$A2<>"",OR($C$5="(Todos)",KPIs!$L2=$C$5),OR($C$6="(Todas)",KPIs!$M2=$C$6)),BO2,"") | BO2: =IF(AND(KPIs!$A2<>"",OR($C$5="(Todos)",KPIs!$L2=$C$5),OR($C$6="(Todas)",KPIs!$M2=$C$6)),N(BO1)+1,N(BO1)) | BR2: =IF(AND(Hitos!$A2<>"",OR($C$5="(Todos)",Hitos!$I2=$C$5),OR($C$6="(Todas)",Hitos!$J2=$C$6),OR(Hitos!$L2="Vencido",Hitos!$L2="Esta semana",Hitos!$L2="Próximos 30 días")),BS2,"") | BS2: =IF(AND(Hitos!$A2<>"",OR($C$5="(Todos)",Hitos!$I2=$C$5),OR($C$6="(Todas)",Hitos!$J2=$C$6),OR(Hitos!$L2="Vencido",Hitos!$L2="Esta semana",Hitos!$L2="Próximos 30 días")),N(BS1)+1,N(BS1))
B3: Elige departamento, subárea y estado en los desplegables: las tres tablas de abajo y las tarjetas se recalculan solas. | BJ3: =IF(AND(Proyectos!$A3<>"",OR($C$5="(Todos)",Proyectos!$C3=$C$5),OR($C$6="(Todas)",Proyectos!$D3=$C$6),OR($C$7="(Todos)",Proyectos!$H3=$C$7)),BK3,"") | BK3: =IF(AND(Proyectos!$A3<>"",OR($C$5="(Todos)",Proyectos!$C3=$C$5),OR($C$6="(Todas)",Proyectos!$D3=$C$6),OR($C$7="(Todos)",Proyectos!$H3=$C$7)),N(BK2)+1,N(BK2)) | BN3: =IF(AND(KPIs!$A3<>"",OR($C$5="(Todos)",KPIs!$L3=$C$5),OR($C$6="(Todas)",KPIs!$M3=$C$6)),BO3,"") | BO3: =IF(AND(KPIs!$A3<>"",OR($C$5="(Todos)",KPIs!$L3=$C$5),OR($C$6="(Todas)",KPIs!$M3=$C$6)),N(BO2)+1,N(BO2)) | BR3: =IF(AND(Hitos!$A3<>"",OR($C$5="(Todos)",Hitos!$I3=$C$5),OR($C$6="(Todas)",Hitos!$J3=$C$6),OR(Hitos!$L3="Vencido",Hitos!$L3="Esta semana",Hitos!$L3="Próximos 30 días")),BS3,"") | BS3: =IF(AND(Hitos!$A3<>"",OR($C$5="(Todos)",Hitos!$I3=$C$5),OR($C$6="(Todas)",Hitos!$J3=$C$6),OR(Hitos!$L3="Vencido",Hitos!$L3="Esta semana",Hitos!$L3="Próximos 30 días")),N(BS2)+1,N(BS2))
BJ4: =IF(AND(Proyectos!$A4<>"",OR($C$5="(Todos)",Proyectos!$C4=$C$5),OR($C$6="(Todas)",Proyectos!$D4=$C$6),OR($C$7="(Todos)",Proyectos!$H4=$C$7)),BK4,"") | BK4: =IF(AND(Proyectos!$A4<>"",OR($C$5="(Todos)",Proyectos!$C4=$C$5),OR($C$6="(Todas)",Proyectos!$D4=$C$6),OR($C$7="(Todos)",Proyectos!$H4=$C$7)),N(BK3)+1,N(BK3)) | BN4: =IF(AND(KPIs!$A4<>"",OR($C$5="(Todos)",KPIs!$L4=$C$5),OR($C$6="(Todas)",KPIs!$M4=$C$6)),BO4,"") | BO4: =IF(AND(KPIs!$A4<>"",OR($C$5="(Todos)",KPIs!$L4=$C$5),OR($C$6="(Todas)",KPIs!$M4=$C$6)),N(BO3)+1,N(BO3)) | BR4: =IF(AND(Hitos!$A4<>"",OR($C$5="(Todos)",Hitos!$I4=$C$5),OR($C$6="(Todas)",Hitos!$J4=$C$6),OR(Hitos!$L4="Vencido",Hitos!$L4="Esta semana",Hitos!$L4="Próximos 30 días")),BS4,"") | BS4: =IF(AND(Hitos!$A4<>"",OR($C$5="(Todos)",Hitos!$I4=$C$5),OR($C$6="(Todas)",Hitos!$J4=$C$6),OR(Hitos!$L4="Vencido",Hitos!$L4="Esta semana",Hitos!$L4="Próximos 30 días")),N(BS3)+1,N(BS3))
B5: Departamento | C5: (Todos) | G5: Celdas amarillas = filtros editables. El resto de la hoja es fórmula. | BJ5: =IF(AND(Proyectos!$A5<>"",OR($C$5="(Todos)",Proyectos!$C5=$C$5),OR($C$6="(Todas)",Proyectos!$D5=$C$6),OR($C$7="(Todos)",Proyectos!$H5=$C$7)),BK5,"") | BK5: =IF(AND(Proyectos!$A5<>"",OR($C$5="(Todos)",Proyectos!$C5=$C$5),OR($C$6="(Todas)",Proyectos!$D5=$C$6),OR($C$7="(Todos)",Proyectos!$H5=$C$7)),N(BK4)+1,N(BK4)) | BN5: =IF(AND(KPIs!$A5<>"",OR($C$5="(Todos)",KPIs!$L5=$C$5),OR($C$6="(Todas)",KPIs!$M5=$C$6)),BO5,"") | BO5: =IF(AND(KPIs!$A5<>"",OR($C$5="(Todos)",KPIs!$L5=$C$5),OR($C$6="(Todas)",KPIs!$M5=$C$6)),N(BO4)+1,N(BO4)) | BR5: =IF(AND(Hitos!$A5<>"",OR($C$5="(Todos)",Hitos!$I5=$C$5),OR($C$6="(Todas)",Hitos!$J5=$C$6),OR(Hitos!$L5="Vencido",Hitos!$L5="Esta semana",Hitos!$L5="Próximos 30 días")),BS5,"") | BS5: =IF(AND(Hitos!$A5<>"",OR($C$5="(Todos)",Hitos!$I5=$C$5),OR($C$6="(Todas)",Hitos!$J5=$C$6),OR(Hitos!$L5="Vencido",Hitos!$L5="Esta semana",Hitos!$L5="Próximos 30 días")),N(BS4)+1,N(BS4))
B6: Subárea | C6: (Todas) | BJ6: =IF(AND(Proyectos!$A6<>"",OR($C$5="(Todos)",Proyectos!$C6=$C$5),OR($C$6="(Todas)",Proyectos!$D6=$C$6),OR($C$7="(Todos)",Proyectos!$H6=$C$7)),BK6,"") | BK6: =IF(AND(Proyectos!$A6<>"",OR($C$5="(Todos)",Proyectos!$C6=$C$5),OR($C$6="(Todas)",Proyectos!$D6=$C$6),OR($C$7="(Todos)",Proyectos!$H6=$C$7)),N(BK5)+1,N(BK5)) | BN6: =IF(AND(KPIs!$A6<>"",OR($C$5="(Todos)",KPIs!$L6=$C$5),OR($C$6="(Todas)",KPIs!$M6=$C$6)),BO6,"") | BO6: =IF(AND(KPIs!$A6<>"",OR($C$5="(Todos)",KPIs!$L6=$C$5),OR($C$6="(Todas)",KPIs!$M6=$C$6)),N(BO5)+1,N(BO5)) | BR6: =IF(AND(Hitos!$A6<>"",OR($C$5="(Todos)",Hitos!$I6=$C$5),OR($C$6="(Todas)",Hitos!$J6=$C$6),OR(Hitos!$L6="Vencido",Hitos!$L6="Esta semana",Hitos!$L6="Próximos 30 días")),BS6,"") | BS6: =IF(AND(Hitos!$A6<>"",OR($C$5="(Todos)",Hitos!$I6=$C$5),OR($C$6="(Todas)",Hitos!$J6=$C$6),OR(Hitos!$L6="Vencido",Hitos!$L6="Esta semana",Hitos!$L6="Próximos 30 días")),N(BS5)+1,N(BS5))
B7: Estado | C7: (Todos) | BJ7: =IF(AND(Proyectos!$A7<>"",OR($C$5="(Todos)",Proyectos!$C7=$C$5),OR($C$6="(Todas)",Proyectos!$D7=$C$6),OR($C$7="(Todos)",Proyectos!$H7=$C$7)),BK7,"") | BK7: =IF(AND(Proyectos!$A7<>"",OR($C$5="(Todos)",Proyectos!$C7=$C$5),OR($C$6="(Todas)",Proyectos!$D7=$C$6),OR($C$7="(Todos)",Proyectos!$H7=$C$7)),N(BK6)+1,N(BK6)) | BN7: =IF(AND(KPIs!$A7<>"",OR($C$5="(Todos)",KPIs!$L7=$C$5),OR($C$6="(Todas)",KPIs!$M7=$C$6)),BO7,"") | BO7: =IF(AND(KPIs!$A7<>"",OR($C$5="(Todos)",KPIs!$L7=$C$5),OR($C$6="(Todas)",KPIs!$M7=$C$6)),N(BO6)+1,N(BO6)) | BR7: =IF(AND(Hitos!$A7<>"",OR($C$5="(Todos)",Hitos!$I7=$C$5),OR($C$6="(Todas)",Hitos!$J7=$C$6),OR(Hitos!$L7="Vencido",Hitos!$L7="Esta semana",Hitos!$L7="Próximos 30 días")),BS7,"") | BS7: =IF(AND(Hitos!$A7<>"",OR($C$5="(Todos)",Hitos!$I7=$C$5),OR($C$6="(Todas)",Hitos!$J7=$C$6),OR(Hitos!$L7="Vencido",Hitos!$L7="Esta semana",Hitos!$L7="Próximos 30 días")),N(BS6)+1,N(BS6))
BJ8: =IF(AND(Proyectos!$A8<>"",OR($C$5="(Todos)",Proyectos!$C8=$C$5),OR($C$6="(Todas)",Proyectos!$D8=$C$6),OR($C$7="(Todos)",Proyectos!$H8=$C$7)),BK8,"") | BK8: =IF(AND(Proyectos!$A8<>"",OR($C$5="(Todos)",Proyectos!$C8=$C$5),OR($C$6="(Todas)",Proyectos!$D8=$C$6),OR($C$7="(Todos)",Proyectos!$H8=$C$7)),N(BK7)+1,N(BK7)) | BN8: =IF(AND(KPIs!$A8<>"",OR($C$5="(Todos)",KPIs!$L8=$C$5),OR($C$6="(Todas)",KPIs!$M8=$C$6)),BO8,"") | BO8: =IF(AND(KPIs!$A8<>"",OR($C$5="(Todos)",KPIs!$L8=$C$5),OR($C$6="(Todas)",KPIs!$M8=$C$6)),N(BO7)+1,N(BO7)) | BR8: =IF(AND(Hitos!$A8<>"",OR($C$5="(Todos)",Hitos!$I8=$C$5),OR($C$6="(Todas)",Hitos!$J8=$C$6),OR(Hitos!$L8="Vencido",Hitos!$L8="Esta semana",Hitos!$L8="Próximos 30 días")),BS8,"") | BS8: =IF(AND(Hitos!$A8<>"",OR($C$5="(Todos)",Hitos!$I8=$C$5),OR($C$6="(Todas)",Hitos!$J8=$C$6),OR(Hitos!$L8="Vencido",Hitos!$L8="Esta semana",Hitos!$L8="Próximos 30 días")),N(BS7)+1,N(BS7))
B9: Proyectos en el filtro | C9: Activos | D9: En riesgo o bloqueados | E9: Avance medio | F9: Presupuesto | G9: Gasto | H9: % consumido | I9: Hitos vencidos | J9: KPIs en crítico | BJ9: =IF(AND(Proyectos!$A9<>"",OR($C$5="(Todos)",Proyectos!$C9=$C$5),OR($C$6="(Todas)",Proyectos!$D9=$C$6),OR($C$7="(Todos)",Proyectos!$H9=$C$7)),BK9,"") | BK9: =IF(AND(Proyectos!$A9<>"",OR($C$5="(Todos)",Proyectos!$C9=$C$5),OR($C$6="(Todas)",Proyectos!$D9=$C$6),OR($C$7="(Todos)",Proyectos!$H9=$C$7)),N(BK8)+1,N(BK8)) | BN9: =IF(AND(KPIs!$A9<>"",OR($C$5="(Todos)",KPIs!$L9=$C$5),OR($C$6="(Todas)",KPIs!$M9=$C$6)),BO9,"") | BO9: =IF(AND(KPIs!$A9<>"",OR($C$5="(Todos)",KPIs!$L9=$C$5),OR($C$6="(Todas)",KPIs!$M9=$C$6)),N(BO8)+1,N(BO8)) | BR9: =IF(AND(Hitos!$A9<>"",OR($C$5="(Todos)",Hitos!$I9=$C$5),OR($C$6="(Todas)",Hitos!$J9=$C$6),OR(Hitos!$L9="Vencido",Hitos!$L9="Esta semana",Hitos!$L9="Próximos 30 días")),BS9,"") | BS9: =IF(AND(Hitos!$A9<>"",OR($C$5="(Todos)",Hitos!$I9=$C$5),OR($C$6="(Todas)",Hitos!$J9=$C$6),OR(Hitos!$L9="Vencido",Hitos!$L9="Esta semana",Hitos!$L9="Próximos 30 días")),N(BS8)+1,N(BS8))
B10: =SUMPRODUCT((Proyectos!$A$2:$A$41<>"")*(($C$5="(Todos)")+(Proyectos!$C$2:$C$41=$C$5)>0)*(($C$6="(Todas)")+(Proyectos!$D$2:$D$41=$C$6)>0)*(($C$7="(Todos)")+(Proyectos!$H$2:$H$41=$C$7)>0)) | C10: =SUMPRODUCT((Proyectos!$A$2:$A$41<>"")*(($C$5="(Todos)")+(Proyectos!$C$2:$C$41=$C$5)>0)*(($C$6="(Todas)")+(Proyectos!$D$2:$D$41=$C$6)>0)*(($C$7="(Todos)")+(Proyectos!$H$2:$H$41=$C$7)>0)*(((Proyectos!$H$2:$H$41="En curso")+(Proyectos!$H$2:$H$41="En riesgo")+(Proyectos!$H$2:$H$41="Bloqueado"))>0)) | D10: =SUMPRODUCT((Proyectos!$A$2:$A$41<>"")*(($C$5="(Todos)")+(Proyectos!$C$2:$C$41=$C$5)>0)*(($C$6="(Todas)")+(Proyectos!$D$2:$D$41=$C$6)>0)*(($C$7="(Todos)")+(Proyectos!$H$2:$H$41=$C$7)>0)*(((Proyectos!$H$2:$H$41="En riesgo")+(Proyectos!$H$2:$H$41="Bloqueado"))>0)) | E10: =IFERROR(SUMPRODUCT((Proyectos!$A$2:$A$41<>"")*(($C$5="(Todos)")+(Proyectos!$C$2:$C$41=$C$5)>0)*(($C$6="(Todas)")+(Proyectos!$D$2:$D$41=$C$6)>0)*(($C$7="(Todos)")+(Proyectos!$H$2:$H$41=$C$7)>0)*Proyectos!$L$2:$L$41)/SUMPRODUCT((Proyectos!$A$2:$A$41<>"")*(($C$5="(Todos)")+(Proyectos!$C$2:$C$41=$C$5)>0)*(($C$6="(Todas)")+(Proyectos!$D$2:$D$41=$C$6)>0)*(($C$7="(Todos)")+(Proyectos!$H$2:$H$41=$C$7)>0)),"") | F10: =SUMPRODUCT((Proyectos!$A$2:$A$41<>"")*(($C$5="(Todos)")+(Proyectos!$C$2:$C$41=$C$5)>0)*(($C$6="(Todas)")+(Proyectos!$D$2:$D$41=$C$6)>0)*(($C$7="(Todos)")+(Proyectos!$H$2:$H$41=$C$7)>0)*Proyectos!$N$2:$N$41) | G10: =SUMPRODUCT((Proyectos!$A$2:$A$41<>"")*(($C$5="(Todos)")+(Proyectos!$C$2:$C$41=$C$5)>0)*(($C$6="(Todas)")+(Proyectos!$D$2:$D$41=$C$6)>0)*(($C$7="(Todos)")+(Proyectos!$H$2:$H$41=$C$7)>0)*Proyectos!$O$2:$O$41) | H10: =IFERROR(SUMPRODUCT((Proyectos!$A$2:$A$41<>"")*(($C$5="(Todos)")+(Proyectos!$C$2:$C$41=$C$5)>0)*(($C$6="(Todas)")+(Proyectos!$D$2:$D$41=$C$6)>0)*(($C$7="(Todos)")+(Proyectos!$H$2:$H$41=$C$7)>0)*Proyectos!$O$2:$O$41)/SUMPRODUCT((Proyectos!$A$2:$A$41<>"")*(($C$5="(Todos)")+(Proyectos!$C$2:$C$41=$C$5)>0)*(($C$6="(Todas)")+(Proyectos!$D$2:$D$41=$C$6)>0)*(($C$7="(Todos)")+(Proyectos!$H$2:$H$41=$C$7)>0)*Proyectos!$N$2:$N$41),"") | I10: =SUMPRODUCT((Hitos!$A$2:$A$81<>"")*(($C$5="(Todos)")+(Hitos!$I$2:$I$81=$C$5)>0)*(($C$6="(Todas)")+(Hitos!$J$2:$J$81=$C$6)>0)*(Hitos!$E$2:$E$81<>"")*(Hitos!$E$2:$E$81<TODAY())*(Hitos!$F$2:$F$81<>"Completado")*(Hitos!$F$2:$F$81<>"Cancelado")) | J10: =SUMPRODUCT((KPIs!$A$2:$A$71<>"")*(($C$5="(Todos)")+(KPIs!$L$2:$L$71=$C$5)>0)*(($C$6="(Todas)")+(KPIs!$M$2:$M$71=$C$6)>0)*(KPIs!$O$2:$O$71="Crítico")) | BJ10: =IF(AND(Proyectos!$A10<>"",OR($C$5="(Todos)",Proyectos!$C10=$C$5),OR($C$6="(Todas)",Proyectos!$D10=$C$6),OR($C$7="(Todos)",Proyectos!$H10=$C$7)),BK10,"") | BK10: =IF(AND(Proyectos!$A10<>"",OR($C$5="(Todos)",Proyectos!$C10=$C$5),OR($C$6="(Todas)",Proyectos!$D10=$C$6),OR($C$7="(Todos)",Proyectos!$H10=$C$7)),N(BK9)+1,N(BK9)) | BN10: =IF(AND(KPIs!$A10<>"",OR($C$5="(Todos)",KPIs!$L10=$C$5),OR($C$6="(Todas)",KPIs!$M10=$C$6)),BO10,"") | BO10: =IF(AND(KPIs!$A10<>"",OR($C$5="(Todos)",KPIs!$L10=$C$5),OR($C$6="(Todas)",KPIs!$M10=$C$6)),N(BO9)+1,N(BO9)) | BR10: =IF(AND(Hitos!$A10<>"",OR($C$5="(Todos)",Hitos!$I10=$C$5),OR($C$6="(Todas)",Hitos!$J10=$C$6),OR(Hitos!$L10="Vencido",Hitos!$L10="Esta semana",Hitos!$L10="Próximos 30 días")),BS10,"") | BS10: =IF(AND(Hitos!$A10<>"",OR($C$5="(Todos)",Hitos!$I10=$C$5),OR($C$6="(Todas)",Hitos!$J10=$C$6),OR(Hitos!$L10="Vencido",Hitos!$L10="Esta semana",Hitos!$L10="Próximos 30 días")),N(BS9)+1,N(BS9))
BJ11: =IF(AND(Proyectos!$A11<>"",OR($C$5="(Todos)",Proyectos!$C11=$C$5),OR($C$6="(Todas)",Proyectos!$D11=$C$6),OR($C$7="(Todos)",Proyectos!$H11=$C$7)),BK11,"") | BK11: =IF(AND(Proyectos!$A11<>"",OR($C$5="(Todos)",Proyectos!$C11=$C$5),OR($C$6="(Todas)",Proyectos!$D11=$C$6),OR($C$7="(Todos)",Proyectos!$H11=$C$7)),N(BK10)+1,N(BK10)) | BN11: =IF(AND(KPIs!$A11<>"",OR($C$5="(Todos)",KPIs!$L11=$C$5),OR($C$6="(Todas)",KPIs!$M11=$C$6)),BO11,"") | BO11: =IF(AND(KPIs!$A11<>"",OR($C$5="(Todos)",KPIs!$L11=$C$5),OR($C$6="(Todas)",KPIs!$M11=$C$6)),N(BO10)+1,N(BO10)) | BR11: =IF(AND(Hitos!$A11<>"",OR($C$5="(Todos)",Hitos!$I11=$C$5),OR($C$6="(Todas)",Hitos!$J11=$C$6),OR(Hitos!$L11="Vencido",Hitos!$L11="Esta semana",Hitos!$L11="Próximos 30 días")),BS11,"") | BS11: =IF(AND(Hitos!$A11<>"",OR($C$5="(Todos)",Hitos!$I11=$C$5),OR($C$6="(Todas)",Hitos!$J11=$C$6),OR(Hitos!$L11="Vencido",Hitos!$L11="Esta semana",Hitos!$L11="Próximos 30 días")),N(BS10)+1,N(BS10))
B12: PROYECTOS DEL FILTRO | BJ12: =IF(AND(Proyectos!$A12<>"",OR($C$5="(Todos)",Proyectos!$C12=$C$5),OR($C$6="(Todas)",Proyectos!$D12=$C$6),OR($C$7="(Todos)",Proyectos!$H12=$C$7)),BK12,"") | BK12: =IF(AND(Proyectos!$A12<>"",OR($C$5="(Todos)",Proyectos!$C12=$C$5),OR($C$6="(Todas)",Proyectos!$D12=$C$6),OR($C$7="(Todos)",Proyectos!$H12=$C$7)),N(BK11)+1,N(BK11)) | BN12: =IF(AND(KPIs!$A12<>"",OR($C$5="(Todos)",KPIs!$L12=$C$5),OR($C$6="(Todas)",KPIs!$M12=$C$6)),BO12,"") | BO12: =IF(AND(KPIs!$A12<>"",OR($C$5="(Todos)",KPIs!$L12=$C$5),OR($C$6="(Todas)",KPIs!$M12=$C$6)),N(BO11)+1,N(BO11)) | BR12: =IF(AND(Hitos!$A12<>"",OR($C$5="(Todos)",Hitos!$I12=$C$5),OR($C$6="(Todas)",Hitos!$J12=$C$6),OR(Hitos!$L12="Vencido",Hitos!$L12="Esta semana",Hitos!$L12="Próximos 30 días")),BS12,"") | BS12: =IF(AND(Hitos!$A12<>"",OR($C$5="(Todos)",Hitos!$I12=$C$5),OR($C$6="(Todas)",Hitos!$J12=$C$6),OR(Hitos!$L12="Vencido",Hitos!$L12="Esta semana",Hitos!$L12="Próximos 30 días")),N(BS11)+1,N(BS11))
B13: ID | C13: Proyecto | D13: Subárea | E13: Owner | F13: Prioridad | G13: Estado | H13: Fase | I13: Fin previsto | J13: Avance | K13: Esperado | L13: Desviación | M13: Semáforo | N13: Presupuesto € | O13: Gasto € | P13: % ppto | Q13: % KPIs | R13: Hitos vencidos | BJ13: =IF(AND(Proyectos!$A13<>"",OR($C$5="(Todos)",Proyectos!$C13=$C$5),OR($C$6="(Todas)",Proyectos!$D13=$C$6),OR($C$7="(Todos)",Proyectos!$H13=$C$7)),BK13,"") | BK13: =IF(AND(Proyectos!$A13<>"",OR($C$5="(Todos)",Proyectos!$C13=$C$5),OR($C$6="(Todas)",Proyectos!$D13=$C$6),OR($C$7="(Todos)",Proyectos!$H13=$C$7)),N(BK12)+1,N(BK12)) | BN13: =IF(AND(KPIs!$A13<>"",OR($C$5="(Todos)",KPIs!$L13=$C$5),OR($C$6="(Todas)",KPIs!$M13=$C$6)),BO13,"") | BO13: =IF(AND(KPIs!$A13<>"",OR($C$5="(Todos)",KPIs!$L13=$C$5),OR($C$6="(Todas)",KPIs!$M13=$C$6)),N(BO12)+1,N(BO12)) | BR13: =IF(AND(Hitos!$A13<>"",OR($C$5="(Todos)",Hitos!$I13=$C$5),OR($C$6="(Todas)",Hitos!$J13=$C$6),OR(Hitos!$L13="Vencido",Hitos!$L13="Esta semana",Hitos!$L13="Próximos 30 días")),BS13,"") | BS13: =IF(AND(Hitos!$A13<>"",OR($C$5="(Todos)",Hitos!$I13=$C$5),OR($C$6="(Todas)",Hitos!$J13=$C$6),OR(Hitos!$L13="Vencido",Hitos!$L13="Esta semana",Hitos!$L13="Próximos 30 días")),N(BS12)+1,N(BS12))
B14: =IF($BH14="","",INDEX(Proyectos!$A$2:$A$41,$BH14)) | C14: =IF($BH14="","",INDEX(Proyectos!$B$2:$B$41,$BH14)) | D14: =IF($BH14="","",INDEX(Proyectos!$D$2:$D$41,$BH14)) | E14: =IF($BH14="","",INDEX(Proyectos!$E$2:$E$41,$BH14)) | F14: =IF($BH14="","",INDEX(Proyectos!$G$2:$G$41,$BH14)) | G14: =IF($BH14="","",INDEX(Proyectos!$H$2:$H$41,$BH14)) | H14: =IF($BH14="","",INDEX(Proyectos!$I$2:$I$41,$BH14)) | I14: =IF($BH14="","",INDEX(Proyectos!$K$2:$K$41,$BH14)) | J14: =IF($BH14="","",INDEX(Proyectos!$L$2:$L$41,$BH14)) | K14: =IF($BH14="","",INDEX(Proyectos!$U$2:$U$41,$BH14)) | L14: =IF($BH14="","",INDEX(Proyectos!$V$2:$V$41,$BH14)) | M14: =IF($BH14="","",INDEX(Proyectos!$W$2:$W$41,$BH14)) | N14: =IF($BH14="","",INDEX(Proyectos!$N$2:$N$41,$BH14)) | O14: =IF($BH14="","",INDEX(Proyectos!$O$2:$O$41,$BH14)) | P14: =IF($BH14="","",INDEX(Proyectos!$S$2:$S$41,$BH14)) | Q14: =IF($BH14="","",INDEX(Proyectos!$Y$2:$Y$41,$BH14)) | R14: =IF($BH14="","",INDEX(Proyectos!$AB$2:$AB$41,$BH14)) | BH14: =IFERROR(MATCH(1,$BJ$2:$BJ$41,0),"") | BJ14: =IF(AND(Proyectos!$A14<>"",OR($C$5="(Todos)",Proyectos!$C14=$C$5),OR($C$6="(Todas)",Proyectos!$D14=$C$6),OR($C$7="(Todos)",Proyectos!$H14=$C$7)),BK14,"") | BK14: =IF(AND(Proyectos!$A14<>"",OR($C$5="(Todos)",Proyectos!$C14=$C$5),OR($C$6="(Todas)",Proyectos!$D14=$C$6),OR($C$7="(Todos)",Proyectos!$H14=$C$7)),N(BK13)+1,N(BK13)) | BN14: =IF(AND(KPIs!$A14<>"",OR($C$5="(Todos)",KPIs!$L14=$C$5),OR($C$6="(Todas)",KPIs!$M14=$C$6)),BO14,"") | BO14: =IF(AND(KPIs!$A14<>"",OR($C$5="(Todos)",KPIs!$L14=$C$5),OR($C$6="(Todas)",KPIs!$M14=$C$6)),N(BO13)+1,N(BO13)) | BR14: =IF(AND(Hitos!$A14<>"",OR($C$5="(Todos)",Hitos!$I14=$C$5),OR($C$6="(Todas)",Hitos!$J14=$C$6),OR(Hitos!$L14="Vencido",Hitos!$L14="Esta semana",Hitos!$L14="Próximos 30 días")),BS14,"") | BS14: =IF(AND(Hitos!$A14<>"",OR($C$5="(Todos)",Hitos!$I14=$C$5),OR($C$6="(Todas)",Hitos!$J14=$C$6),OR(Hitos!$L14="Vencido",Hitos!$L14="Esta semana",Hitos!$L14="Próximos 30 días")),N(BS13)+1,N(BS13))
B15: =IF($BH15="","",INDEX(Proyectos!$A$2:$A$41,$BH15)) | C15: =IF($BH15="","",INDEX(Proyectos!$B$2:$B$41,$BH15)) | D15: =IF($BH15="","",INDEX(Proyectos!$D$2:$D$41,$BH15)) | E15: =IF($BH15="","",INDEX(Proyectos!$E$2:$E$41,$BH15)) | F15: =IF($BH15="","",INDEX(Proyectos!$G$2:$G$41,$BH15)) | G15: =IF($BH15="","",INDEX(Proyectos!$H$2:$H$41,$BH15)) | H15: =IF($BH15="","",INDEX(Proyectos!$I$2:$I$41,$BH15)) | I15: =IF($BH15="","",INDEX(Proyectos!$K$2:$K$41,$BH15)) | J15: =IF($BH15="","",INDEX(Proyectos!$L$2:$L$41,$BH15)) | K15: =IF($BH15="","",INDEX(Proyectos!$U$2:$U$41,$BH15)) | L15: =IF($BH15="","",INDEX(Proyectos!$V$2:$V$41,$BH15)) | M15: =IF($BH15="","",INDEX(Proyectos!$W$2:$W$41,$BH15)) | N15: =IF($BH15="","",INDEX(Proyectos!$N$2:$N$41,$BH15)) | O15: =IF($BH15="","",INDEX(Proyectos!$O$2:$O$41,$BH15)) | P15: =IF($BH15="","",INDEX(Proyectos!$S$2:$S$41,$BH15)) | Q15: =IF($BH15="","",INDEX(Proyectos!$Y$2:$Y$41,$BH15)) | R15: =IF($BH15="","",INDEX(Proyectos!$AB$2:$AB$41,$BH15)) | BH15: =IFERROR(MATCH(2,$BJ$2:$BJ$41,0),"") | BJ15: =IF(AND(Proyectos!$A15<>"",OR($C$5="(Todos)",Proyectos!$C15=$C$5),OR($C$6="(Todas)",Proyectos!$D15=$C$6),OR($C$7="(Todos)",Proyectos!$H15=$C$7)),BK15,"") | BK15: =IF(AND(Proyectos!$A15<>"",OR($C$5="(Todos)",Proyectos!$C15=$C$5),OR($C$6="(Todas)",Proyectos!$D15=$C$6),OR($C$7="(Todos)",Proyectos!$H15=$C$7)),N(BK14)+1,N(BK14)) | BN15: =IF(AND(KPIs!$A15<>"",OR($C$5="(Todos)",KPIs!$L15=$C$5),OR($C$6="(Todas)",KPIs!$M15=$C$6)),BO15,"") | BO15: =IF(AND(KPIs!$A15<>"",OR($C$5="(Todos)",KPIs!$L15=$C$5),OR($C$6="(Todas)",KPIs!$M15=$C$6)),N(BO14)+1,N(BO14)) | BR15: =IF(AND(Hitos!$A15<>"",OR($C$5="(Todos)",Hitos!$I15=$C$5),OR($C$6="(Todas)",Hitos!$J15=$C$6),OR(Hitos!$L15="Vencido",Hitos!$L15="Esta semana",Hitos!$L15="Próximos 30 días")),BS15,"") | BS15: =IF(AND(Hitos!$A15<>"",OR($C$5="(Todos)",Hitos!$I15=$C$5),OR($C$6="(Todas)",Hitos!$J15=$C$6),OR(Hitos!$L15="Vencido",Hitos!$L15="Esta semana",Hitos!$L15="Próximos 30 días")),N(BS14)+1,N(BS14))
B16: =IF($BH16="","",INDEX(Proyectos!$A$2:$A$41,$BH16)) | C16: =IF($BH16="","",INDEX(Proyectos!$B$2:$B$41,$BH16)) | D16: =IF($BH16="","",INDEX(Proyectos!$D$2:$D$41,$BH16)) | E16: =IF($BH16="","",INDEX(Proyectos!$E$2:$E$41,$BH16)) | F16: =IF($BH16="","",INDEX(Proyectos!$G$2:$G$41,$BH16)) | G16: =IF($BH16="","",INDEX(Proyectos!$H$2:$H$41,$BH16)) | H16: =IF($BH16="","",INDEX(Proyectos!$I$2:$I$41,$BH16)) | I16: =IF($BH16="","",INDEX(Proyectos!$K$2:$K$41,$BH16)) | J16: =IF($BH16="","",INDEX(Proyectos!$L$2:$L$41,$BH16)) | K16: =IF($BH16="","",INDEX(Proyectos!$U$2:$U$41,$BH16)) | L16: =IF($BH16="","",INDEX(Proyectos!$V$2:$V$41,$BH16)) | M16: =IF($BH16="","",INDEX(Proyectos!$W$2:$W$41,$BH16)) | N16: =IF($BH16="","",INDEX(Proyectos!$N$2:$N$41,$BH16)) | O16: =IF($BH16="","",INDEX(Proyectos!$O$2:$O$41,$BH16)) | P16: =IF($BH16="","",INDEX(Proyectos!$S$2:$S$41,$BH16)) | Q16: =IF($BH16="","",INDEX(Proyectos!$Y$2:$Y$41,$BH16)) | R16: =IF($BH16="","",INDEX(Proyectos!$AB$2:$AB$41,$BH16)) | BH16: =IFERROR(MATCH(3,$BJ$2:$BJ$41,0),"") | BJ16: =IF(AND(Proyectos!$A16<>"",OR($C$5="(Todos)",Proyectos!$C16=$C$5),OR($C$6="(Todas)",Proyectos!$D16=$C$6),OR($C$7="(Todos)",Proyectos!$H16=$C$7)),BK16,"") | BK16: =IF(AND(Proyectos!$A16<>"",OR($C$5="(Todos)",Proyectos!$C16=$C$5),OR($C$6="(Todas)",Proyectos!$D16=$C$6),OR($C$7="(Todos)",Proyectos!$H16=$C$7)),N(BK15)+1,N(BK15)) | BN16: =IF(AND(KPIs!$A16<>"",OR($C$5="(Todos)",KPIs!$L16=$C$5),OR($C$6="(Todas)",KPIs!$M16=$C$6)),BO16,"") | BO16: =IF(AND(KPIs!$A16<>"",OR($C$5="(Todos)",KPIs!$L16=$C$5),OR($C$6="(Todas)",KPIs!$M16=$C$6)),N(BO15)+1,N(BO15)) | BR16: =IF(AND(Hitos!$A16<>"",OR($C$5="(Todos)",Hitos!$I16=$C$5),OR($C$6="(Todas)",Hitos!$J16=$C$6),OR(Hitos!$L16="Vencido",Hitos!$L16="Esta semana",Hitos!$L16="Próximos 30 días")),BS16,"") | BS16: =IF(AND(Hitos!$A16<>"",OR($C$5="(Todos)",Hitos!$I16=$C$5),OR($C$6="(Todas)",Hitos!$J16=$C$6),OR(Hitos!$L16="Vencido",Hitos!$L16="Esta semana",Hitos!$L16="Próximos 30 días")),N(BS15)+1,N(BS15))
B17: =IF($BH17="","",INDEX(Proyectos!$A$2:$A$41,$BH17)) | C17: =IF($BH17="","",INDEX(Proyectos!$B$2:$B$41,$BH17)) | D17: =IF($BH17="","",INDEX(Proyectos!$D$2:$D$41,$BH17)) | E17: =IF($BH17="","",INDEX(Proyectos!$E$2:$E$41,$BH17)) | F17: =IF($BH17="","",INDEX(Proyectos!$G$2:$G$41,$BH17)) | G17: =IF($BH17="","",INDEX(Proyectos!$H$2:$H$41,$BH17)) | H17: =IF($BH17="","",INDEX(Proyectos!$I$2:$I$41,$BH17)) | I17: =IF($BH17="","",INDEX(Proyectos!$K$2:$K$41,$BH17)) | J17: =IF($BH17="","",INDEX(Proyectos!$L$2:$L$41,$BH17)) | K17: =IF($BH17="","",INDEX(Proyectos!$U$2:$U$41,$BH17)) | L17: =IF($BH17="","",INDEX(Proyectos!$V$2:$V$41,$BH17)) | M17: =IF($BH17="","",INDEX(Proyectos!$W$2:$W$41,$BH17)) | N17: =IF($BH17="","",INDEX(Proyectos!$N$2:$N$41,$BH17)) | O17: =IF($BH17="","",INDEX(Proyectos!$O$2:$O$41,$BH17)) | P17: =IF($BH17="","",INDEX(Proyectos!$S$2:$S$41,$BH17)) | Q17: =IF($BH17="","",INDEX(Proyectos!$Y$2:$Y$41,$BH17)) | R17: =IF($BH17="","",INDEX(Proyectos!$AB$2:$AB$41,$BH17)) | BH17: =IFERROR(MATCH(4,$BJ$2:$BJ$41,0),"") | BJ17: =IF(AND(Proyectos!$A17<>"",OR($C$5="(Todos)",Proyectos!$C17=$C$5),OR($C$6="(Todas)",Proyectos!$D17=$C$6),OR($C$7="(Todos)",Proyectos!$H17=$C$7)),BK17,"") | BK17: =IF(AND(Proyectos!$A17<>"",OR($C$5="(Todos)",Proyectos!$C17=$C$5),OR($C$6="(Todas)",Proyectos!$D17=$C$6),OR($C$7="(Todos)",Proyectos!$H17=$C$7)),N(BK16)+1,N(BK16)) | BN17: =IF(AND(KPIs!$A17<>"",OR($C$5="(Todos)",KPIs!$L17=$C$5),OR($C$6="(Todas)",KPIs!$M17=$C$6)),BO17,"") | BO17: =IF(AND(KPIs!$A17<>"",OR($C$5="(Todos)",KPIs!$L17=$C$5),OR($C$6="(Todas)",KPIs!$M17=$C$6)),N(BO16)+1,N(BO16)) | BR17: =IF(AND(Hitos!$A17<>"",OR($C$5="(Todos)",Hitos!$I17=$C$5),OR($C$6="(Todas)",Hitos!$J17=$C$6),OR(Hitos!$L17="Vencido",Hitos!$L17="Esta semana",Hitos!$L17="Próximos 30 días")),BS17,"") | BS17: =IF(AND(Hitos!$A17<>"",OR($C$5="(Todos)",Hitos!$I17=$C$5),OR($C$6="(Todas)",Hitos!$J17=$C$6),OR(Hitos!$L17="Vencido",Hitos!$L17="Esta semana",Hitos!$L17="Próximos 30 días")),N(BS16)+1,N(BS16))
B18: =IF($BH18="","",INDEX(Proyectos!$A$2:$A$41,$BH18)) | C18: =IF($BH18="","",INDEX(Proyectos!$B$2:$B$41,$BH18)) | D18: =IF($BH18="","",INDEX(Proyectos!$D$2:$D$41,$BH18)) | E18: =IF($BH18="","",INDEX(Proyectos!$E$2:$E$41,$BH18)) | F18: =IF($BH18="","",INDEX(Proyectos!$G$2:$G$41,$BH18)) | G18: =IF($BH18="","",INDEX(Proyectos!$H$2:$H$41,$BH18)) | H18: =IF($BH18="","",INDEX(Proyectos!$I$2:$I$41,$BH18)) | I18: =IF($BH18="","",INDEX(Proyectos!$K$2:$K$41,$BH18)) | J18: =IF($BH18="","",INDEX(Proyectos!$L$2:$L$41,$BH18)) | K18: =IF($BH18="","",INDEX(Proyectos!$U$2:$U$41,$BH18)) | L18: =IF($BH18="","",INDEX(Proyectos!$V$2:$V$41,$BH18)) | M18: =IF($BH18="","",INDEX(Proyectos!$W$2:$W$41,$BH18)) | N18: =IF($BH18="","",INDEX(Proyectos!$N$2:$N$41,$BH18)) | O18: =IF($BH18="","",INDEX(Proyectos!$O$2:$O$41,$BH18)) | P18: =IF($BH18="","",INDEX(Proyectos!$S$2:$S$41,$BH18)) | Q18: =IF($BH18="","",INDEX(Proyectos!$Y$2:$Y$41,$BH18)) | R18: =IF($BH18="","",INDEX(Proyectos!$AB$2:$AB$41,$BH18)) | BH18: =IFERROR(MATCH(5,$BJ$2:$BJ$41,0),"") | BJ18: =IF(AND(Proyectos!$A18<>"",OR($C$5="(Todos)",Proyectos!$C18=$C$5),OR($C$6="(Todas)",Proyectos!$D18=$C$6),OR($C$7="(Todos)",Proyectos!$H18=$C$7)),BK18,"") | BK18: =IF(AND(Proyectos!$A18<>"",OR($C$5="(Todos)",Proyectos!$C18=$C$5),OR($C$6="(Todas)",Proyectos!$D18=$C$6),OR($C$7="(Todos)",Proyectos!$H18=$C$7)),N(BK17)+1,N(BK17)) | BN18: =IF(AND(KPIs!$A18<>"",OR($C$5="(Todos)",KPIs!$L18=$C$5),OR($C$6="(Todas)",KPIs!$M18=$C$6)),BO18,"") | BO18: =IF(AND(KPIs!$A18<>"",OR($C$5="(Todos)",KPIs!$L18=$C$5),OR($C$6="(Todas)",KPIs!$M18=$C$6)),N(BO17)+1,N(BO17)) | BR18: =IF(AND(Hitos!$A18<>"",OR($C$5="(Todos)",Hitos!$I18=$C$5),OR($C$6="(Todas)",Hitos!$J18=$C$6),OR(Hitos!$L18="Vencido",Hitos!$L18="Esta semana",Hitos!$L18="Próximos 30 días")),BS18,"") | BS18: =IF(AND(Hitos!$A18<>"",OR($C$5="(Todos)",Hitos!$I18=$C$5),OR($C$6="(Todas)",Hitos!$J18=$C$6),OR(Hitos!$L18="Vencido",Hitos!$L18="Esta semana",Hitos!$L18="Próximos 30 días")),N(BS17)+1,N(BS17))
B19: =IF($BH19="","",INDEX(Proyectos!$A$2:$A$41,$BH19)) | C19: =IF($BH19="","",INDEX(Proyectos!$B$2:$B$41,$BH19)) | D19: =IF($BH19="","",INDEX(Proyectos!$D$2:$D$41,$BH19)) | E19: =IF($BH19="","",INDEX(Proyectos!$E$2:$E$41,$BH19)) | F19: =IF($BH19="","",INDEX(Proyectos!$G$2:$G$41,$BH19)) | G19: =IF($BH19="","",INDEX(Proyectos!$H$2:$H$41,$BH19)) | H19: =IF($BH19="","",INDEX(Proyectos!$I$2:$I$41,$BH19)) | I19: =IF($BH19="","",INDEX(Proyectos!$K$2:$K$41,$BH19)) | J19: =IF($BH19="","",INDEX(Proyectos!$L$2:$L$41,$BH19)) | K19: =IF($BH19="","",INDEX(Proyectos!$U$2:$U$41,$BH19)) | L19: =IF($BH19="","",INDEX(Proyectos!$V$2:$V$41,$BH19)) | M19: =IF($BH19="","",INDEX(Proyectos!$W$2:$W$41,$BH19)) | N19: =IF($BH19="","",INDEX(Proyectos!$N$2:$N$41,$BH19)) | O19: =IF($BH19="","",INDEX(Proyectos!$O$2:$O$41,$BH19)) | P19: =IF($BH19="","",INDEX(Proyectos!$S$2:$S$41,$BH19)) | Q19: =IF($BH19="","",INDEX(Proyectos!$Y$2:$Y$41,$BH19)) | R19: =IF($BH19="","",INDEX(Proyectos!$AB$2:$AB$41,$BH19)) | BH19: =IFERROR(MATCH(6,$BJ$2:$BJ$41,0),"") | BJ19: =IF(AND(Proyectos!$A19<>"",OR($C$5="(Todos)",Proyectos!$C19=$C$5),OR($C$6="(Todas)",Proyectos!$D19=$C$6),OR($C$7="(Todos)",Proyectos!$H19=$C$7)),BK19,"") | BK19: =IF(AND(Proyectos!$A19<>"",OR($C$5="(Todos)",Proyectos!$C19=$C$5),OR($C$6="(Todas)",Proyectos!$D19=$C$6),OR($C$7="(Todos)",Proyectos!$H19=$C$7)),N(BK18)+1,N(BK18)) | BN19: =IF(AND(KPIs!$A19<>"",OR($C$5="(Todos)",KPIs!$L19=$C$5),OR($C$6="(Todas)",KPIs!$M19=$C$6)),BO19,"") | BO19: =IF(AND(KPIs!$A19<>"",OR($C$5="(Todos)",KPIs!$L19=$C$5),OR($C$6="(Todas)",KPIs!$M19=$C$6)),N(BO18)+1,N(BO18)) | BR19: =IF(AND(Hitos!$A19<>"",OR($C$5="(Todos)",Hitos!$I19=$C$5),OR($C$6="(Todas)",Hitos!$J19=$C$6),OR(Hitos!$L19="Vencido",Hitos!$L19="Esta semana",Hitos!$L19="Próximos 30 días")),BS19,"") | BS19: =IF(AND(Hitos!$A19<>"",OR($C$5="(Todos)",Hitos!$I19=$C$5),OR($C$6="(Todas)",Hitos!$J19=$C$6),OR(Hitos!$L19="Vencido",Hitos!$L19="Esta semana",Hitos!$L19="Próximos 30 días")),N(BS18)+1,N(BS18))
B20: =IF($BH20="","",INDEX(Proyectos!$A$2:$A$41,$BH20)) | C20: =IF($BH20="","",INDEX(Proyectos!$B$2:$B$41,$BH20)) | D20: =IF($BH20="","",INDEX(Proyectos!$D$2:$D$41,$BH20)) | E20: =IF($BH20="","",INDEX(Proyectos!$E$2:$E$41,$BH20)) | F20: =IF($BH20="","",INDEX(Proyectos!$G$2:$G$41,$BH20)) | G20: =IF($BH20="","",INDEX(Proyectos!$H$2:$H$41,$BH20)) | H20: =IF($BH20="","",INDEX(Proyectos!$I$2:$I$41,$BH20)) | I20: =IF($BH20="","",INDEX(Proyectos!$K$2:$K$41,$BH20)) | J20: =IF($BH20="","",INDEX(Proyectos!$L$2:$L$41,$BH20)) | K20: =IF($BH20="","",INDEX(Proyectos!$U$2:$U$41,$BH20)) | L20: =IF($BH20="","",INDEX(Proyectos!$V$2:$V$41,$BH20)) | M20: =IF($BH20="","",INDEX(Proyectos!$W$2:$W$41,$BH20)) | N20: =IF($BH20="","",INDEX(Proyectos!$N$2:$N$41,$BH20)) | O20: =IF($BH20="","",INDEX(Proyectos!$O$2:$O$41,$BH20)) | P20: =IF($BH20="","",INDEX(Proyectos!$S$2:$S$41,$BH20)) | Q20: =IF($BH20="","",INDEX(Proyectos!$Y$2:$Y$41,$BH20)) | R20: =IF($BH20="","",INDEX(Proyectos!$AB$2:$AB$41,$BH20)) | BH20: =IFERROR(MATCH(7,$BJ$2:$BJ$41,0),"") | BJ20: =IF(AND(Proyectos!$A20<>"",OR($C$5="(Todos)",Proyectos!$C20=$C$5),OR($C$6="(Todas)",Proyectos!$D20=$C$6),OR($C$7="(Todos)",Proyectos!$H20=$C$7)),BK20,"") | BK20: =IF(AND(Proyectos!$A20<>"",OR($C$5="(Todos)",Proyectos!$C20=$C$5),OR($C$6="(Todas)",Proyectos!$D20=$C$6),OR($C$7="(Todos)",Proyectos!$H20=$C$7)),N(BK19)+1,N(BK19)) | BN20: =IF(AND(KPIs!$A20<>"",OR($C$5="(Todos)",KPIs!$L20=$C$5),OR($C$6="(Todas)",KPIs!$M20=$C$6)),BO20,"") | BO20: =IF(AND(KPIs!$A20<>"",OR($C$5="(Todos)",KPIs!$L20=$C$5),OR($C$6="(Todas)",KPIs!$M20=$C$6)),N(BO19)+1,N(BO19)) | BR20: =IF(AND(Hitos!$A20<>"",OR($C$5="(Todos)",Hitos!$I20=$C$5),OR($C$6="(Todas)",Hitos!$J20=$C$6),OR(Hitos!$L20="Vencido",Hitos!$L20="Esta semana",Hitos!$L20="Próximos 30 días")),BS20,"") | BS20: =IF(AND(Hitos!$A20<>"",OR($C$5="(Todos)",Hitos!$I20=$C$5),OR($C$6="(Todas)",Hitos!$J20=$C$6),OR(Hitos!$L20="Vencido",Hitos!$L20="Esta semana",Hitos!$L20="Próximos 30 días")),N(BS19)+1,N(BS19))
B21: =IF($BH21="","",INDEX(Proyectos!$A$2:$A$41,$BH21)) | C21: =IF($BH21="","",INDEX(Proyectos!$B$2:$B$41,$BH21)) | D21: =IF($BH21="","",INDEX(Proyectos!$D$2:$D$41,$BH21)) | E21: =IF($BH21="","",INDEX(Proyectos!$E$2:$E$41,$BH21)) | F21: =IF($BH21="","",INDEX(Proyectos!$G$2:$G$41,$BH21)) | G21: =IF($BH21="","",INDEX(Proyectos!$H$2:$H$41,$BH21)) | H21: =IF($BH21="","",INDEX(Proyectos!$I$2:$I$41,$BH21)) | I21: =IF($BH21="","",INDEX(Proyectos!$K$2:$K$41,$BH21)) | J21: =IF($BH21="","",INDEX(Proyectos!$L$2:$L$41,$BH21)) | K21: =IF($BH21="","",INDEX(Proyectos!$U$2:$U$41,$BH21)) | L21: =IF($BH21="","",INDEX(Proyectos!$V$2:$V$41,$BH21)) | M21: =IF($BH21="","",INDEX(Proyectos!$W$2:$W$41,$BH21)) | N21: =IF($BH21="","",INDEX(Proyectos!$N$2:$N$41,$BH21)) | O21: =IF($BH21="","",INDEX(Proyectos!$O$2:$O$41,$BH21)) | P21: =IF($BH21="","",INDEX(Proyectos!$S$2:$S$41,$BH21)) | Q21: =IF($BH21="","",INDEX(Proyectos!$Y$2:$Y$41,$BH21)) | R21: =IF($BH21="","",INDEX(Proyectos!$AB$2:$AB$41,$BH21)) | BH21: =IFERROR(MATCH(8,$BJ$2:$BJ$41,0),"") | BJ21: =IF(AND(Proyectos!$A21<>"",OR($C$5="(Todos)",Proyectos!$C21=$C$5),OR($C$6="(Todas)",Proyectos!$D21=$C$6),OR($C$7="(Todos)",Proyectos!$H21=$C$7)),BK21,"") | BK21: =IF(AND(Proyectos!$A21<>"",OR($C$5="(Todos)",Proyectos!$C21=$C$5),OR($C$6="(Todas)",Proyectos!$D21=$C$6),OR($C$7="(Todos)",Proyectos!$H21=$C$7)),N(BK20)+1,N(BK20)) | BN21: =IF(AND(KPIs!$A21<>"",OR($C$5="(Todos)",KPIs!$L21=$C$5),OR($C$6="(Todas)",KPIs!$M21=$C$6)),BO21,"") | BO21: =IF(AND(KPIs!$A21<>"",OR($C$5="(Todos)",KPIs!$L21=$C$5),OR($C$6="(Todas)",KPIs!$M21=$C$6)),N(BO20)+1,N(BO20)) | BR21: =IF(AND(Hitos!$A21<>"",OR($C$5="(Todos)",Hitos!$I21=$C$5),OR($C$6="(Todas)",Hitos!$J21=$C$6),OR(Hitos!$L21="Vencido",Hitos!$L21="Esta semana",Hitos!$L21="Próximos 30 días")),BS21,"") | BS21: =IF(AND(Hitos!$A21<>"",OR($C$5="(Todos)",Hitos!$I21=$C$5),OR($C$6="(Todas)",Hitos!$J21=$C$6),OR(Hitos!$L21="Vencido",Hitos!$L21="Esta semana",Hitos!$L21="Próximos 30 días")),N(BS20)+1,N(BS20))
B22: =IF($BH22="","",INDEX(Proyectos!$A$2:$A$41,$BH22)) | C22: =IF($BH22="","",INDEX(Proyectos!$B$2:$B$41,$BH22)) | D22: =IF($BH22="","",INDEX(Proyectos!$D$2:$D$41,$BH22)) | E22: =IF($BH22="","",INDEX(Proyectos!$E$2:$E$41,$BH22)) | F22: =IF($BH22="","",INDEX(Proyectos!$G$2:$G$41,$BH22)) | G22: =IF($BH22="","",INDEX(Proyectos!$H$2:$H$41,$BH22)) | H22: =IF($BH22="","",INDEX(Proyectos!$I$2:$I$41,$BH22)) | I22: =IF($BH22="","",INDEX(Proyectos!$K$2:$K$41,$BH22)) | J22: =IF($BH22="","",INDEX(Proyectos!$L$2:$L$41,$BH22)) | K22: =IF($BH22="","",INDEX(Proyectos!$U$2:$U$41,$BH22)) | L22: =IF($BH22="","",INDEX(Proyectos!$V$2:$V$41,$BH22)) | M22: =IF($BH22="","",INDEX(Proyectos!$W$2:$W$41,$BH22)) | N22: =IF($BH22="","",INDEX(Proyectos!$N$2:$N$41,$BH22)) | O22: =IF($BH22="","",INDEX(Proyectos!$O$2:$O$41,$BH22)) | P22: =IF($BH22="","",INDEX(Proyectos!$S$2:$S$41,$BH22)) | Q22: =IF($BH22="","",INDEX(Proyectos!$Y$2:$Y$41,$BH22)) | R22: =IF($BH22="","",INDEX(Proyectos!$AB$2:$AB$41,$BH22)) | BH22: =IFERROR(MATCH(9,$BJ$2:$BJ$41,0),"") | BJ22: =IF(AND(Proyectos!$A22<>"",OR($C$5="(Todos)",Proyectos!$C22=$C$5),OR($C$6="(Todas)",Proyectos!$D22=$C$6),OR($C$7="(Todos)",Proyectos!$H22=$C$7)),BK22,"") | BK22: =IF(AND(Proyectos!$A22<>"",OR($C$5="(Todos)",Proyectos!$C22=$C$5),OR($C$6="(Todas)",Proyectos!$D22=$C$6),OR($C$7="(Todos)",Proyectos!$H22=$C$7)),N(BK21)+1,N(BK21)) | BN22: =IF(AND(KPIs!$A22<>"",OR($C$5="(Todos)",KPIs!$L22=$C$5),OR($C$6="(Todas)",KPIs!$M22=$C$6)),BO22,"") | BO22: =IF(AND(KPIs!$A22<>"",OR($C$5="(Todos)",KPIs!$L22=$C$5),OR($C$6="(Todas)",KPIs!$M22=$C$6)),N(BO21)+1,N(BO21)) | BR22: =IF(AND(Hitos!$A22<>"",OR($C$5="(Todos)",Hitos!$I22=$C$5),OR($C$6="(Todas)",Hitos!$J22=$C$6),OR(Hitos!$L22="Vencido",Hitos!$L22="Esta semana",Hitos!$L22="Próximos 30 días")),BS22,"") | BS22: =IF(AND(Hitos!$A22<>"",OR($C$5="(Todos)",Hitos!$I22=$C$5),OR($C$6="(Todas)",Hitos!$J22=$C$6),OR(Hitos!$L22="Vencido",Hitos!$L22="Esta semana",Hitos!$L22="Próximos 30 días")),N(BS21)+1,N(BS21))
B23: =IF($BH23="","",INDEX(Proyectos!$A$2:$A$41,$BH23)) | C23: =IF($BH23="","",INDEX(Proyectos!$B$2:$B$41,$BH23)) | D23: =IF($BH23="","",INDEX(Proyectos!$D$2:$D$41,$BH23)) | E23: =IF($BH23="","",INDEX(Proyectos!$E$2:$E$41,$BH23)) | F23: =IF($BH23="","",INDEX(Proyectos!$G$2:$G$41,$BH23)) | G23: =IF($BH23="","",INDEX(Proyectos!$H$2:$H$41,$BH23)) | H23: =IF($BH23="","",INDEX(Proyectos!$I$2:$I$41,$BH23)) | I23: =IF($BH23="","",INDEX(Proyectos!$K$2:$K$41,$BH23)) | J23: =IF($BH23="","",INDEX(Proyectos!$L$2:$L$41,$BH23)) | K23: =IF($BH23="","",INDEX(Proyectos!$U$2:$U$41,$BH23)) | L23: =IF($BH23="","",INDEX(Proyectos!$V$2:$V$41,$BH23)) | M23: =IF($BH23="","",INDEX(Proyectos!$W$2:$W$41,$BH23)) | N23: =IF($BH23="","",INDEX(Proyectos!$N$2:$N$41,$BH23)) | O23: =IF($BH23="","",INDEX(Proyectos!$O$2:$O$41,$BH23)) | P23: =IF($BH23="","",INDEX(Proyectos!$S$2:$S$41,$BH23)) | Q23: =IF($BH23="","",INDEX(Proyectos!$Y$2:$Y$41,$BH23)) | R23: =IF($BH23="","",INDEX(Proyectos!$AB$2:$AB$41,$BH23)) | BH23: =IFERROR(MATCH(10,$BJ$2:$BJ$41,0),"") | BJ23: =IF(AND(Proyectos!$A23<>"",OR($C$5="(Todos)",Proyectos!$C23=$C$5),OR($C$6="(Todas)",Proyectos!$D23=$C$6),OR($C$7="(Todos)",Proyectos!$H23=$C$7)),BK23,"") | BK23: =IF(AND(Proyectos!$A23<>"",OR($C$5="(Todos)",Proyectos!$C23=$C$5),OR($C$6="(Todas)",Proyectos!$D23=$C$6),OR($C$7="(Todos)",Proyectos!$H23=$C$7)),N(BK22)+1,N(BK22)) | BN23: =IF(AND(KPIs!$A23<>"",OR($C$5="(Todos)",KPIs!$L23=$C$5),OR($C$6="(Todas)",KPIs!$M23=$C$6)),BO23,"") | BO23: =IF(AND(KPIs!$A23<>"",OR($C$5="(Todos)",KPIs!$L23=$C$5),OR($C$6="(Todas)",KPIs!$M23=$C$6)),N(BO22)+1,N(BO22)) | BR23: =IF(AND(Hitos!$A23<>"",OR($C$5="(Todos)",Hitos!$I23=$C$5),OR($C$6="(Todas)",Hitos!$J23=$C$6),OR(Hitos!$L23="Vencido",Hitos!$L23="Esta semana",Hitos!$L23="Próximos 30 días")),BS23,"") | BS23: =IF(AND(Hitos!$A23<>"",OR($C$5="(Todos)",Hitos!$I23=$C$5),OR($C$6="(Todas)",Hitos!$J23=$C$6),OR(Hitos!$L23="Vencido",Hitos!$L23="Esta semana",Hitos!$L23="Próximos 30 días")),N(BS22)+1,N(BS22))
B24: =IF($BH24="","",INDEX(Proyectos!$A$2:$A$41,$BH24)) | C24: =IF($BH24="","",INDEX(Proyectos!$B$2:$B$41,$BH24)) | D24: =IF($BH24="","",INDEX(Proyectos!$D$2:$D$41,$BH24)) | E24: =IF($BH24="","",INDEX(Proyectos!$E$2:$E$41,$BH24)) | F24: =IF($BH24="","",INDEX(Proyectos!$G$2:$G$41,$BH24)) | G24: =IF($BH24="","",INDEX(Proyectos!$H$2:$H$41,$BH24)) | H24: =IF($BH24="","",INDEX(Proyectos!$I$2:$I$41,$BH24)) | I24: =IF($BH24="","",INDEX(Proyectos!$K$2:$K$41,$BH24)) | J24: =IF($BH24="","",INDEX(Proyectos!$L$2:$L$41,$BH24)) | K24: =IF($BH24="","",INDEX(Proyectos!$U$2:$U$41,$BH24)) | L24: =IF($BH24="","",INDEX(Proyectos!$V$2:$V$41,$BH24)) | M24: =IF($BH24="","",INDEX(Proyectos!$W$2:$W$41,$BH24)) | N24: =IF($BH24="","",INDEX(Proyectos!$N$2:$N$41,$BH24)) | O24: =IF($BH24="","",INDEX(Proyectos!$O$2:$O$41,$BH24)) | P24: =IF($BH24="","",INDEX(Proyectos!$S$2:$S$41,$BH24)) | Q24: =IF($BH24="","",INDEX(Proyectos!$Y$2:$Y$41,$BH24)) | R24: =IF($BH24="","",INDEX(Proyectos!$AB$2:$AB$41,$BH24)) | BH24: =IFERROR(MATCH(11,$BJ$2:$BJ$41,0),"") | BJ24: =IF(AND(Proyectos!$A24<>"",OR($C$5="(Todos)",Proyectos!$C24=$C$5),OR($C$6="(Todas)",Proyectos!$D24=$C$6),OR($C$7="(Todos)",Proyectos!$H24=$C$7)),BK24,"") | BK24: =IF(AND(Proyectos!$A24<>"",OR($C$5="(Todos)",Proyectos!$C24=$C$5),OR($C$6="(Todas)",Proyectos!$D24=$C$6),OR($C$7="(Todos)",Proyectos!$H24=$C$7)),N(BK23)+1,N(BK23)) | BN24: =IF(AND(KPIs!$A24<>"",OR($C$5="(Todos)",KPIs!$L24=$C$5),OR($C$6="(Todas)",KPIs!$M24=$C$6)),BO24,"") | BO24: =IF(AND(KPIs!$A24<>"",OR($C$5="(Todos)",KPIs!$L24=$C$5),OR($C$6="(Todas)",KPIs!$M24=$C$6)),N(BO23)+1,N(BO23)) | BR24: =IF(AND(Hitos!$A24<>"",OR($C$5="(Todos)",Hitos!$I24=$C$5),OR($C$6="(Todas)",Hitos!$J24=$C$6),OR(Hitos!$L24="Vencido",Hitos!$L24="Esta semana",Hitos!$L24="Próximos 30 días")),BS24,"") | BS24: =IF(AND(Hitos!$A24<>"",OR($C$5="(Todos)",Hitos!$I24=$C$5),OR($C$6="(Todas)",Hitos!$J24=$C$6),OR(Hitos!$L24="Vencido",Hitos!$L24="Esta semana",Hitos!$L24="Próximos 30 días")),N(BS23)+1,N(BS23))
B25: =IF($BH25="","",INDEX(Proyectos!$A$2:$A$41,$BH25)) | C25: =IF($BH25="","",INDEX(Proyectos!$B$2:$B$41,$BH25)) | D25: =IF($BH25="","",INDEX(Proyectos!$D$2:$D$41,$BH25)) | E25: =IF($BH25="","",INDEX(Proyectos!$E$2:$E$41,$BH25)) | F25: =IF($BH25="","",INDEX(Proyectos!$G$2:$G$41,$BH25)) | G25: =IF($BH25="","",INDEX(Proyectos!$H$2:$H$41,$BH25)) | H25: =IF($BH25="","",INDEX(Proyectos!$I$2:$I$41,$BH25)) | I25: =IF($BH25="","",INDEX(Proyectos!$K$2:$K$41,$BH25)) | J25: =IF($BH25="","",INDEX(Proyectos!$L$2:$L$41,$BH25)) | K25: =IF($BH25="","",INDEX(Proyectos!$U$2:$U$41,$BH25)) | L25: =IF($BH25="","",INDEX(Proyectos!$V$2:$V$41,$BH25)) | M25: =IF($BH25="","",INDEX(Proyectos!$W$2:$W$41,$BH25)) | N25: =IF($BH25="","",INDEX(Proyectos!$N$2:$N$41,$BH25)) | O25: =IF($BH25="","",INDEX(Proyectos!$O$2:$O$41,$BH25)) | P25: =IF($BH25="","",INDEX(Proyectos!$S$2:$S$41,$BH25)) | Q25: =IF($BH25="","",INDEX(Proyectos!$Y$2:$Y$41,$BH25)) | R25: =IF($BH25="","",INDEX(Proyectos!$AB$2:$AB$41,$BH25)) | BH25: =IFERROR(MATCH(12,$BJ$2:$BJ$41,0),"") | BJ25: =IF(AND(Proyectos!$A25<>"",OR($C$5="(Todos)",Proyectos!$C25=$C$5),OR($C$6="(Todas)",Proyectos!$D25=$C$6),OR($C$7="(Todos)",Proyectos!$H25=$C$7)),BK25,"") | BK25: =IF(AND(Proyectos!$A25<>"",OR($C$5="(Todos)",Proyectos!$C25=$C$5),OR($C$6="(Todas)",Proyectos!$D25=$C$6),OR($C$7="(Todos)",Proyectos!$H25=$C$7)),N(BK24)+1,N(BK24)) | BN25: =IF(AND(KPIs!$A25<>"",OR($C$5="(Todos)",KPIs!$L25=$C$5),OR($C$6="(Todas)",KPIs!$M25=$C$6)),BO25,"") | BO25: =IF(AND(KPIs!$A25<>"",OR($C$5="(Todos)",KPIs!$L25=$C$5),OR($C$6="(Todas)",KPIs!$M25=$C$6)),N(BO24)+1,N(BO24)) | BR25: =IF(AND(Hitos!$A25<>"",OR($C$5="(Todos)",Hitos!$I25=$C$5),OR($C$6="(Todas)",Hitos!$J25=$C$6),OR(Hitos!$L25="Vencido",Hitos!$L25="Esta semana",Hitos!$L25="Próximos 30 días")),BS25,"") | BS25: =IF(AND(Hitos!$A25<>"",OR($C$5="(Todos)",Hitos!$I25=$C$5),OR($C$6="(Todas)",Hitos!$J25=$C$6),OR(Hitos!$L25="Vencido",Hitos!$L25="Esta semana",Hitos!$L25="Próximos 30 días")),N(BS24)+1,N(BS24))
B26: =IF($BH26="","",INDEX(Proyectos!$A$2:$A$41,$BH26)) | C26: =IF($BH26="","",INDEX(Proyectos!$B$2:$B$41,$BH26)) | D26: =IF($BH26="","",INDEX(Proyectos!$D$2:$D$41,$BH26)) | E26: =IF($BH26="","",INDEX(Proyectos!$E$2:$E$41,$BH26)) | F26: =IF($BH26="","",INDEX(Proyectos!$G$2:$G$41,$BH26)) | G26: =IF($BH26="","",INDEX(Proyectos!$H$2:$H$41,$BH26)) | H26: =IF($BH26="","",INDEX(Proyectos!$I$2:$I$41,$BH26)) | I26: =IF($BH26="","",INDEX(Proyectos!$K$2:$K$41,$BH26)) | J26: =IF($BH26="","",INDEX(Proyectos!$L$2:$L$41,$BH26)) | K26: =IF($BH26="","",INDEX(Proyectos!$U$2:$U$41,$BH26)) | L26: =IF($BH26="","",INDEX(Proyectos!$V$2:$V$41,$BH26)) | M26: =IF($BH26="","",INDEX(Proyectos!$W$2:$W$41,$BH26)) | N26: =IF($BH26="","",INDEX(Proyectos!$N$2:$N$41,$BH26)) | O26: =IF($BH26="","",INDEX(Proyectos!$O$2:$O$41,$BH26)) | P26: =IF($BH26="","",INDEX(Proyectos!$S$2:$S$41,$BH26)) | Q26: =IF($BH26="","",INDEX(Proyectos!$Y$2:$Y$41,$BH26)) | R26: =IF($BH26="","",INDEX(Proyectos!$AB$2:$AB$41,$BH26)) | BH26: =IFERROR(MATCH(13,$BJ$2:$BJ$41,0),"") | BJ26: =IF(AND(Proyectos!$A26<>"",OR($C$5="(Todos)",Proyectos!$C26=$C$5),OR($C$6="(Todas)",Proyectos!$D26=$C$6),OR($C$7="(Todos)",Proyectos!$H26=$C$7)),BK26,"") | BK26: =IF(AND(Proyectos!$A26<>"",OR($C$5="(Todos)",Proyectos!$C26=$C$5),OR($C$6="(Todas)",Proyectos!$D26=$C$6),OR($C$7="(Todos)",Proyectos!$H26=$C$7)),N(BK25)+1,N(BK25)) | BN26: =IF(AND(KPIs!$A26<>"",OR($C$5="(Todos)",KPIs!$L26=$C$5),OR($C$6="(Todas)",KPIs!$M26=$C$6)),BO26,"") | BO26: =IF(AND(KPIs!$A26<>"",OR($C$5="(Todos)",KPIs!$L26=$C$5),OR($C$6="(Todas)",KPIs!$M26=$C$6)),N(BO25)+1,N(BO25)) | BR26: =IF(AND(Hitos!$A26<>"",OR($C$5="(Todos)",Hitos!$I26=$C$5),OR($C$6="(Todas)",Hitos!$J26=$C$6),OR(Hitos!$L26="Vencido",Hitos!$L26="Esta semana",Hitos!$L26="Próximos 30 días")),BS26,"") | BS26: =IF(AND(Hitos!$A26<>"",OR($C$5="(Todos)",Hitos!$I26=$C$5),OR($C$6="(Todas)",Hitos!$J26=$C$6),OR(Hitos!$L26="Vencido",Hitos!$L26="Esta semana",Hitos!$L26="Próximos 30 días")),N(BS25)+1,N(BS25))
B27: =IF($BH27="","",INDEX(Proyectos!$A$2:$A$41,$BH27)) | C27: =IF($BH27="","",INDEX(Proyectos!$B$2:$B$41,$BH27)) | D27: =IF($BH27="","",INDEX(Proyectos!$D$2:$D$41,$BH27)) | E27: =IF($BH27="","",INDEX(Proyectos!$E$2:$E$41,$BH27)) | F27: =IF($BH27="","",INDEX(Proyectos!$G$2:$G$41,$BH27)) | G27: =IF($BH27="","",INDEX(Proyectos!$H$2:$H$41,$BH27)) | H27: =IF($BH27="","",INDEX(Proyectos!$I$2:$I$41,$BH27)) | I27: =IF($BH27="","",INDEX(Proyectos!$K$2:$K$41,$BH27)) | J27: =IF($BH27="","",INDEX(Proyectos!$L$2:$L$41,$BH27)) | K27: =IF($BH27="","",INDEX(Proyectos!$U$2:$U$41,$BH27)) | L27: =IF($BH27="","",INDEX(Proyectos!$V$2:$V$41,$BH27)) | M27: =IF($BH27="","",INDEX(Proyectos!$W$2:$W$41,$BH27)) | N27: =IF($BH27="","",INDEX(Proyectos!$N$2:$N$41,$BH27)) | O27: =IF($BH27="","",INDEX(Proyectos!$O$2:$O$41,$BH27)) | P27: =IF($BH27="","",INDEX(Proyectos!$S$2:$S$41,$BH27)) | Q27: =IF($BH27="","",INDEX(Proyectos!$Y$2:$Y$41,$BH27)) | R27: =IF($BH27="","",INDEX(Proyectos!$AB$2:$AB$41,$BH27)) | BH27: =IFERROR(MATCH(14,$BJ$2:$BJ$41,0),"") | BJ27: =IF(AND(Proyectos!$A27<>"",OR($C$5="(Todos)",Proyectos!$C27=$C$5),OR($C$6="(Todas)",Proyectos!$D27=$C$6),OR($C$7="(Todos)",Proyectos!$H27=$C$7)),BK27,"") | BK27: =IF(AND(Proyectos!$A27<>"",OR($C$5="(Todos)",Proyectos!$C27=$C$5),OR($C$6="(Todas)",Proyectos!$D27=$C$6),OR($C$7="(Todos)",Proyectos!$H27=$C$7)),N(BK26)+1,N(BK26)) | BN27: =IF(AND(KPIs!$A27<>"",OR($C$5="(Todos)",KPIs!$L27=$C$5),OR($C$6="(Todas)",KPIs!$M27=$C$6)),BO27,"") | BO27: =IF(AND(KPIs!$A27<>"",OR($C$5="(Todos)",KPIs!$L27=$C$5),OR($C$6="(Todas)",KPIs!$M27=$C$6)),N(BO26)+1,N(BO26)) | BR27: =IF(AND(Hitos!$A27<>"",OR($C$5="(Todos)",Hitos!$I27=$C$5),OR($C$6="(Todas)",Hitos!$J27=$C$6),OR(Hitos!$L27="Vencido",Hitos!$L27="Esta semana",Hitos!$L27="Próximos 30 días")),BS27,"") | BS27: =IF(AND(Hitos!$A27<>"",OR($C$5="(Todos)",Hitos!$I27=$C$5),OR($C$6="(Todas)",Hitos!$J27=$C$6),OR(Hitos!$L27="Vencido",Hitos!$L27="Esta semana",Hitos!$L27="Próximos 30 días")),N(BS26)+1,N(BS26))
B28: =IF($BH28="","",INDEX(Proyectos!$A$2:$A$41,$BH28)) | C28: =IF($BH28="","",INDEX(Proyectos!$B$2:$B$41,$BH28)) | D28: =IF($BH28="","",INDEX(Proyectos!$D$2:$D$41,$BH28)) | E28: =IF($BH28="","",INDEX(Proyectos!$E$2:$E$41,$BH28)) | F28: =IF($BH28="","",INDEX(Proyectos!$G$2:$G$41,$BH28)) | G28: =IF($BH28="","",INDEX(Proyectos!$H$2:$H$41,$BH28)) | H28: =IF($BH28="","",INDEX(Proyectos!$I$2:$I$41,$BH28)) | I28: =IF($BH28="","",INDEX(Proyectos!$K$2:$K$41,$BH28)) | J28: =IF($BH28="","",INDEX(Proyectos!$L$2:$L$41,$BH28)) | K28: =IF($BH28="","",INDEX(Proyectos!$U$2:$U$41,$BH28)) | L28: =IF($BH28="","",INDEX(Proyectos!$V$2:$V$41,$BH28)) | M28: =IF($BH28="","",INDEX(Proyectos!$W$2:$W$41,$BH28)) | N28: =IF($BH28="","",INDEX(Proyectos!$N$2:$N$41,$BH28)) | O28: =IF($BH28="","",INDEX(Proyectos!$O$2:$O$41,$BH28)) | P28: =IF($BH28="","",INDEX(Proyectos!$S$2:$S$41,$BH28)) | Q28: =IF($BH28="","",INDEX(Proyectos!$Y$2:$Y$41,$BH28)) | R28: =IF($BH28="","",INDEX(Proyectos!$AB$2:$AB$41,$BH28)) | BH28: =IFERROR(MATCH(15,$BJ$2:$BJ$41,0),"") | BJ28: =IF(AND(Proyectos!$A28<>"",OR($C$5="(Todos)",Proyectos!$C28=$C$5),OR($C$6="(Todas)",Proyectos!$D28=$C$6),OR($C$7="(Todos)",Proyectos!$H28=$C$7)),BK28,"") | BK28: =IF(AND(Proyectos!$A28<>"",OR($C$5="(Todos)",Proyectos!$C28=$C$5),OR($C$6="(Todas)",Proyectos!$D28=$C$6),OR($C$7="(Todos)",Proyectos!$H28=$C$7)),N(BK27)+1,N(BK27)) | BN28: =IF(AND(KPIs!$A28<>"",OR($C$5="(Todos)",KPIs!$L28=$C$5),OR($C$6="(Todas)",KPIs!$M28=$C$6)),BO28,"") | BO28: =IF(AND(KPIs!$A28<>"",OR($C$5="(Todos)",KPIs!$L28=$C$5),OR($C$6="(Todas)",KPIs!$M28=$C$6)),N(BO27)+1,N(BO27)) | BR28: =IF(AND(Hitos!$A28<>"",OR($C$5="(Todos)",Hitos!$I28=$C$5),OR($C$6="(Todas)",Hitos!$J28=$C$6),OR(Hitos!$L28="Vencido",Hitos!$L28="Esta semana",Hitos!$L28="Próximos 30 días")),BS28,"") | BS28: =IF(AND(Hitos!$A28<>"",OR($C$5="(Todos)",Hitos!$I28=$C$5),OR($C$6="(Todas)",Hitos!$J28=$C$6),OR(Hitos!$L28="Vencido",Hitos!$L28="Esta semana",Hitos!$L28="Próximos 30 días")),N(BS27)+1,N(BS27))
B29: =IF($BH29="","",INDEX(Proyectos!$A$2:$A$41,$BH29)) | C29: =IF($BH29="","",INDEX(Proyectos!$B$2:$B$41,$BH29)) | D29: =IF($BH29="","",INDEX(Proyectos!$D$2:$D$41,$BH29)) | E29: =IF($BH29="","",INDEX(Proyectos!$E$2:$E$41,$BH29)) | F29: =IF($BH29="","",INDEX(Proyectos!$G$2:$G$41,$BH29)) | G29: =IF($BH29="","",INDEX(Proyectos!$H$2:$H$41,$BH29)) | H29: =IF($BH29="","",INDEX(Proyectos!$I$2:$I$41,$BH29)) | I29: =IF($BH29="","",INDEX(Proyectos!$K$2:$K$41,$BH29)) | J29: =IF($BH29="","",INDEX(Proyectos!$L$2:$L$41,$BH29)) | K29: =IF($BH29="","",INDEX(Proyectos!$U$2:$U$41,$BH29)) | L29: =IF($BH29="","",INDEX(Proyectos!$V$2:$V$41,$BH29)) | M29: =IF($BH29="","",INDEX(Proyectos!$W$2:$W$41,$BH29)) | N29: =IF($BH29="","",INDEX(Proyectos!$N$2:$N$41,$BH29)) | O29: =IF($BH29="","",INDEX(Proyectos!$O$2:$O$41,$BH29)) | P29: =IF($BH29="","",INDEX(Proyectos!$S$2:$S$41,$BH29)) | Q29: =IF($BH29="","",INDEX(Proyectos!$Y$2:$Y$41,$BH29)) | R29: =IF($BH29="","",INDEX(Proyectos!$AB$2:$AB$41,$BH29)) | BH29: =IFERROR(MATCH(16,$BJ$2:$BJ$41,0),"") | BJ29: =IF(AND(Proyectos!$A29<>"",OR($C$5="(Todos)",Proyectos!$C29=$C$5),OR($C$6="(Todas)",Proyectos!$D29=$C$6),OR($C$7="(Todos)",Proyectos!$H29=$C$7)),BK29,"") | BK29: =IF(AND(Proyectos!$A29<>"",OR($C$5="(Todos)",Proyectos!$C29=$C$5),OR($C$6="(Todas)",Proyectos!$D29=$C$6),OR($C$7="(Todos)",Proyectos!$H29=$C$7)),N(BK28)+1,N(BK28)) | BN29: =IF(AND(KPIs!$A29<>"",OR($C$5="(Todos)",KPIs!$L29=$C$5),OR($C$6="(Todas)",KPIs!$M29=$C$6)),BO29,"") | BO29: =IF(AND(KPIs!$A29<>"",OR($C$5="(Todos)",KPIs!$L29=$C$5),OR($C$6="(Todas)",KPIs!$M29=$C$6)),N(BO28)+1,N(BO28)) | BR29: =IF(AND(Hitos!$A29<>"",OR($C$5="(Todos)",Hitos!$I29=$C$5),OR($C$6="(Todas)",Hitos!$J29=$C$6),OR(Hitos!$L29="Vencido",Hitos!$L29="Esta semana",Hitos!$L29="Próximos 30 días")),BS29,"") | BS29: =IF(AND(Hitos!$A29<>"",OR($C$5="(Todos)",Hitos!$I29=$C$5),OR($C$6="(Todas)",Hitos!$J29=$C$6),OR(Hitos!$L29="Vencido",Hitos!$L29="Esta semana",Hitos!$L29="Próximos 30 días")),N(BS28)+1,N(BS28))
B30: =IF($BH30="","",INDEX(Proyectos!$A$2:$A$41,$BH30)) | C30: =IF($BH30="","",INDEX(Proyectos!$B$2:$B$41,$BH30)) | D30: =IF($BH30="","",INDEX(Proyectos!$D$2:$D$41,$BH30)) | E30: =IF($BH30="","",INDEX(Proyectos!$E$2:$E$41,$BH30)) | F30: =IF($BH30="","",INDEX(Proyectos!$G$2:$G$41,$BH30)) | G30: =IF($BH30="","",INDEX(Proyectos!$H$2:$H$41,$BH30)) | H30: =IF($BH30="","",INDEX(Proyectos!$I$2:$I$41,$BH30)) | I30: =IF($BH30="","",INDEX(Proyectos!$K$2:$K$41,$BH30)) | J30: =IF($BH30="","",INDEX(Proyectos!$L$2:$L$41,$BH30)) | K30: =IF($BH30="","",INDEX(Proyectos!$U$2:$U$41,$BH30)) | L30: =IF($BH30="","",INDEX(Proyectos!$V$2:$V$41,$BH30)) | M30: =IF($BH30="","",INDEX(Proyectos!$W$2:$W$41,$BH30)) | N30: =IF($BH30="","",INDEX(Proyectos!$N$2:$N$41,$BH30)) | O30: =IF($BH30="","",INDEX(Proyectos!$O$2:$O$41,$BH30)) | P30: =IF($BH30="","",INDEX(Proyectos!$S$2:$S$41,$BH30)) | Q30: =IF($BH30="","",INDEX(Proyectos!$Y$2:$Y$41,$BH30)) | R30: =IF($BH30="","",INDEX(Proyectos!$AB$2:$AB$41,$BH30)) | BH30: =IFERROR(MATCH(17,$BJ$2:$BJ$41,0),"") | BJ30: =IF(AND(Proyectos!$A30<>"",OR($C$5="(Todos)",Proyectos!$C30=$C$5),OR($C$6="(Todas)",Proyectos!$D30=$C$6),OR($C$7="(Todos)",Proyectos!$H30=$C$7)),BK30,"") | BK30: =IF(AND(Proyectos!$A30<>"",OR($C$5="(Todos)",Proyectos!$C30=$C$5),OR($C$6="(Todas)",Proyectos!$D30=$C$6),OR($C$7="(Todos)",Proyectos!$H30=$C$7)),N(BK29)+1,N(BK29)) | BN30: =IF(AND(KPIs!$A30<>"",OR($C$5="(Todos)",KPIs!$L30=$C$5),OR($C$6="(Todas)",KPIs!$M30=$C$6)),BO30,"") | BO30: =IF(AND(KPIs!$A30<>"",OR($C$5="(Todos)",KPIs!$L30=$C$5),OR($C$6="(Todas)",KPIs!$M30=$C$6)),N(BO29)+1,N(BO29)) | BR30: =IF(AND(Hitos!$A30<>"",OR($C$5="(Todos)",Hitos!$I30=$C$5),OR($C$6="(Todas)",Hitos!$J30=$C$6),OR(Hitos!$L30="Vencido",Hitos!$L30="Esta semana",Hitos!$L30="Próximos 30 días")),BS30,"") | BS30: =IF(AND(Hitos!$A30<>"",OR($C$5="(Todos)",Hitos!$I30=$C$5),OR($C$6="(Todas)",Hitos!$J30=$C$6),OR(Hitos!$L30="Vencido",Hitos!$L30="Esta semana",Hitos!$L30="Próximos 30 días")),N(BS29)+1,N(BS29))
B31: =IF($BH31="","",INDEX(Proyectos!$A$2:$A$41,$BH31)) | C31: =IF($BH31="","",INDEX(Proyectos!$B$2:$B$41,$BH31)) | D31: =IF($BH31="","",INDEX(Proyectos!$D$2:$D$41,$BH31)) | E31: =IF($BH31="","",INDEX(Proyectos!$E$2:$E$41,$BH31)) | F31: =IF($BH31="","",INDEX(Proyectos!$G$2:$G$41,$BH31)) | G31: =IF($BH31="","",INDEX(Proyectos!$H$2:$H$41,$BH31)) | H31: =IF($BH31="","",INDEX(Proyectos!$I$2:$I$41,$BH31)) | I31: =IF($BH31="","",INDEX(Proyectos!$K$2:$K$41,$BH31)) | J31: =IF($BH31="","",INDEX(Proyectos!$L$2:$L$41,$BH31)) | K31: =IF($BH31="","",INDEX(Proyectos!$U$2:$U$41,$BH31)) | L31: =IF($BH31="","",INDEX(Proyectos!$V$2:$V$41,$BH31)) | M31: =IF($BH31="","",INDEX(Proyectos!$W$2:$W$41,$BH31)) | N31: =IF($BH31="","",INDEX(Proyectos!$N$2:$N$41,$BH31)) | O31: =IF($BH31="","",INDEX(Proyectos!$O$2:$O$41,$BH31)) | P31: =IF($BH31="","",INDEX(Proyectos!$S$2:$S$41,$BH31)) | Q31: =IF($BH31="","",INDEX(Proyectos!$Y$2:$Y$41,$BH31)) | R31: =IF($BH31="","",INDEX(Proyectos!$AB$2:$AB$41,$BH31)) | BH31: =IFERROR(MATCH(18,$BJ$2:$BJ$41,0),"") | BJ31: =IF(AND(Proyectos!$A31<>"",OR($C$5="(Todos)",Proyectos!$C31=$C$5),OR($C$6="(Todas)",Proyectos!$D31=$C$6),OR($C$7="(Todos)",Proyectos!$H31=$C$7)),BK31,"") | BK31: =IF(AND(Proyectos!$A31<>"",OR($C$5="(Todos)",Proyectos!$C31=$C$5),OR($C$6="(Todas)",Proyectos!$D31=$C$6),OR($C$7="(Todos)",Proyectos!$H31=$C$7)),N(BK30)+1,N(BK30)) | BN31: =IF(AND(KPIs!$A31<>"",OR($C$5="(Todos)",KPIs!$L31=$C$5),OR($C$6="(Todas)",KPIs!$M31=$C$6)),BO31,"") | BO31: =IF(AND(KPIs!$A31<>"",OR($C$5="(Todos)",KPIs!$L31=$C$5),OR($C$6="(Todas)",KPIs!$M31=$C$6)),N(BO30)+1,N(BO30)) | BR31: =IF(AND(Hitos!$A31<>"",OR($C$5="(Todos)",Hitos!$I31=$C$5),OR($C$6="(Todas)",Hitos!$J31=$C$6),OR(Hitos!$L31="Vencido",Hitos!$L31="Esta semana",Hitos!$L31="Próximos 30 días")),BS31,"") | BS31: =IF(AND(Hitos!$A31<>"",OR($C$5="(Todos)",Hitos!$I31=$C$5),OR($C$6="(Todas)",Hitos!$J31=$C$6),OR(Hitos!$L31="Vencido",Hitos!$L31="Esta semana",Hitos!$L31="Próximos 30 días")),N(BS30)+1,N(BS30))
B32: =IF($BH32="","",INDEX(Proyectos!$A$2:$A$41,$BH32)) | C32: =IF($BH32="","",INDEX(Proyectos!$B$2:$B$41,$BH32)) | D32: =IF($BH32="","",INDEX(Proyectos!$D$2:$D$41,$BH32)) | E32: =IF($BH32="","",INDEX(Proyectos!$E$2:$E$41,$BH32)) | F32: =IF($BH32="","",INDEX(Proyectos!$G$2:$G$41,$BH32)) | G32: =IF($BH32="","",INDEX(Proyectos!$H$2:$H$41,$BH32)) | H32: =IF($BH32="","",INDEX(Proyectos!$I$2:$I$41,$BH32)) | I32: =IF($BH32="","",INDEX(Proyectos!$K$2:$K$41,$BH32)) | J32: =IF($BH32="","",INDEX(Proyectos!$L$2:$L$41,$BH32)) | K32: =IF($BH32="","",INDEX(Proyectos!$U$2:$U$41,$BH32)) | L32: =IF($BH32="","",INDEX(Proyectos!$V$2:$V$41,$BH32)) | M32: =IF($BH32="","",INDEX(Proyectos!$W$2:$W$41,$BH32)) | N32: =IF($BH32="","",INDEX(Proyectos!$N$2:$N$41,$BH32)) | O32: =IF($BH32="","",INDEX(Proyectos!$O$2:$O$41,$BH32)) | P32: =IF($BH32="","",INDEX(Proyectos!$S$2:$S$41,$BH32)) | Q32: =IF($BH32="","",INDEX(Proyectos!$Y$2:$Y$41,$BH32)) | R32: =IF($BH32="","",INDEX(Proyectos!$AB$2:$AB$41,$BH32)) | BH32: =IFERROR(MATCH(19,$BJ$2:$BJ$41,0),"") | BJ32: =IF(AND(Proyectos!$A32<>"",OR($C$5="(Todos)",Proyectos!$C32=$C$5),OR($C$6="(Todas)",Proyectos!$D32=$C$6),OR($C$7="(Todos)",Proyectos!$H32=$C$7)),BK32,"") | BK32: =IF(AND(Proyectos!$A32<>"",OR($C$5="(Todos)",Proyectos!$C32=$C$5),OR($C$6="(Todas)",Proyectos!$D32=$C$6),OR($C$7="(Todos)",Proyectos!$H32=$C$7)),N(BK31)+1,N(BK31)) | BN32: =IF(AND(KPIs!$A32<>"",OR($C$5="(Todos)",KPIs!$L32=$C$5),OR($C$6="(Todas)",KPIs!$M32=$C$6)),BO32,"") | BO32: =IF(AND(KPIs!$A32<>"",OR($C$5="(Todos)",KPIs!$L32=$C$5),OR($C$6="(Todas)",KPIs!$M32=$C$6)),N(BO31)+1,N(BO31)) | BR32: =IF(AND(Hitos!$A32<>"",OR($C$5="(Todos)",Hitos!$I32=$C$5),OR($C$6="(Todas)",Hitos!$J32=$C$6),OR(Hitos!$L32="Vencido",Hitos!$L32="Esta semana",Hitos!$L32="Próximos 30 días")),BS32,"") | BS32: =IF(AND(Hitos!$A32<>"",OR($C$5="(Todos)",Hitos!$I32=$C$5),OR($C$6="(Todas)",Hitos!$J32=$C$6),OR(Hitos!$L32="Vencido",Hitos!$L32="Esta semana",Hitos!$L32="Próximos 30 días")),N(BS31)+1,N(BS31))
B33: =IF($BH33="","",INDEX(Proyectos!$A$2:$A$41,$BH33)) | C33: =IF($BH33="","",INDEX(Proyectos!$B$2:$B$41,$BH33)) | D33: =IF($BH33="","",INDEX(Proyectos!$D$2:$D$41,$BH33)) | E33: =IF($BH33="","",INDEX(Proyectos!$E$2:$E$41,$BH33)) | F33: =IF($BH33="","",INDEX(Proyectos!$G$2:$G$41,$BH33)) | G33: =IF($BH33="","",INDEX(Proyectos!$H$2:$H$41,$BH33)) | H33: =IF($BH33="","",INDEX(Proyectos!$I$2:$I$41,$BH33)) | I33: =IF($BH33="","",INDEX(Proyectos!$K$2:$K$41,$BH33)) | J33: =IF($BH33="","",INDEX(Proyectos!$L$2:$L$41,$BH33)) | K33: =IF($BH33="","",INDEX(Proyectos!$U$2:$U$41,$BH33)) | L33: =IF($BH33="","",INDEX(Proyectos!$V$2:$V$41,$BH33)) | M33: =IF($BH33="","",INDEX(Proyectos!$W$2:$W$41,$BH33)) | N33: =IF($BH33="","",INDEX(Proyectos!$N$2:$N$41,$BH33)) | O33: =IF($BH33="","",INDEX(Proyectos!$O$2:$O$41,$BH33)) | P33: =IF($BH33="","",INDEX(Proyectos!$S$2:$S$41,$BH33)) | Q33: =IF($BH33="","",INDEX(Proyectos!$Y$2:$Y$41,$BH33)) | R33: =IF($BH33="","",INDEX(Proyectos!$AB$2:$AB$41,$BH33)) | BH33: =IFERROR(MATCH(20,$BJ$2:$BJ$41,0),"") | BJ33: =IF(AND(Proyectos!$A33<>"",OR($C$5="(Todos)",Proyectos!$C33=$C$5),OR($C$6="(Todas)",Proyectos!$D33=$C$6),OR($C$7="(Todos)",Proyectos!$H33=$C$7)),BK33,"") | BK33: =IF(AND(Proyectos!$A33<>"",OR($C$5="(Todos)",Proyectos!$C33=$C$5),OR($C$6="(Todas)",Proyectos!$D33=$C$6),OR($C$7="(Todos)",Proyectos!$H33=$C$7)),N(BK32)+1,N(BK32)) | BN33: =IF(AND(KPIs!$A33<>"",OR($C$5="(Todos)",KPIs!$L33=$C$5),OR($C$6="(Todas)",KPIs!$M33=$C$6)),BO33,"") | BO33: =IF(AND(KPIs!$A33<>"",OR($C$5="(Todos)",KPIs!$L33=$C$5),OR($C$6="(Todas)",KPIs!$M33=$C$6)),N(BO32)+1,N(BO32)) | BR33: =IF(AND(Hitos!$A33<>"",OR($C$5="(Todos)",Hitos!$I33=$C$5),OR($C$6="(Todas)",Hitos!$J33=$C$6),OR(Hitos!$L33="Vencido",Hitos!$L33="Esta semana",Hitos!$L33="Próximos 30 días")),BS33,"") | BS33: =IF(AND(Hitos!$A33<>"",OR($C$5="(Todos)",Hitos!$I33=$C$5),OR($C$6="(Todas)",Hitos!$J33=$C$6),OR(Hitos!$L33="Vencido",Hitos!$L33="Esta semana",Hitos!$L33="Próximos 30 días")),N(BS32)+1,N(BS32))
B34: =IF($BH34="","",INDEX(Proyectos!$A$2:$A$41,$BH34)) | C34: =IF($BH34="","",INDEX(Proyectos!$B$2:$B$41,$BH34)) | D34: =IF($BH34="","",INDEX(Proyectos!$D$2:$D$41,$BH34)) | E34: =IF($BH34="","",INDEX(Proyectos!$E$2:$E$41,$BH34)) | F34: =IF($BH34="","",INDEX(Proyectos!$G$2:$G$41,$BH34)) | G34: =IF($BH34="","",INDEX(Proyectos!$H$2:$H$41,$BH34)) | H34: =IF($BH34="","",INDEX(Proyectos!$I$2:$I$41,$BH34)) | I34: =IF($BH34="","",INDEX(Proyectos!$K$2:$K$41,$BH34)) | J34: =IF($BH34="","",INDEX(Proyectos!$L$2:$L$41,$BH34)) | K34: =IF($BH34="","",INDEX(Proyectos!$U$2:$U$41,$BH34)) | L34: =IF($BH34="","",INDEX(Proyectos!$V$2:$V$41,$BH34)) | M34: =IF($BH34="","",INDEX(Proyectos!$W$2:$W$41,$BH34)) | N34: =IF($BH34="","",INDEX(Proyectos!$N$2:$N$41,$BH34)) | O34: =IF($BH34="","",INDEX(Proyectos!$O$2:$O$41,$BH34)) | P34: =IF($BH34="","",INDEX(Proyectos!$S$2:$S$41,$BH34)) | Q34: =IF($BH34="","",INDEX(Proyectos!$Y$2:$Y$41,$BH34)) | R34: =IF($BH34="","",INDEX(Proyectos!$AB$2:$AB$41,$BH34)) | BH34: =IFERROR(MATCH(21,$BJ$2:$BJ$41,0),"") | BJ34: =IF(AND(Proyectos!$A34<>"",OR($C$5="(Todos)",Proyectos!$C34=$C$5),OR($C$6="(Todas)",Proyectos!$D34=$C$6),OR($C$7="(Todos)",Proyectos!$H34=$C$7)),BK34,"") | BK34: =IF(AND(Proyectos!$A34<>"",OR($C$5="(Todos)",Proyectos!$C34=$C$5),OR($C$6="(Todas)",Proyectos!$D34=$C$6),OR($C$7="(Todos)",Proyectos!$H34=$C$7)),N(BK33)+1,N(BK33)) | BN34: =IF(AND(KPIs!$A34<>"",OR($C$5="(Todos)",KPIs!$L34=$C$5),OR($C$6="(Todas)",KPIs!$M34=$C$6)),BO34,"") | BO34: =IF(AND(KPIs!$A34<>"",OR($C$5="(Todos)",KPIs!$L34=$C$5),OR($C$6="(Todas)",KPIs!$M34=$C$6)),N(BO33)+1,N(BO33)) | BR34: =IF(AND(Hitos!$A34<>"",OR($C$5="(Todos)",Hitos!$I34=$C$5),OR($C$6="(Todas)",Hitos!$J34=$C$6),OR(Hitos!$L34="Vencido",Hitos!$L34="Esta semana",Hitos!$L34="Próximos 30 días")),BS34,"") | BS34: =IF(AND(Hitos!$A34<>"",OR($C$5="(Todos)",Hitos!$I34=$C$5),OR($C$6="(Todas)",Hitos!$J34=$C$6),OR(Hitos!$L34="Vencido",Hitos!$L34="Esta semana",Hitos!$L34="Próximos 30 días")),N(BS33)+1,N(BS33))
B35: =IF($BH35="","",INDEX(Proyectos!$A$2:$A$41,$BH35)) | C35: =IF($BH35="","",INDEX(Proyectos!$B$2:$B$41,$BH35)) | D35: =IF($BH35="","",INDEX(Proyectos!$D$2:$D$41,$BH35)) | E35: =IF($BH35="","",INDEX(Proyectos!$E$2:$E$41,$BH35)) | F35: =IF($BH35="","",INDEX(Proyectos!$G$2:$G$41,$BH35)) | G35: =IF($BH35="","",INDEX(Proyectos!$H$2:$H$41,$BH35)) | H35: =IF($BH35="","",INDEX(Proyectos!$I$2:$I$41,$BH35)) | I35: =IF($BH35="","",INDEX(Proyectos!$K$2:$K$41,$BH35)) | J35: =IF($BH35="","",INDEX(Proyectos!$L$2:$L$41,$BH35)) | K35: =IF($BH35="","",INDEX(Proyectos!$U$2:$U$41,$BH35)) | L35: =IF($BH35="","",INDEX(Proyectos!$V$2:$V$41,$BH35)) | M35: =IF($BH35="","",INDEX(Proyectos!$W$2:$W$41,$BH35)) | N35: =IF($BH35="","",INDEX(Proyectos!$N$2:$N$41,$BH35)) | O35: =IF($BH35="","",INDEX(Proyectos!$O$2:$O$41,$BH35)) | P35: =IF($BH35="","",INDEX(Proyectos!$S$2:$S$41,$BH35)) | Q35: =IF($BH35="","",INDEX(Proyectos!$Y$2:$Y$41,$BH35)) | R35: =IF($BH35="","",INDEX(Proyectos!$AB$2:$AB$41,$BH35)) | BH35: =IFERROR(MATCH(22,$BJ$2:$BJ$41,0),"") | BJ35: =IF(AND(Proyectos!$A35<>"",OR($C$5="(Todos)",Proyectos!$C35=$C$5),OR($C$6="(Todas)",Proyectos!$D35=$C$6),OR($C$7="(Todos)",Proyectos!$H35=$C$7)),BK35,"") | BK35: =IF(AND(Proyectos!$A35<>"",OR($C$5="(Todos)",Proyectos!$C35=$C$5),OR($C$6="(Todas)",Proyectos!$D35=$C$6),OR($C$7="(Todos)",Proyectos!$H35=$C$7)),N(BK34)+1,N(BK34)) | BN35: =IF(AND(KPIs!$A35<>"",OR($C$5="(Todos)",KPIs!$L35=$C$5),OR($C$6="(Todas)",KPIs!$M35=$C$6)),BO35,"") | BO35: =IF(AND(KPIs!$A35<>"",OR($C$5="(Todos)",KPIs!$L35=$C$5),OR($C$6="(Todas)",KPIs!$M35=$C$6)),N(BO34)+1,N(BO34)) | BR35: =IF(AND(Hitos!$A35<>"",OR($C$5="(Todos)",Hitos!$I35=$C$5),OR($C$6="(Todas)",Hitos!$J35=$C$6),OR(Hitos!$L35="Vencido",Hitos!$L35="Esta semana",Hitos!$L35="Próximos 30 días")),BS35,"") | BS35: =IF(AND(Hitos!$A35<>"",OR($C$5="(Todos)",Hitos!$I35=$C$5),OR($C$6="(Todas)",Hitos!$J35=$C$6),OR(Hitos!$L35="Vencido",Hitos!$L35="Esta semana",Hitos!$L35="Próximos 30 días")),N(BS34)+1,N(BS34))
B36: =IF($BH36="","",INDEX(Proyectos!$A$2:$A$41,$BH36)) | C36: =IF($BH36="","",INDEX(Proyectos!$B$2:$B$41,$BH36)) | D36: =IF($BH36="","",INDEX(Proyectos!$D$2:$D$41,$BH36)) | E36: =IF($BH36="","",INDEX(Proyectos!$E$2:$E$41,$BH36)) | F36: =IF($BH36="","",INDEX(Proyectos!$G$2:$G$41,$BH36)) | G36: =IF($BH36="","",INDEX(Proyectos!$H$2:$H$41,$BH36)) | H36: =IF($BH36="","",INDEX(Proyectos!$I$2:$I$41,$BH36)) | I36: =IF($BH36="","",INDEX(Proyectos!$K$2:$K$41,$BH36)) | J36: =IF($BH36="","",INDEX(Proyectos!$L$2:$L$41,$BH36)) | K36: =IF($BH36="","",INDEX(Proyectos!$U$2:$U$41,$BH36)) | L36: =IF($BH36="","",INDEX(Proyectos!$V$2:$V$41,$BH36)) | M36: =IF($BH36="","",INDEX(Proyectos!$W$2:$W$41,$BH36)) | N36: =IF($BH36="","",INDEX(Proyectos!$N$2:$N$41,$BH36)) | O36: =IF($BH36="","",INDEX(Proyectos!$O$2:$O$41,$BH36)) | P36: =IF($BH36="","",INDEX(Proyectos!$S$2:$S$41,$BH36)) | Q36: =IF($BH36="","",INDEX(Proyectos!$Y$2:$Y$41,$BH36)) | R36: =IF($BH36="","",INDEX(Proyectos!$AB$2:$AB$41,$BH36)) | BH36: =IFERROR(MATCH(23,$BJ$2:$BJ$41,0),"") | BJ36: =IF(AND(Proyectos!$A36<>"",OR($C$5="(Todos)",Proyectos!$C36=$C$5),OR($C$6="(Todas)",Proyectos!$D36=$C$6),OR($C$7="(Todos)",Proyectos!$H36=$C$7)),BK36,"") | BK36: =IF(AND(Proyectos!$A36<>"",OR($C$5="(Todos)",Proyectos!$C36=$C$5),OR($C$6="(Todas)",Proyectos!$D36=$C$6),OR($C$7="(Todos)",Proyectos!$H36=$C$7)),N(BK35)+1,N(BK35)) | BN36: =IF(AND(KPIs!$A36<>"",OR($C$5="(Todos)",KPIs!$L36=$C$5),OR($C$6="(Todas)",KPIs!$M36=$C$6)),BO36,"") | BO36: =IF(AND(KPIs!$A36<>"",OR($C$5="(Todos)",KPIs!$L36=$C$5),OR($C$6="(Todas)",KPIs!$M36=$C$6)),N(BO35)+1,N(BO35)) | BR36: =IF(AND(Hitos!$A36<>"",OR($C$5="(Todos)",Hitos!$I36=$C$5),OR($C$6="(Todas)",Hitos!$J36=$C$6),OR(Hitos!$L36="Vencido",Hitos!$L36="Esta semana",Hitos!$L36="Próximos 30 días")),BS36,"") | BS36: =IF(AND(Hitos!$A36<>"",OR($C$5="(Todos)",Hitos!$I36=$C$5),OR($C$6="(Todas)",Hitos!$J36=$C$6),OR(Hitos!$L36="Vencido",Hitos!$L36="Esta semana",Hitos!$L36="Próximos 30 días")),N(BS35)+1,N(BS35))
B37: =IF($BH37="","",INDEX(Proyectos!$A$2:$A$41,$BH37)) | C37: =IF($BH37="","",INDEX(Proyectos!$B$2:$B$41,$BH37)) | D37: =IF($BH37="","",INDEX(Proyectos!$D$2:$D$41,$BH37)) | E37: =IF($BH37="","",INDEX(Proyectos!$E$2:$E$41,$BH37)) | F37: =IF($BH37="","",INDEX(Proyectos!$G$2:$G$41,$BH37)) | G37: =IF($BH37="","",INDEX(Proyectos!$H$2:$H$41,$BH37)) | H37: =IF($BH37="","",INDEX(Proyectos!$I$2:$I$41,$BH37)) | I37: =IF($BH37="","",INDEX(Proyectos!$K$2:$K$41,$BH37)) | J37: =IF($BH37="","",INDEX(Proyectos!$L$2:$L$41,$BH37)) | K37: =IF($BH37="","",INDEX(Proyectos!$U$2:$U$41,$BH37)) | L37: =IF($BH37="","",INDEX(Proyectos!$V$2:$V$41,$BH37)) | M37: =IF($BH37="","",INDEX(Proyectos!$W$2:$W$41,$BH37)) | N37: =IF($BH37="","",INDEX(Proyectos!$N$2:$N$41,$BH37)) | O37: =IF($BH37="","",INDEX(Proyectos!$O$2:$O$41,$BH37)) | P37: =IF($BH37="","",INDEX(Proyectos!$S$2:$S$41,$BH37)) | Q37: =IF($BH37="","",INDEX(Proyectos!$Y$2:$Y$41,$BH37)) | R37: =IF($BH37="","",INDEX(Proyectos!$AB$2:$AB$41,$BH37)) | BH37: =IFERROR(MATCH(24,$BJ$2:$BJ$41,0),"") | BJ37: =IF(AND(Proyectos!$A37<>"",OR($C$5="(Todos)",Proyectos!$C37=$C$5),OR($C$6="(Todas)",Proyectos!$D37=$C$6),OR($C$7="(Todos)",Proyectos!$H37=$C$7)),BK37,"") | BK37: =IF(AND(Proyectos!$A37<>"",OR($C$5="(Todos)",Proyectos!$C37=$C$5),OR($C$6="(Todas)",Proyectos!$D37=$C$6),OR($C$7="(Todos)",Proyectos!$H37=$C$7)),N(BK36)+1,N(BK36)) | BN37: =IF(AND(KPIs!$A37<>"",OR($C$5="(Todos)",KPIs!$L37=$C$5),OR($C$6="(Todas)",KPIs!$M37=$C$6)),BO37,"") | BO37: =IF(AND(KPIs!$A37<>"",OR($C$5="(Todos)",KPIs!$L37=$C$5),OR($C$6="(Todas)",KPIs!$M37=$C$6)),N(BO36)+1,N(BO36)) | BR37: =IF(AND(Hitos!$A37<>"",OR($C$5="(Todos)",Hitos!$I37=$C$5),OR($C$6="(Todas)",Hitos!$J37=$C$6),OR(Hitos!$L37="Vencido",Hitos!$L37="Esta semana",Hitos!$L37="Próximos 30 días")),BS37,"") | BS37: =IF(AND(Hitos!$A37<>"",OR($C$5="(Todos)",Hitos!$I37=$C$5),OR($C$6="(Todas)",Hitos!$J37=$C$6),OR(Hitos!$L37="Vencido",Hitos!$L37="Esta semana",Hitos!$L37="Próximos 30 días")),N(BS36)+1,N(BS36))
B38: =IF($BH38="","",INDEX(Proyectos!$A$2:$A$41,$BH38)) | C38: =IF($BH38="","",INDEX(Proyectos!$B$2:$B$41,$BH38)) | D38: =IF($BH38="","",INDEX(Proyectos!$D$2:$D$41,$BH38)) | E38: =IF($BH38="","",INDEX(Proyectos!$E$2:$E$41,$BH38)) | F38: =IF($BH38="","",INDEX(Proyectos!$G$2:$G$41,$BH38)) | G38: =IF($BH38="","",INDEX(Proyectos!$H$2:$H$41,$BH38)) | H38: =IF($BH38="","",INDEX(Proyectos!$I$2:$I$41,$BH38)) | I38: =IF($BH38="","",INDEX(Proyectos!$K$2:$K$41,$BH38)) | J38: =IF($BH38="","",INDEX(Proyectos!$L$2:$L$41,$BH38)) | K38: =IF($BH38="","",INDEX(Proyectos!$U$2:$U$41,$BH38)) | L38: =IF($BH38="","",INDEX(Proyectos!$V$2:$V$41,$BH38)) | M38: =IF($BH38="","",INDEX(Proyectos!$W$2:$W$41,$BH38)) | N38: =IF($BH38="","",INDEX(Proyectos!$N$2:$N$41,$BH38)) | O38: =IF($BH38="","",INDEX(Proyectos!$O$2:$O$41,$BH38)) | P38: =IF($BH38="","",INDEX(Proyectos!$S$2:$S$41,$BH38)) | Q38: =IF($BH38="","",INDEX(Proyectos!$Y$2:$Y$41,$BH38)) | R38: =IF($BH38="","",INDEX(Proyectos!$AB$2:$AB$41,$BH38)) | BH38: =IFERROR(MATCH(25,$BJ$2:$BJ$41,0),"") | BJ38: =IF(AND(Proyectos!$A38<>"",OR($C$5="(Todos)",Proyectos!$C38=$C$5),OR($C$6="(Todas)",Proyectos!$D38=$C$6),OR($C$7="(Todos)",Proyectos!$H38=$C$7)),BK38,"") | BK38: =IF(AND(Proyectos!$A38<>"",OR($C$5="(Todos)",Proyectos!$C38=$C$5),OR($C$6="(Todas)",Proyectos!$D38=$C$6),OR($C$7="(Todos)",Proyectos!$H38=$C$7)),N(BK37)+1,N(BK37)) | BN38: =IF(AND(KPIs!$A38<>"",OR($C$5="(Todos)",KPIs!$L38=$C$5),OR($C$6="(Todas)",KPIs!$M38=$C$6)),BO38,"") | BO38: =IF(AND(KPIs!$A38<>"",OR($C$5="(Todos)",KPIs!$L38=$C$5),OR($C$6="(Todas)",KPIs!$M38=$C$6)),N(BO37)+1,N(BO37)) | BR38: =IF(AND(Hitos!$A38<>"",OR($C$5="(Todos)",Hitos!$I38=$C$5),OR($C$6="(Todas)",Hitos!$J38=$C$6),OR(Hitos!$L38="Vencido",Hitos!$L38="Esta semana",Hitos!$L38="Próximos 30 días")),BS38,"") | BS38: =IF(AND(Hitos!$A38<>"",OR($C$5="(Todos)",Hitos!$I38=$C$5),OR($C$6="(Todas)",Hitos!$J38=$C$6),OR(Hitos!$L38="Vencido",Hitos!$L38="Esta semana",Hitos!$L38="Próximos 30 días")),N(BS37)+1,N(BS37))
B39: =IF($BH39="","",INDEX(Proyectos!$A$2:$A$41,$BH39)) | C39: =IF($BH39="","",INDEX(Proyectos!$B$2:$B$41,$BH39)) | D39: =IF($BH39="","",INDEX(Proyectos!$D$2:$D$41,$BH39)) | E39: =IF($BH39="","",INDEX(Proyectos!$E$2:$E$41,$BH39)) | F39: =IF($BH39="","",INDEX(Proyectos!$G$2:$G$41,$BH39)) | G39: =IF($BH39="","",INDEX(Proyectos!$H$2:$H$41,$BH39)) | H39: =IF($BH39="","",INDEX(Proyectos!$I$2:$I$41,$BH39)) | I39: =IF($BH39="","",INDEX(Proyectos!$K$2:$K$41,$BH39)) | J39: =IF($BH39="","",INDEX(Proyectos!$L$2:$L$41,$BH39)) | K39: =IF($BH39="","",INDEX(Proyectos!$U$2:$U$41,$BH39)) | L39: =IF($BH39="","",INDEX(Proyectos!$V$2:$V$41,$BH39)) | M39: =IF($BH39="","",INDEX(Proyectos!$W$2:$W$41,$BH39)) | N39: =IF($BH39="","",INDEX(Proyectos!$N$2:$N$41,$BH39)) | O39: =IF($BH39="","",INDEX(Proyectos!$O$2:$O$41,$BH39)) | P39: =IF($BH39="","",INDEX(Proyectos!$S$2:$S$41,$BH39)) | Q39: =IF($BH39="","",INDEX(Proyectos!$Y$2:$Y$41,$BH39)) | R39: =IF($BH39="","",INDEX(Proyectos!$AB$2:$AB$41,$BH39)) | BH39: =IFERROR(MATCH(26,$BJ$2:$BJ$41,0),"") | BJ39: =IF(AND(Proyectos!$A39<>"",OR($C$5="(Todos)",Proyectos!$C39=$C$5),OR($C$6="(Todas)",Proyectos!$D39=$C$6),OR($C$7="(Todos)",Proyectos!$H39=$C$7)),BK39,"") | BK39: =IF(AND(Proyectos!$A39<>"",OR($C$5="(Todos)",Proyectos!$C39=$C$5),OR($C$6="(Todas)",Proyectos!$D39=$C$6),OR($C$7="(Todos)",Proyectos!$H39=$C$7)),N(BK38)+1,N(BK38)) | BN39: =IF(AND(KPIs!$A39<>"",OR($C$5="(Todos)",KPIs!$L39=$C$5),OR($C$6="(Todas)",KPIs!$M39=$C$6)),BO39,"") | BO39: =IF(AND(KPIs!$A39<>"",OR($C$5="(Todos)",KPIs!$L39=$C$5),OR($C$6="(Todas)",KPIs!$M39=$C$6)),N(BO38)+1,N(BO38)) | BR39: =IF(AND(Hitos!$A39<>"",OR($C$5="(Todos)",Hitos!$I39=$C$5),OR($C$6="(Todas)",Hitos!$J39=$C$6),OR(Hitos!$L39="Vencido",Hitos!$L39="Esta semana",Hitos!$L39="Próximos 30 días")),BS39,"") | BS39: =IF(AND(Hitos!$A39<>"",OR($C$5="(Todos)",Hitos!$I39=$C$5),OR($C$6="(Todas)",Hitos!$J39=$C$6),OR(Hitos!$L39="Vencido",Hitos!$L39="Esta semana",Hitos!$L39="Próximos 30 días")),N(BS38)+1,N(BS38))
B40: =IF($BH40="","",INDEX(Proyectos!$A$2:$A$41,$BH40)) | C40: =IF($BH40="","",INDEX(Proyectos!$B$2:$B$41,$BH40)) | D40: =IF($BH40="","",INDEX(Proyectos!$D$2:$D$41,$BH40)) | E40: =IF($BH40="","",INDEX(Proyectos!$E$2:$E$41,$BH40)) | F40: =IF($BH40="","",INDEX(Proyectos!$G$2:$G$41,$BH40)) | G40: =IF($BH40="","",INDEX(Proyectos!$H$2:$H$41,$BH40)) | H40: =IF($BH40="","",INDEX(Proyectos!$I$2:$I$41,$BH40)) | I40: =IF($BH40="","",INDEX(Proyectos!$K$2:$K$41,$BH40)) | J40: =IF($BH40="","",INDEX(Proyectos!$L$2:$L$41,$BH40)) | K40: =IF($BH40="","",INDEX(Proyectos!$U$2:$U$41,$BH40)) | L40: =IF($BH40="","",INDEX(Proyectos!$V$2:$V$41,$BH40)) | M40: =IF($BH40="","",INDEX(Proyectos!$W$2:$W$41,$BH40)) | N40: =IF($BH40="","",INDEX(Proyectos!$N$2:$N$41,$BH40)) | O40: =IF($BH40="","",INDEX(Proyectos!$O$2:$O$41,$BH40)) | P40: =IF($BH40="","",INDEX(Proyectos!$S$2:$S$41,$BH40)) | Q40: =IF($BH40="","",INDEX(Proyectos!$Y$2:$Y$41,$BH40)) | R40: =IF($BH40="","",INDEX(Proyectos!$AB$2:$AB$41,$BH40)) | BH40: =IFERROR(MATCH(27,$BJ$2:$BJ$41,0),"") | BJ40: =IF(AND(Proyectos!$A40<>"",OR($C$5="(Todos)",Proyectos!$C40=$C$5),OR($C$6="(Todas)",Proyectos!$D40=$C$6),OR($C$7="(Todos)",Proyectos!$H40=$C$7)),BK40,"") | BK40: =IF(AND(Proyectos!$A40<>"",OR($C$5="(Todos)",Proyectos!$C40=$C$5),OR($C$6="(Todas)",Proyectos!$D40=$C$6),OR($C$7="(Todos)",Proyectos!$H40=$C$7)),N(BK39)+1,N(BK39)) | BN40: =IF(AND(KPIs!$A40<>"",OR($C$5="(Todos)",KPIs!$L40=$C$5),OR($C$6="(Todas)",KPIs!$M40=$C$6)),BO40,"") | BO40: =IF(AND(KPIs!$A40<>"",OR($C$5="(Todos)",KPIs!$L40=$C$5),OR($C$6="(Todas)",KPIs!$M40=$C$6)),N(BO39)+1,N(BO39)) | BR40: =IF(AND(Hitos!$A40<>"",OR($C$5="(Todos)",Hitos!$I40=$C$5),OR($C$6="(Todas)",Hitos!$J40=$C$6),OR(Hitos!$L40="Vencido",Hitos!$L40="Esta semana",Hitos!$L40="Próximos 30 días")),BS40,"") | BS40: =IF(AND(Hitos!$A40<>"",OR($C$5="(Todos)",Hitos!$I40=$C$5),OR($C$6="(Todas)",Hitos!$J40=$C$6),OR(Hitos!$L40="Vencido",Hitos!$L40="Esta semana",Hitos!$L40="Próximos 30 días")),N(BS39)+1,N(BS39))
B41: =IF($BH41="","",INDEX(Proyectos!$A$2:$A$41,$BH41)) | C41: =IF($BH41="","",INDEX(Proyectos!$B$2:$B$41,$BH41)) | D41: =IF($BH41="","",INDEX(Proyectos!$D$2:$D$41,$BH41)) | E41: =IF($BH41="","",INDEX(Proyectos!$E$2:$E$41,$BH41)) | F41: =IF($BH41="","",INDEX(Proyectos!$G$2:$G$41,$BH41)) | G41: =IF($BH41="","",INDEX(Proyectos!$H$2:$H$41,$BH41)) | H41: =IF($BH41="","",INDEX(Proyectos!$I$2:$I$41,$BH41)) | I41: =IF($BH41="","",INDEX(Proyectos!$K$2:$K$41,$BH41)) | J41: =IF($BH41="","",INDEX(Proyectos!$L$2:$L$41,$BH41)) | K41: =IF($BH41="","",INDEX(Proyectos!$U$2:$U$41,$BH41)) | L41: =IF($BH41="","",INDEX(Proyectos!$V$2:$V$41,$BH41)) | M41: =IF($BH41="","",INDEX(Proyectos!$W$2:$W$41,$BH41)) | N41: =IF($BH41="","",INDEX(Proyectos!$N$2:$N$41,$BH41)) | O41: =IF($BH41="","",INDEX(Proyectos!$O$2:$O$41,$BH41)) | P41: =IF($BH41="","",INDEX(Proyectos!$S$2:$S$41,$BH41)) | Q41: =IF($BH41="","",INDEX(Proyectos!$Y$2:$Y$41,$BH41)) | R41: =IF($BH41="","",INDEX(Proyectos!$AB$2:$AB$41,$BH41)) | BH41: =IFERROR(MATCH(28,$BJ$2:$BJ$41,0),"") | BJ41: =IF(AND(Proyectos!$A41<>"",OR($C$5="(Todos)",Proyectos!$C41=$C$5),OR($C$6="(Todas)",Proyectos!$D41=$C$6),OR($C$7="(Todos)",Proyectos!$H41=$C$7)),BK41,"") | BK41: =IF(AND(Proyectos!$A41<>"",OR($C$5="(Todos)",Proyectos!$C41=$C$5),OR($C$6="(Todas)",Proyectos!$D41=$C$6),OR($C$7="(Todos)",Proyectos!$H41=$C$7)),N(BK40)+1,N(BK40)) | BN41: =IF(AND(KPIs!$A41<>"",OR($C$5="(Todos)",KPIs!$L41=$C$5),OR($C$6="(Todas)",KPIs!$M41=$C$6)),BO41,"") | BO41: =IF(AND(KPIs!$A41<>"",OR($C$5="(Todos)",KPIs!$L41=$C$5),OR($C$6="(Todas)",KPIs!$M41=$C$6)),N(BO40)+1,N(BO40)) | BR41: =IF(AND(Hitos!$A41<>"",OR($C$5="(Todos)",Hitos!$I41=$C$5),OR($C$6="(Todas)",Hitos!$J41=$C$6),OR(Hitos!$L41="Vencido",Hitos!$L41="Esta semana",Hitos!$L41="Próximos 30 días")),BS41,"") | BS41: =IF(AND(Hitos!$A41<>"",OR($C$5="(Todos)",Hitos!$I41=$C$5),OR($C$6="(Todas)",Hitos!$J41=$C$6),OR(Hitos!$L41="Vencido",Hitos!$L41="Esta semana",Hitos!$L41="Próximos 30 días")),N(BS40)+1,N(BS40))
B42: =IF($BH42="","",INDEX(Proyectos!$A$2:$A$41,$BH42)) | C42: =IF($BH42="","",INDEX(Proyectos!$B$2:$B$41,$BH42)) | D42: =IF($BH42="","",INDEX(Proyectos!$D$2:$D$41,$BH42)) | E42: =IF($BH42="","",INDEX(Proyectos!$E$2:$E$41,$BH42)) | F42: =IF($BH42="","",INDEX(Proyectos!$G$2:$G$41,$BH42)) | G42: =IF($BH42="","",INDEX(Proyectos!$H$2:$H$41,$BH42)) | H42: =IF($BH42="","",INDEX(Proyectos!$I$2:$I$41,$BH42)) | I42: =IF($BH42="","",INDEX(Proyectos!$K$2:$K$41,$BH42)) | J42: =IF($BH42="","",INDEX(Proyectos!$L$2:$L$41,$BH42)) | K42: =IF($BH42="","",INDEX(Proyectos!$U$2:$U$41,$BH42)) | L42: =IF($BH42="","",INDEX(Proyectos!$V$2:$V$41,$BH42)) | M42: =IF($BH42="","",INDEX(Proyectos!$W$2:$W$41,$BH42)) | N42: =IF($BH42="","",INDEX(Proyectos!$N$2:$N$41,$BH42)) | O42: =IF($BH42="","",INDEX(Proyectos!$O$2:$O$41,$BH42)) | P42: =IF($BH42="","",INDEX(Proyectos!$S$2:$S$41,$BH42)) | Q42: =IF($BH42="","",INDEX(Proyectos!$Y$2:$Y$41,$BH42)) | R42: =IF($BH42="","",INDEX(Proyectos!$AB$2:$AB$41,$BH42)) | BH42: =IFERROR(MATCH(29,$BJ$2:$BJ$41,0),"") | BN42: =IF(AND(KPIs!$A42<>"",OR($C$5="(Todos)",KPIs!$L42=$C$5),OR($C$6="(Todas)",KPIs!$M42=$C$6)),BO42,"") | BO42: =IF(AND(KPIs!$A42<>"",OR($C$5="(Todos)",KPIs!$L42=$C$5),OR($C$6="(Todas)",KPIs!$M42=$C$6)),N(BO41)+1,N(BO41)) | BR42: =IF(AND(Hitos!$A42<>"",OR($C$5="(Todos)",Hitos!$I42=$C$5),OR($C$6="(Todas)",Hitos!$J42=$C$6),OR(Hitos!$L42="Vencido",Hitos!$L42="Esta semana",Hitos!$L42="Próximos 30 días")),BS42,"") | BS42: =IF(AND(Hitos!$A42<>"",OR($C$5="(Todos)",Hitos!$I42=$C$5),OR($C$6="(Todas)",Hitos!$J42=$C$6),OR(Hitos!$L42="Vencido",Hitos!$L42="Esta semana",Hitos!$L42="Próximos 30 días")),N(BS41)+1,N(BS41))
B43: =IF($BH43="","",INDEX(Proyectos!$A$2:$A$41,$BH43)) | C43: =IF($BH43="","",INDEX(Proyectos!$B$2:$B$41,$BH43)) | D43: =IF($BH43="","",INDEX(Proyectos!$D$2:$D$41,$BH43)) | E43: =IF($BH43="","",INDEX(Proyectos!$E$2:$E$41,$BH43)) | F43: =IF($BH43="","",INDEX(Proyectos!$G$2:$G$41,$BH43)) | G43: =IF($BH43="","",INDEX(Proyectos!$H$2:$H$41,$BH43)) | H43: =IF($BH43="","",INDEX(Proyectos!$I$2:$I$41,$BH43)) | I43: =IF($BH43="","",INDEX(Proyectos!$K$2:$K$41,$BH43)) | J43: =IF($BH43="","",INDEX(Proyectos!$L$2:$L$41,$BH43)) | K43: =IF($BH43="","",INDEX(Proyectos!$U$2:$U$41,$BH43)) | L43: =IF($BH43="","",INDEX(Proyectos!$V$2:$V$41,$BH43)) | M43: =IF($BH43="","",INDEX(Proyectos!$W$2:$W$41,$BH43)) | N43: =IF($BH43="","",INDEX(Proyectos!$N$2:$N$41,$BH43)) | O43: =IF($BH43="","",INDEX(Proyectos!$O$2:$O$41,$BH43)) | P43: =IF($BH43="","",INDEX(Proyectos!$S$2:$S$41,$BH43)) | Q43: =IF($BH43="","",INDEX(Proyectos!$Y$2:$Y$41,$BH43)) | R43: =IF($BH43="","",INDEX(Proyectos!$AB$2:$AB$41,$BH43)) | BH43: =IFERROR(MATCH(30,$BJ$2:$BJ$41,0),"") | BN43: =IF(AND(KPIs!$A43<>"",OR($C$5="(Todos)",KPIs!$L43=$C$5),OR($C$6="(Todas)",KPIs!$M43=$C$6)),BO43,"") | BO43: =IF(AND(KPIs!$A43<>"",OR($C$5="(Todos)",KPIs!$L43=$C$5),OR($C$6="(Todas)",KPIs!$M43=$C$6)),N(BO42)+1,N(BO42)) | BR43: =IF(AND(Hitos!$A43<>"",OR($C$5="(Todos)",Hitos!$I43=$C$5),OR($C$6="(Todas)",Hitos!$J43=$C$6),OR(Hitos!$L43="Vencido",Hitos!$L43="Esta semana",Hitos!$L43="Próximos 30 días")),BS43,"") | BS43: =IF(AND(Hitos!$A43<>"",OR($C$5="(Todos)",Hitos!$I43=$C$5),OR($C$6="(Todas)",Hitos!$J43=$C$6),OR(Hitos!$L43="Vencido",Hitos!$L43="Esta semana",Hitos!$L43="Próximos 30 días")),N(BS42)+1,N(BS42))
B44: =IF($BH44="","",INDEX(Proyectos!$A$2:$A$41,$BH44)) | C44: =IF($BH44="","",INDEX(Proyectos!$B$2:$B$41,$BH44)) | D44: =IF($BH44="","",INDEX(Proyectos!$D$2:$D$41,$BH44)) | E44: =IF($BH44="","",INDEX(Proyectos!$E$2:$E$41,$BH44)) | F44: =IF($BH44="","",INDEX(Proyectos!$G$2:$G$41,$BH44)) | G44: =IF($BH44="","",INDEX(Proyectos!$H$2:$H$41,$BH44)) | H44: =IF($BH44="","",INDEX(Proyectos!$I$2:$I$41,$BH44)) | I44: =IF($BH44="","",INDEX(Proyectos!$K$2:$K$41,$BH44)) | J44: =IF($BH44="","",INDEX(Proyectos!$L$2:$L$41,$BH44)) | K44: =IF($BH44="","",INDEX(Proyectos!$U$2:$U$41,$BH44)) | L44: =IF($BH44="","",INDEX(Proyectos!$V$2:$V$41,$BH44)) | M44: =IF($BH44="","",INDEX(Proyectos!$W$2:$W$41,$BH44)) | N44: =IF($BH44="","",INDEX(Proyectos!$N$2:$N$41,$BH44)) | O44: =IF($BH44="","",INDEX(Proyectos!$O$2:$O$41,$BH44)) | P44: =IF($BH44="","",INDEX(Proyectos!$S$2:$S$41,$BH44)) | Q44: =IF($BH44="","",INDEX(Proyectos!$Y$2:$Y$41,$BH44)) | R44: =IF($BH44="","",INDEX(Proyectos!$AB$2:$AB$41,$BH44)) | BH44: =IFERROR(MATCH(31,$BJ$2:$BJ$41,0),"") | BN44: =IF(AND(KPIs!$A44<>"",OR($C$5="(Todos)",KPIs!$L44=$C$5),OR($C$6="(Todas)",KPIs!$M44=$C$6)),BO44,"") | BO44: =IF(AND(KPIs!$A44<>"",OR($C$5="(Todos)",KPIs!$L44=$C$5),OR($C$6="(Todas)",KPIs!$M44=$C$6)),N(BO43)+1,N(BO43)) | BR44: =IF(AND(Hitos!$A44<>"",OR($C$5="(Todos)",Hitos!$I44=$C$5),OR($C$6="(Todas)",Hitos!$J44=$C$6),OR(Hitos!$L44="Vencido",Hitos!$L44="Esta semana",Hitos!$L44="Próximos 30 días")),BS44,"") | BS44: =IF(AND(Hitos!$A44<>"",OR($C$5="(Todos)",Hitos!$I44=$C$5),OR($C$6="(Todas)",Hitos!$J44=$C$6),OR(Hitos!$L44="Vencido",Hitos!$L44="Esta semana",Hitos!$L44="Próximos 30 días")),N(BS43)+1,N(BS43))
B45: =IF($BH45="","",INDEX(Proyectos!$A$2:$A$41,$BH45)) | C45: =IF($BH45="","",INDEX(Proyectos!$B$2:$B$41,$BH45)) | D45: =IF($BH45="","",INDEX(Proyectos!$D$2:$D$41,$BH45)) | E45: =IF($BH45="","",INDEX(Proyectos!$E$2:$E$41,$BH45)) | F45: =IF($BH45="","",INDEX(Proyectos!$G$2:$G$41,$BH45)) | G45: =IF($BH45="","",INDEX(Proyectos!$H$2:$H$41,$BH45)) | H45: =IF($BH45="","",INDEX(Proyectos!$I$2:$I$41,$BH45)) | I45: =IF($BH45="","",INDEX(Proyectos!$K$2:$K$41,$BH45)) | J45: =IF($BH45="","",INDEX(Proyectos!$L$2:$L$41,$BH45)) | K45: =IF($BH45="","",INDEX(Proyectos!$U$2:$U$41,$BH45)) | L45: =IF($BH45="","",INDEX(Proyectos!$V$2:$V$41,$BH45)) | M45: =IF($BH45="","",INDEX(Proyectos!$W$2:$W$41,$BH45)) | N45: =IF($BH45="","",INDEX(Proyectos!$N$2:$N$41,$BH45)) | O45: =IF($BH45="","",INDEX(Proyectos!$O$2:$O$41,$BH45)) | P45: =IF($BH45="","",INDEX(Proyectos!$S$2:$S$41,$BH45)) | Q45: =IF($BH45="","",INDEX(Proyectos!$Y$2:$Y$41,$BH45)) | R45: =IF($BH45="","",INDEX(Proyectos!$AB$2:$AB$41,$BH45)) | BH45: =IFERROR(MATCH(32,$BJ$2:$BJ$41,0),"") | BN45: =IF(AND(KPIs!$A45<>"",OR($C$5="(Todos)",KPIs!$L45=$C$5),OR($C$6="(Todas)",KPIs!$M45=$C$6)),BO45,"") | BO45: =IF(AND(KPIs!$A45<>"",OR($C$5="(Todos)",KPIs!$L45=$C$5),OR($C$6="(Todas)",KPIs!$M45=$C$6)),N(BO44)+1,N(BO44)) | BR45: =IF(AND(Hitos!$A45<>"",OR($C$5="(Todos)",Hitos!$I45=$C$5),OR($C$6="(Todas)",Hitos!$J45=$C$6),OR(Hitos!$L45="Vencido",Hitos!$L45="Esta semana",Hitos!$L45="Próximos 30 días")),BS45,"") | BS45: =IF(AND(Hitos!$A45<>"",OR($C$5="(Todos)",Hitos!$I45=$C$5),OR($C$6="(Todas)",Hitos!$J45=$C$6),OR(Hitos!$L45="Vencido",Hitos!$L45="Esta semana",Hitos!$L45="Próximos 30 días")),N(BS44)+1,N(BS44))
B46: =IF($BH46="","",INDEX(Proyectos!$A$2:$A$41,$BH46)) | C46: =IF($BH46="","",INDEX(Proyectos!$B$2:$B$41,$BH46)) | D46: =IF($BH46="","",INDEX(Proyectos!$D$2:$D$41,$BH46)) | E46: =IF($BH46="","",INDEX(Proyectos!$E$2:$E$41,$BH46)) | F46: =IF($BH46="","",INDEX(Proyectos!$G$2:$G$41,$BH46)) | G46: =IF($BH46="","",INDEX(Proyectos!$H$2:$H$41,$BH46)) | H46: =IF($BH46="","",INDEX(Proyectos!$I$2:$I$41,$BH46)) | I46: =IF($BH46="","",INDEX(Proyectos!$K$2:$K$41,$BH46)) | J46: =IF($BH46="","",INDEX(Proyectos!$L$2:$L$41,$BH46)) | K46: =IF($BH46="","",INDEX(Proyectos!$U$2:$U$41,$BH46)) | L46: =IF($BH46="","",INDEX(Proyectos!$V$2:$V$41,$BH46)) | M46: =IF($BH46="","",INDEX(Proyectos!$W$2:$W$41,$BH46)) | N46: =IF($BH46="","",INDEX(Proyectos!$N$2:$N$41,$BH46)) | O46: =IF($BH46="","",INDEX(Proyectos!$O$2:$O$41,$BH46)) | P46: =IF($BH46="","",INDEX(Proyectos!$S$2:$S$41,$BH46)) | Q46: =IF($BH46="","",INDEX(Proyectos!$Y$2:$Y$41,$BH46)) | R46: =IF($BH46="","",INDEX(Proyectos!$AB$2:$AB$41,$BH46)) | BH46: =IFERROR(MATCH(33,$BJ$2:$BJ$41,0),"") | BN46: =IF(AND(KPIs!$A46<>"",OR($C$5="(Todos)",KPIs!$L46=$C$5),OR($C$6="(Todas)",KPIs!$M46=$C$6)),BO46,"") | BO46: =IF(AND(KPIs!$A46<>"",OR($C$5="(Todos)",KPIs!$L46=$C$5),OR($C$6="(Todas)",KPIs!$M46=$C$6)),N(BO45)+1,N(BO45)) | BR46: =IF(AND(Hitos!$A46<>"",OR($C$5="(Todos)",Hitos!$I46=$C$5),OR($C$6="(Todas)",Hitos!$J46=$C$6),OR(Hitos!$L46="Vencido",Hitos!$L46="Esta semana",Hitos!$L46="Próximos 30 días")),BS46,"") | BS46: =IF(AND(Hitos!$A46<>"",OR($C$5="(Todos)",Hitos!$I46=$C$5),OR($C$6="(Todas)",Hitos!$J46=$C$6),OR(Hitos!$L46="Vencido",Hitos!$L46="Esta semana",Hitos!$L46="Próximos 30 días")),N(BS45)+1,N(BS45))
B47: =IF($BH47="","",INDEX(Proyectos!$A$2:$A$41,$BH47)) | C47: =IF($BH47="","",INDEX(Proyectos!$B$2:$B$41,$BH47)) | D47: =IF($BH47="","",INDEX(Proyectos!$D$2:$D$41,$BH47)) | E47: =IF($BH47="","",INDEX(Proyectos!$E$2:$E$41,$BH47)) | F47: =IF($BH47="","",INDEX(Proyectos!$G$2:$G$41,$BH47)) | G47: =IF($BH47="","",INDEX(Proyectos!$H$2:$H$41,$BH47)) | H47: =IF($BH47="","",INDEX(Proyectos!$I$2:$I$41,$BH47)) | I47: =IF($BH47="","",INDEX(Proyectos!$K$2:$K$41,$BH47)) | J47: =IF($BH47="","",INDEX(Proyectos!$L$2:$L$41,$BH47)) | K47: =IF($BH47="","",INDEX(Proyectos!$U$2:$U$41,$BH47)) | L47: =IF($BH47="","",INDEX(Proyectos!$V$2:$V$41,$BH47)) | M47: =IF($BH47="","",INDEX(Proyectos!$W$2:$W$41,$BH47)) | N47: =IF($BH47="","",INDEX(Proyectos!$N$2:$N$41,$BH47)) | O47: =IF($BH47="","",INDEX(Proyectos!$O$2:$O$41,$BH47)) | P47: =IF($BH47="","",INDEX(Proyectos!$S$2:$S$41,$BH47)) | Q47: =IF($BH47="","",INDEX(Proyectos!$Y$2:$Y$41,$BH47)) | R47: =IF($BH47="","",INDEX(Proyectos!$AB$2:$AB$41,$BH47)) | BH47: =IFERROR(MATCH(34,$BJ$2:$BJ$41,0),"") | BN47: =IF(AND(KPIs!$A47<>"",OR($C$5="(Todos)",KPIs!$L47=$C$5),OR($C$6="(Todas)",KPIs!$M47=$C$6)),BO47,"") | BO47: =IF(AND(KPIs!$A47<>"",OR($C$5="(Todos)",KPIs!$L47=$C$5),OR($C$6="(Todas)",KPIs!$M47=$C$6)),N(BO46)+1,N(BO46)) | BR47: =IF(AND(Hitos!$A47<>"",OR($C$5="(Todos)",Hitos!$I47=$C$5),OR($C$6="(Todas)",Hitos!$J47=$C$6),OR(Hitos!$L47="Vencido",Hitos!$L47="Esta semana",Hitos!$L47="Próximos 30 días")),BS47,"") | BS47: =IF(AND(Hitos!$A47<>"",OR($C$5="(Todos)",Hitos!$I47=$C$5),OR($C$6="(Todas)",Hitos!$J47=$C$6),OR(Hitos!$L47="Vencido",Hitos!$L47="Esta semana",Hitos!$L47="Próximos 30 días")),N(BS46)+1,N(BS46))
B48: =IF($BH48="","",INDEX(Proyectos!$A$2:$A$41,$BH48)) | C48: =IF($BH48="","",INDEX(Proyectos!$B$2:$B$41,$BH48)) | D48: =IF($BH48="","",INDEX(Proyectos!$D$2:$D$41,$BH48)) | E48: =IF($BH48="","",INDEX(Proyectos!$E$2:$E$41,$BH48)) | F48: =IF($BH48="","",INDEX(Proyectos!$G$2:$G$41,$BH48)) | G48: =IF($BH48="","",INDEX(Proyectos!$H$2:$H$41,$BH48)) | H48: =IF($BH48="","",INDEX(Proyectos!$I$2:$I$41,$BH48)) | I48: =IF($BH48="","",INDEX(Proyectos!$K$2:$K$41,$BH48)) | J48: =IF($BH48="","",INDEX(Proyectos!$L$2:$L$41,$BH48)) | K48: =IF($BH48="","",INDEX(Proyectos!$U$2:$U$41,$BH48)) | L48: =IF($BH48="","",INDEX(Proyectos!$V$2:$V$41,$BH48)) | M48: =IF($BH48="","",INDEX(Proyectos!$W$2:$W$41,$BH48)) | N48: =IF($BH48="","",INDEX(Proyectos!$N$2:$N$41,$BH48)) | O48: =IF($BH48="","",INDEX(Proyectos!$O$2:$O$41,$BH48)) | P48: =IF($BH48="","",INDEX(Proyectos!$S$2:$S$41,$BH48)) | Q48: =IF($BH48="","",INDEX(Proyectos!$Y$2:$Y$41,$BH48)) | R48: =IF($BH48="","",INDEX(Proyectos!$AB$2:$AB$41,$BH48)) | BH48: =IFERROR(MATCH(35,$BJ$2:$BJ$41,0),"") | BN48: =IF(AND(KPIs!$A48<>"",OR($C$5="(Todos)",KPIs!$L48=$C$5),OR($C$6="(Todas)",KPIs!$M48=$C$6)),BO48,"") | BO48: =IF(AND(KPIs!$A48<>"",OR($C$5="(Todos)",KPIs!$L48=$C$5),OR($C$6="(Todas)",KPIs!$M48=$C$6)),N(BO47)+1,N(BO47)) | BR48: =IF(AND(Hitos!$A48<>"",OR($C$5="(Todos)",Hitos!$I48=$C$5),OR($C$6="(Todas)",Hitos!$J48=$C$6),OR(Hitos!$L48="Vencido",Hitos!$L48="Esta semana",Hitos!$L48="Próximos 30 días")),BS48,"") | BS48: =IF(AND(Hitos!$A48<>"",OR($C$5="(Todos)",Hitos!$I48=$C$5),OR($C$6="(Todas)",Hitos!$J48=$C$6),OR(Hitos!$L48="Vencido",Hitos!$L48="Esta semana",Hitos!$L48="Próximos 30 días")),N(BS47)+1,N(BS47))
B49: =IF($BH49="","",INDEX(Proyectos!$A$2:$A$41,$BH49)) | C49: =IF($BH49="","",INDEX(Proyectos!$B$2:$B$41,$BH49)) | D49: =IF($BH49="","",INDEX(Proyectos!$D$2:$D$41,$BH49)) | E49: =IF($BH49="","",INDEX(Proyectos!$E$2:$E$41,$BH49)) | F49: =IF($BH49="","",INDEX(Proyectos!$G$2:$G$41,$BH49)) | G49: =IF($BH49="","",INDEX(Proyectos!$H$2:$H$41,$BH49)) | H49: =IF($BH49="","",INDEX(Proyectos!$I$2:$I$41,$BH49)) | I49: =IF($BH49="","",INDEX(Proyectos!$K$2:$K$41,$BH49)) | J49: =IF($BH49="","",INDEX(Proyectos!$L$2:$L$41,$BH49)) | K49: =IF($BH49="","",INDEX(Proyectos!$U$2:$U$41,$BH49)) | L49: =IF($BH49="","",INDEX(Proyectos!$V$2:$V$41,$BH49)) | M49: =IF($BH49="","",INDEX(Proyectos!$W$2:$W$41,$BH49)) | N49: =IF($BH49="","",INDEX(Proyectos!$N$2:$N$41,$BH49)) | O49: =IF($BH49="","",INDEX(Proyectos!$O$2:$O$41,$BH49)) | P49: =IF($BH49="","",INDEX(Proyectos!$S$2:$S$41,$BH49)) | Q49: =IF($BH49="","",INDEX(Proyectos!$Y$2:$Y$41,$BH49)) | R49: =IF($BH49="","",INDEX(Proyectos!$AB$2:$AB$41,$BH49)) | BH49: =IFERROR(MATCH(36,$BJ$2:$BJ$41,0),"") | BN49: =IF(AND(KPIs!$A49<>"",OR($C$5="(Todos)",KPIs!$L49=$C$5),OR($C$6="(Todas)",KPIs!$M49=$C$6)),BO49,"") | BO49: =IF(AND(KPIs!$A49<>"",OR($C$5="(Todos)",KPIs!$L49=$C$5),OR($C$6="(Todas)",KPIs!$M49=$C$6)),N(BO48)+1,N(BO48)) | BR49: =IF(AND(Hitos!$A49<>"",OR($C$5="(Todos)",Hitos!$I49=$C$5),OR($C$6="(Todas)",Hitos!$J49=$C$6),OR(Hitos!$L49="Vencido",Hitos!$L49="Esta semana",Hitos!$L49="Próximos 30 días")),BS49,"") | BS49: =IF(AND(Hitos!$A49<>"",OR($C$5="(Todos)",Hitos!$I49=$C$5),OR($C$6="(Todas)",Hitos!$J49=$C$6),OR(Hitos!$L49="Vencido",Hitos!$L49="Esta semana",Hitos!$L49="Próximos 30 días")),N(BS48)+1,N(BS48))
B50: =IF($BH50="","",INDEX(Proyectos!$A$2:$A$41,$BH50)) | C50: =IF($BH50="","",INDEX(Proyectos!$B$2:$B$41,$BH50)) | D50: =IF($BH50="","",INDEX(Proyectos!$D$2:$D$41,$BH50)) | E50: =IF($BH50="","",INDEX(Proyectos!$E$2:$E$41,$BH50)) | F50: =IF($BH50="","",INDEX(Proyectos!$G$2:$G$41,$BH50)) | G50: =IF($BH50="","",INDEX(Proyectos!$H$2:$H$41,$BH50)) | H50: =IF($BH50="","",INDEX(Proyectos!$I$2:$I$41,$BH50)) | I50: =IF($BH50="","",INDEX(Proyectos!$K$2:$K$41,$BH50)) | J50: =IF($BH50="","",INDEX(Proyectos!$L$2:$L$41,$BH50)) | K50: =IF($BH50="","",INDEX(Proyectos!$U$2:$U$41,$BH50)) | L50: =IF($BH50="","",INDEX(Proyectos!$V$2:$V$41,$BH50)) | M50: =IF($BH50="","",INDEX(Proyectos!$W$2:$W$41,$BH50)) | N50: =IF($BH50="","",INDEX(Proyectos!$N$2:$N$41,$BH50)) | O50: =IF($BH50="","",INDEX(Proyectos!$O$2:$O$41,$BH50)) | P50: =IF($BH50="","",INDEX(Proyectos!$S$2:$S$41,$BH50)) | Q50: =IF($BH50="","",INDEX(Proyectos!$Y$2:$Y$41,$BH50)) | R50: =IF($BH50="","",INDEX(Proyectos!$AB$2:$AB$41,$BH50)) | BH50: =IFERROR(MATCH(37,$BJ$2:$BJ$41,0),"") | BN50: =IF(AND(KPIs!$A50<>"",OR($C$5="(Todos)",KPIs!$L50=$C$5),OR($C$6="(Todas)",KPIs!$M50=$C$6)),BO50,"") | BO50: =IF(AND(KPIs!$A50<>"",OR($C$5="(Todos)",KPIs!$L50=$C$5),OR($C$6="(Todas)",KPIs!$M50=$C$6)),N(BO49)+1,N(BO49)) | BR50: =IF(AND(Hitos!$A50<>"",OR($C$5="(Todos)",Hitos!$I50=$C$5),OR($C$6="(Todas)",Hitos!$J50=$C$6),OR(Hitos!$L50="Vencido",Hitos!$L50="Esta semana",Hitos!$L50="Próximos 30 días")),BS50,"") | BS50: =IF(AND(Hitos!$A50<>"",OR($C$5="(Todos)",Hitos!$I50=$C$5),OR($C$6="(Todas)",Hitos!$J50=$C$6),OR(Hitos!$L50="Vencido",Hitos!$L50="Esta semana",Hitos!$L50="Próximos 30 días")),N(BS49)+1,N(BS49))
B51: =IF($BH51="","",INDEX(Proyectos!$A$2:$A$41,$BH51)) | C51: =IF($BH51="","",INDEX(Proyectos!$B$2:$B$41,$BH51)) | D51: =IF($BH51="","",INDEX(Proyectos!$D$2:$D$41,$BH51)) | E51: =IF($BH51="","",INDEX(Proyectos!$E$2:$E$41,$BH51)) | F51: =IF($BH51="","",INDEX(Proyectos!$G$2:$G$41,$BH51)) | G51: =IF($BH51="","",INDEX(Proyectos!$H$2:$H$41,$BH51)) | H51: =IF($BH51="","",INDEX(Proyectos!$I$2:$I$41,$BH51)) | I51: =IF($BH51="","",INDEX(Proyectos!$K$2:$K$41,$BH51)) | J51: =IF($BH51="","",INDEX(Proyectos!$L$2:$L$41,$BH51)) | K51: =IF($BH51="","",INDEX(Proyectos!$U$2:$U$41,$BH51)) | L51: =IF($BH51="","",INDEX(Proyectos!$V$2:$V$41,$BH51)) | M51: =IF($BH51="","",INDEX(Proyectos!$W$2:$W$41,$BH51)) | N51: =IF($BH51="","",INDEX(Proyectos!$N$2:$N$41,$BH51)) | O51: =IF($BH51="","",INDEX(Proyectos!$O$2:$O$41,$BH51)) | P51: =IF($BH51="","",INDEX(Proyectos!$S$2:$S$41,$BH51)) | Q51: =IF($BH51="","",INDEX(Proyectos!$Y$2:$Y$41,$BH51)) | R51: =IF($BH51="","",INDEX(Proyectos!$AB$2:$AB$41,$BH51)) | BH51: =IFERROR(MATCH(38,$BJ$2:$BJ$41,0),"") | BN51: =IF(AND(KPIs!$A51<>"",OR($C$5="(Todos)",KPIs!$L51=$C$5),OR($C$6="(Todas)",KPIs!$M51=$C$6)),BO51,"") | BO51: =IF(AND(KPIs!$A51<>"",OR($C$5="(Todos)",KPIs!$L51=$C$5),OR($C$6="(Todas)",KPIs!$M51=$C$6)),N(BO50)+1,N(BO50)) | BR51: =IF(AND(Hitos!$A51<>"",OR($C$5="(Todos)",Hitos!$I51=$C$5),OR($C$6="(Todas)",Hitos!$J51=$C$6),OR(Hitos!$L51="Vencido",Hitos!$L51="Esta semana",Hitos!$L51="Próximos 30 días")),BS51,"") | BS51: =IF(AND(Hitos!$A51<>"",OR($C$5="(Todos)",Hitos!$I51=$C$5),OR($C$6="(Todas)",Hitos!$J51=$C$6),OR(Hitos!$L51="Vencido",Hitos!$L51="Esta semana",Hitos!$L51="Próximos 30 días")),N(BS50)+1,N(BS50))
B52: =IF($BH52="","",INDEX(Proyectos!$A$2:$A$41,$BH52)) | C52: =IF($BH52="","",INDEX(Proyectos!$B$2:$B$41,$BH52)) | D52: =IF($BH52="","",INDEX(Proyectos!$D$2:$D$41,$BH52)) | E52: =IF($BH52="","",INDEX(Proyectos!$E$2:$E$41,$BH52)) | F52: =IF($BH52="","",INDEX(Proyectos!$G$2:$G$41,$BH52)) | G52: =IF($BH52="","",INDEX(Proyectos!$H$2:$H$41,$BH52)) | H52: =IF($BH52="","",INDEX(Proyectos!$I$2:$I$41,$BH52)) | I52: =IF($BH52="","",INDEX(Proyectos!$K$2:$K$41,$BH52)) | J52: =IF($BH52="","",INDEX(Proyectos!$L$2:$L$41,$BH52)) | K52: =IF($BH52="","",INDEX(Proyectos!$U$2:$U$41,$BH52)) | L52: =IF($BH52="","",INDEX(Proyectos!$V$2:$V$41,$BH52)) | M52: =IF($BH52="","",INDEX(Proyectos!$W$2:$W$41,$BH52)) | N52: =IF($BH52="","",INDEX(Proyectos!$N$2:$N$41,$BH52)) | O52: =IF($BH52="","",INDEX(Proyectos!$O$2:$O$41,$BH52)) | P52: =IF($BH52="","",INDEX(Proyectos!$S$2:$S$41,$BH52)) | Q52: =IF($BH52="","",INDEX(Proyectos!$Y$2:$Y$41,$BH52)) | R52: =IF($BH52="","",INDEX(Proyectos!$AB$2:$AB$41,$BH52)) | BH52: =IFERROR(MATCH(39,$BJ$2:$BJ$41,0),"") | BN52: =IF(AND(KPIs!$A52<>"",OR($C$5="(Todos)",KPIs!$L52=$C$5),OR($C$6="(Todas)",KPIs!$M52=$C$6)),BO52,"") | BO52: =IF(AND(KPIs!$A52<>"",OR($C$5="(Todos)",KPIs!$L52=$C$5),OR($C$6="(Todas)",KPIs!$M52=$C$6)),N(BO51)+1,N(BO51)) | BR52: =IF(AND(Hitos!$A52<>"",OR($C$5="(Todos)",Hitos!$I52=$C$5),OR($C$6="(Todas)",Hitos!$J52=$C$6),OR(Hitos!$L52="Vencido",Hitos!$L52="Esta semana",Hitos!$L52="Próximos 30 días")),BS52,"") | BS52: =IF(AND(Hitos!$A52<>"",OR($C$5="(Todos)",Hitos!$I52=$C$5),OR($C$6="(Todas)",Hitos!$J52=$C$6),OR(Hitos!$L52="Vencido",Hitos!$L52="Esta semana",Hitos!$L52="Próximos 30 días")),N(BS51)+1,N(BS51))
B53: =IF($BH53="","",INDEX(Proyectos!$A$2:$A$41,$BH53)) | C53: =IF($BH53="","",INDEX(Proyectos!$B$2:$B$41,$BH53)) | D53: =IF($BH53="","",INDEX(Proyectos!$D$2:$D$41,$BH53)) | E53: =IF($BH53="","",INDEX(Proyectos!$E$2:$E$41,$BH53)) | F53: =IF($BH53="","",INDEX(Proyectos!$G$2:$G$41,$BH53)) | G53: =IF($BH53="","",INDEX(Proyectos!$H$2:$H$41,$BH53)) | H53: =IF($BH53="","",INDEX(Proyectos!$I$2:$I$41,$BH53)) | I53: =IF($BH53="","",INDEX(Proyectos!$K$2:$K$41,$BH53)) | J53: =IF($BH53="","",INDEX(Proyectos!$L$2:$L$41,$BH53)) | K53: =IF($BH53="","",INDEX(Proyectos!$U$2:$U$41,$BH53)) | L53: =IF($BH53="","",INDEX(Proyectos!$V$2:$V$41,$BH53)) | M53: =IF($BH53="","",INDEX(Proyectos!$W$2:$W$41,$BH53)) | N53: =IF($BH53="","",INDEX(Proyectos!$N$2:$N$41,$BH53)) | O53: =IF($BH53="","",INDEX(Proyectos!$O$2:$O$41,$BH53)) | P53: =IF($BH53="","",INDEX(Proyectos!$S$2:$S$41,$BH53)) | Q53: =IF($BH53="","",INDEX(Proyectos!$Y$2:$Y$41,$BH53)) | R53: =IF($BH53="","",INDEX(Proyectos!$AB$2:$AB$41,$BH53)) | BH53: =IFERROR(MATCH(40,$BJ$2:$BJ$41,0),"") | BN53: =IF(AND(KPIs!$A53<>"",OR($C$5="(Todos)",KPIs!$L53=$C$5),OR($C$6="(Todas)",KPIs!$M53=$C$6)),BO53,"") | BO53: =IF(AND(KPIs!$A53<>"",OR($C$5="(Todos)",KPIs!$L53=$C$5),OR($C$6="(Todas)",KPIs!$M53=$C$6)),N(BO52)+1,N(BO52)) | BR53: =IF(AND(Hitos!$A53<>"",OR($C$5="(Todos)",Hitos!$I53=$C$5),OR($C$6="(Todas)",Hitos!$J53=$C$6),OR(Hitos!$L53="Vencido",Hitos!$L53="Esta semana",Hitos!$L53="Próximos 30 días")),BS53,"") | BS53: =IF(AND(Hitos!$A53<>"",OR($C$5="(Todos)",Hitos!$I53=$C$5),OR($C$6="(Todas)",Hitos!$J53=$C$6),OR(Hitos!$L53="Vencido",Hitos!$L53="Esta semana",Hitos!$L53="Próximos 30 días")),N(BS52)+1,N(BS52))
BN54: =IF(AND(KPIs!$A54<>"",OR($C$5="(Todos)",KPIs!$L54=$C$5),OR($C$6="(Todas)",KPIs!$M54=$C$6)),BO54,"") | BO54: =IF(AND(KPIs!$A54<>"",OR($C$5="(Todos)",KPIs!$L54=$C$5),OR($C$6="(Todas)",KPIs!$M54=$C$6)),N(BO53)+1,N(BO53)) | BR54: =IF(AND(Hitos!$A54<>"",OR($C$5="(Todos)",Hitos!$I54=$C$5),OR($C$6="(Todas)",Hitos!$J54=$C$6),OR(Hitos!$L54="Vencido",Hitos!$L54="Esta semana",Hitos!$L54="Próximos 30 días")),BS54,"") | BS54: =IF(AND(Hitos!$A54<>"",OR($C$5="(Todos)",Hitos!$I54=$C$5),OR($C$6="(Todas)",Hitos!$J54=$C$6),OR(Hitos!$L54="Vencido",Hitos!$L54="Esta semana",Hitos!$L54="Próximos 30 días")),N(BS53)+1,N(BS53))
B55: KPIS DE LOS PROYECTOS DEL FILTRO | BN55: =IF(AND(KPIs!$A55<>"",OR($C$5="(Todos)",KPIs!$L55=$C$5),OR($C$6="(Todas)",KPIs!$M55=$C$6)),BO55,"") | BO55: =IF(AND(KPIs!$A55<>"",OR($C$5="(Todos)",KPIs!$L55=$C$5),OR($C$6="(Todas)",KPIs!$M55=$C$6)),N(BO54)+1,N(BO54)) | BR55: =IF(AND(Hitos!$A55<>"",OR($C$5="(Todos)",Hitos!$I55=$C$5),OR($C$6="(Todas)",Hitos!$J55=$C$6),OR(Hitos!$L55="Vencido",Hitos!$L55="Esta semana",Hitos!$L55="Próximos 30 días")),BS55,"") | BS55: =IF(AND(Hitos!$A55<>"",OR($C$5="(Todos)",Hitos!$I55=$C$5),OR($C$6="(Todas)",Hitos!$J55=$C$6),OR(Hitos!$L55="Vencido",Hitos!$L55="Esta semana",Hitos!$L55="Próximos 30 días")),N(BS54)+1,N(BS54))
B56: Proyecto | C56: KPI | D56: Unidad | E56: Dirección | F56: Baseline | G56: Target | H56: Actual | I56: % consecución | J56: Estado | K56: Frecuencia | L56: Fuente | BN56: =IF(AND(KPIs!$A56<>"",OR($C$5="(Todos)",KPIs!$L56=$C$5),OR($C$6="(Todas)",KPIs!$M56=$C$6)),BO56,"") | BO56: =IF(AND(KPIs!$A56<>"",OR($C$5="(Todos)",KPIs!$L56=$C$5),OR($C$6="(Todas)",KPIs!$M56=$C$6)),N(BO55)+1,N(BO55)) | BR56: =IF(AND(Hitos!$A56<>"",OR($C$5="(Todos)",Hitos!$I56=$C$5),OR($C$6="(Todas)",Hitos!$J56=$C$6),OR(Hitos!$L56="Vencido",Hitos!$L56="Esta semana",Hitos!$L56="Próximos 30 días")),BS56,"") | BS56: =IF(AND(Hitos!$A56<>"",OR($C$5="(Todos)",Hitos!$I56=$C$5),OR($C$6="(Todas)",Hitos!$J56=$C$6),OR(Hitos!$L56="Vencido",Hitos!$L56="Esta semana",Hitos!$L56="Próximos 30 días")),N(BS55)+1,N(BS55))
B57: =IF($BL57="","",INDEX(KPIs!$K$2:$K$71,$BL57)) | C57: =IF($BL57="","",INDEX(KPIs!$C$2:$C$71,$BL57)) | D57: =IF($BL57="","",INDEX(KPIs!$D$2:$D$71,$BL57)) | E57: =IF($BL57="","",INDEX(KPIs!$E$2:$E$71,$BL57)) | F57: =IF($BL57="","",INDEX(KPIs!$F$2:$F$71,$BL57)) | G57: =IF($BL57="","",INDEX(KPIs!$G$2:$G$71,$BL57)) | H57: =IF($BL57="","",INDEX(KPIs!$H$2:$H$71,$BL57)) | I57: =IF($BL57="","",INDEX(KPIs!$N$2:$N$71,$BL57)) | J57: =IF($BL57="","",INDEX(KPIs!$O$2:$O$71,$BL57)) | K57: =IF($BL57="","",INDEX(KPIs!$I$2:$I$71,$BL57)) | L57: =IF($BL57="","",INDEX(KPIs!$J$2:$J$71,$BL57)) | BL57: =IFERROR(MATCH(1,$BN$2:$BN$71,0),"") | BN57: =IF(AND(KPIs!$A57<>"",OR($C$5="(Todos)",KPIs!$L57=$C$5),OR($C$6="(Todas)",KPIs!$M57=$C$6)),BO57,"") | BO57: =IF(AND(KPIs!$A57<>"",OR($C$5="(Todos)",KPIs!$L57=$C$5),OR($C$6="(Todas)",KPIs!$M57=$C$6)),N(BO56)+1,N(BO56)) | BR57: =IF(AND(Hitos!$A57<>"",OR($C$5="(Todos)",Hitos!$I57=$C$5),OR($C$6="(Todas)",Hitos!$J57=$C$6),OR(Hitos!$L57="Vencido",Hitos!$L57="Esta semana",Hitos!$L57="Próximos 30 días")),BS57,"") | BS57: =IF(AND(Hitos!$A57<>"",OR($C$5="(Todos)",Hitos!$I57=$C$5),OR($C$6="(Todas)",Hitos!$J57=$C$6),OR(Hitos!$L57="Vencido",Hitos!$L57="Esta semana",Hitos!$L57="Próximos 30 días")),N(BS56)+1,N(BS56))
B58: =IF($BL58="","",INDEX(KPIs!$K$2:$K$71,$BL58)) | C58: =IF($BL58="","",INDEX(KPIs!$C$2:$C$71,$BL58)) | D58: =IF($BL58="","",INDEX(KPIs!$D$2:$D$71,$BL58)) | E58: =IF($BL58="","",INDEX(KPIs!$E$2:$E$71,$BL58)) | F58: =IF($BL58="","",INDEX(KPIs!$F$2:$F$71,$BL58)) | G58: =IF($BL58="","",INDEX(KPIs!$G$2:$G$71,$BL58)) | H58: =IF($BL58="","",INDEX(KPIs!$H$2:$H$71,$BL58)) | I58: =IF($BL58="","",INDEX(KPIs!$N$2:$N$71,$BL58)) | J58: =IF($BL58="","",INDEX(KPIs!$O$2:$O$71,$BL58)) | K58: =IF($BL58="","",INDEX(KPIs!$I$2:$I$71,$BL58)) | L58: =IF($BL58="","",INDEX(KPIs!$J$2:$J$71,$BL58)) | BL58: =IFERROR(MATCH(2,$BN$2:$BN$71,0),"") | BN58: =IF(AND(KPIs!$A58<>"",OR($C$5="(Todos)",KPIs!$L58=$C$5),OR($C$6="(Todas)",KPIs!$M58=$C$6)),BO58,"") | BO58: =IF(AND(KPIs!$A58<>"",OR($C$5="(Todos)",KPIs!$L58=$C$5),OR($C$6="(Todas)",KPIs!$M58=$C$6)),N(BO57)+1,N(BO57)) | BR58: =IF(AND(Hitos!$A58<>"",OR($C$5="(Todos)",Hitos!$I58=$C$5),OR($C$6="(Todas)",Hitos!$J58=$C$6),OR(Hitos!$L58="Vencido",Hitos!$L58="Esta semana",Hitos!$L58="Próximos 30 días")),BS58,"") | BS58: =IF(AND(Hitos!$A58<>"",OR($C$5="(Todos)",Hitos!$I58=$C$5),OR($C$6="(Todas)",Hitos!$J58=$C$6),OR(Hitos!$L58="Vencido",Hitos!$L58="Esta semana",Hitos!$L58="Próximos 30 días")),N(BS57)+1,N(BS57))
B59: =IF($BL59="","",INDEX(KPIs!$K$2:$K$71,$BL59)) | C59: =IF($BL59="","",INDEX(KPIs!$C$2:$C$71,$BL59)) | D59: =IF($BL59="","",INDEX(KPIs!$D$2:$D$71,$BL59)) | E59: =IF($BL59="","",INDEX(KPIs!$E$2:$E$71,$BL59)) | F59: =IF($BL59="","",INDEX(KPIs!$F$2:$F$71,$BL59)) | G59: =IF($BL59="","",INDEX(KPIs!$G$2:$G$71,$BL59)) | H59: =IF($BL59="","",INDEX(KPIs!$H$2:$H$71,$BL59)) | I59: =IF($BL59="","",INDEX(KPIs!$N$2:$N$71,$BL59)) | J59: =IF($BL59="","",INDEX(KPIs!$O$2:$O$71,$BL59)) | K59: =IF($BL59="","",INDEX(KPIs!$I$2:$I$71,$BL59)) | L59: =IF($BL59="","",INDEX(KPIs!$J$2:$J$71,$BL59)) | BL59: =IFERROR(MATCH(3,$BN$2:$BN$71,0),"") | BN59: =IF(AND(KPIs!$A59<>"",OR($C$5="(Todos)",KPIs!$L59=$C$5),OR($C$6="(Todas)",KPIs!$M59=$C$6)),BO59,"") | BO59: =IF(AND(KPIs!$A59<>"",OR($C$5="(Todos)",KPIs!$L59=$C$5),OR($C$6="(Todas)",KPIs!$M59=$C$6)),N(BO58)+1,N(BO58)) | BR59: =IF(AND(Hitos!$A59<>"",OR($C$5="(Todos)",Hitos!$I59=$C$5),OR($C$6="(Todas)",Hitos!$J59=$C$6),OR(Hitos!$L59="Vencido",Hitos!$L59="Esta semana",Hitos!$L59="Próximos 30 días")),BS59,"") | BS59: =IF(AND(Hitos!$A59<>"",OR($C$5="(Todos)",Hitos!$I59=$C$5),OR($C$6="(Todas)",Hitos!$J59=$C$6),OR(Hitos!$L59="Vencido",Hitos!$L59="Esta semana",Hitos!$L59="Próximos 30 días")),N(BS58)+1,N(BS58))
B60: =IF($BL60="","",INDEX(KPIs!$K$2:$K$71,$BL60)) | C60: =IF($BL60="","",INDEX(KPIs!$C$2:$C$71,$BL60)) | D60: =IF($BL60="","",INDEX(KPIs!$D$2:$D$71,$BL60)) | E60: =IF($BL60="","",INDEX(KPIs!$E$2:$E$71,$BL60)) | F60: =IF($BL60="","",INDEX(KPIs!$F$2:$F$71,$BL60)) | G60: =IF($BL60="","",INDEX(KPIs!$G$2:$G$71,$BL60)) | H60: =IF($BL60="","",INDEX(KPIs!$H$2:$H$71,$BL60)) | I60: =IF($BL60="","",INDEX(KPIs!$N$2:$N$71,$BL60)) | J60: =IF($BL60="","",INDEX(KPIs!$O$2:$O$71,$BL60)) | K60: =IF($BL60="","",INDEX(KPIs!$I$2:$I$71,$BL60)) | L60: =IF($BL60="","",INDEX(KPIs!$J$2:$J$71,$BL60)) | BL60: =IFERROR(MATCH(4,$BN$2:$BN$71,0),"") | BN60: =IF(AND(KPIs!$A60<>"",OR($C$5="(Todos)",KPIs!$L60=$C$5),OR($C$6="(Todas)",KPIs!$M60=$C$6)),BO60,"") | BO60: =IF(AND(KPIs!$A60<>"",OR($C$5="(Todos)",KPIs!$L60=$C$5),OR($C$6="(Todas)",KPIs!$M60=$C$6)),N(BO59)+1,N(BO59)) | BR60: =IF(AND(Hitos!$A60<>"",OR($C$5="(Todos)",Hitos!$I60=$C$5),OR($C$6="(Todas)",Hitos!$J60=$C$6),OR(Hitos!$L60="Vencido",Hitos!$L60="Esta semana",Hitos!$L60="Próximos 30 días")),BS60,"") | BS60: =IF(AND(Hitos!$A60<>"",OR($C$5="(Todos)",Hitos!$I60=$C$5),OR($C$6="(Todas)",Hitos!$J60=$C$6),OR(Hitos!$L60="Vencido",Hitos!$L60="Esta semana",Hitos!$L60="Próximos 30 días")),N(BS59)+1,N(BS59))
B61: =IF($BL61="","",INDEX(KPIs!$K$2:$K$71,$BL61)) | C61: =IF($BL61="","",INDEX(KPIs!$C$2:$C$71,$BL61)) | D61: =IF($BL61="","",INDEX(KPIs!$D$2:$D$71,$BL61)) | E61: =IF($BL61="","",INDEX(KPIs!$E$2:$E$71,$BL61)) | F61: =IF($BL61="","",INDEX(KPIs!$F$2:$F$71,$BL61)) | G61: =IF($BL61="","",INDEX(KPIs!$G$2:$G$71,$BL61)) | H61: =IF($BL61="","",INDEX(KPIs!$H$2:$H$71,$BL61)) | I61: =IF($BL61="","",INDEX(KPIs!$N$2:$N$71,$BL61)) | J61: =IF($BL61="","",INDEX(KPIs!$O$2:$O$71,$BL61)) | K61: =IF($BL61="","",INDEX(KPIs!$I$2:$I$71,$BL61)) | L61: =IF($BL61="","",INDEX(KPIs!$J$2:$J$71,$BL61)) | BL61: =IFERROR(MATCH(5,$BN$2:$BN$71,0),"") | BN61: =IF(AND(KPIs!$A61<>"",OR($C$5="(Todos)",KPIs!$L61=$C$5),OR($C$6="(Todas)",KPIs!$M61=$C$6)),BO61,"") | BO61: =IF(AND(KPIs!$A61<>"",OR($C$5="(Todos)",KPIs!$L61=$C$5),OR($C$6="(Todas)",KPIs!$M61=$C$6)),N(BO60)+1,N(BO60)) | BR61: =IF(AND(Hitos!$A61<>"",OR($C$5="(Todos)",Hitos!$I61=$C$5),OR($C$6="(Todas)",Hitos!$J61=$C$6),OR(Hitos!$L61="Vencido",Hitos!$L61="Esta semana",Hitos!$L61="Próximos 30 días")),BS61,"") | BS61: =IF(AND(Hitos!$A61<>"",OR($C$5="(Todos)",Hitos!$I61=$C$5),OR($C$6="(Todas)",Hitos!$J61=$C$6),OR(Hitos!$L61="Vencido",Hitos!$L61="Esta semana",Hitos!$L61="Próximos 30 días")),N(BS60)+1,N(BS60))
B62: =IF($BL62="","",INDEX(KPIs!$K$2:$K$71,$BL62)) | C62: =IF($BL62="","",INDEX(KPIs!$C$2:$C$71,$BL62)) | D62: =IF($BL62="","",INDEX(KPIs!$D$2:$D$71,$BL62)) | E62: =IF($BL62="","",INDEX(KPIs!$E$2:$E$71,$BL62)) | F62: =IF($BL62="","",INDEX(KPIs!$F$2:$F$71,$BL62)) | G62: =IF($BL62="","",INDEX(KPIs!$G$2:$G$71,$BL62)) | H62: =IF($BL62="","",INDEX(KPIs!$H$2:$H$71,$BL62)) | I62: =IF($BL62="","",INDEX(KPIs!$N$2:$N$71,$BL62)) | J62: =IF($BL62="","",INDEX(KPIs!$O$2:$O$71,$BL62)) | K62: =IF($BL62="","",INDEX(KPIs!$I$2:$I$71,$BL62)) | L62: =IF($BL62="","",INDEX(KPIs!$J$2:$J$71,$BL62)) | BL62: =IFERROR(MATCH(6,$BN$2:$BN$71,0),"") | BN62: =IF(AND(KPIs!$A62<>"",OR($C$5="(Todos)",KPIs!$L62=$C$5),OR($C$6="(Todas)",KPIs!$M62=$C$6)),BO62,"") | BO62: =IF(AND(KPIs!$A62<>"",OR($C$5="(Todos)",KPIs!$L62=$C$5),OR($C$6="(Todas)",KPIs!$M62=$C$6)),N(BO61)+1,N(BO61)) | BR62: =IF(AND(Hitos!$A62<>"",OR($C$5="(Todos)",Hitos!$I62=$C$5),OR($C$6="(Todas)",Hitos!$J62=$C$6),OR(Hitos!$L62="Vencido",Hitos!$L62="Esta semana",Hitos!$L62="Próximos 30 días")),BS62,"") | BS62: =IF(AND(Hitos!$A62<>"",OR($C$5="(Todos)",Hitos!$I62=$C$5),OR($C$6="(Todas)",Hitos!$J62=$C$6),OR(Hitos!$L62="Vencido",Hitos!$L62="Esta semana",Hitos!$L62="Próximos 30 días")),N(BS61)+1,N(BS61))
B63: =IF($BL63="","",INDEX(KPIs!$K$2:$K$71,$BL63)) | C63: =IF($BL63="","",INDEX(KPIs!$C$2:$C$71,$BL63)) | D63: =IF($BL63="","",INDEX(KPIs!$D$2:$D$71,$BL63)) | E63: =IF($BL63="","",INDEX(KPIs!$E$2:$E$71,$BL63)) | F63: =IF($BL63="","",INDEX(KPIs!$F$2:$F$71,$BL63)) | G63: =IF($BL63="","",INDEX(KPIs!$G$2:$G$71,$BL63)) | H63: =IF($BL63="","",INDEX(KPIs!$H$2:$H$71,$BL63)) | I63: =IF($BL63="","",INDEX(KPIs!$N$2:$N$71,$BL63)) | J63: =IF($BL63="","",INDEX(KPIs!$O$2:$O$71,$BL63)) | K63: =IF($BL63="","",INDEX(KPIs!$I$2:$I$71,$BL63)) | L63: =IF($BL63="","",INDEX(KPIs!$J$2:$J$71,$BL63)) | BL63: =IFERROR(MATCH(7,$BN$2:$BN$71,0),"") | BN63: =IF(AND(KPIs!$A63<>"",OR($C$5="(Todos)",KPIs!$L63=$C$5),OR($C$6="(Todas)",KPIs!$M63=$C$6)),BO63,"") | BO63: =IF(AND(KPIs!$A63<>"",OR($C$5="(Todos)",KPIs!$L63=$C$5),OR($C$6="(Todas)",KPIs!$M63=$C$6)),N(BO62)+1,N(BO62)) | BR63: =IF(AND(Hitos!$A63<>"",OR($C$5="(Todos)",Hitos!$I63=$C$5),OR($C$6="(Todas)",Hitos!$J63=$C$6),OR(Hitos!$L63="Vencido",Hitos!$L63="Esta semana",Hitos!$L63="Próximos 30 días")),BS63,"") | BS63: =IF(AND(Hitos!$A63<>"",OR($C$5="(Todos)",Hitos!$I63=$C$5),OR($C$6="(Todas)",Hitos!$J63=$C$6),OR(Hitos!$L63="Vencido",Hitos!$L63="Esta semana",Hitos!$L63="Próximos 30 días")),N(BS62)+1,N(BS62))
B64: =IF($BL64="","",INDEX(KPIs!$K$2:$K$71,$BL64)) | C64: =IF($BL64="","",INDEX(KPIs!$C$2:$C$71,$BL64)) | D64: =IF($BL64="","",INDEX(KPIs!$D$2:$D$71,$BL64)) | E64: =IF($BL64="","",INDEX(KPIs!$E$2:$E$71,$BL64)) | F64: =IF($BL64="","",INDEX(KPIs!$F$2:$F$71,$BL64)) | G64: =IF($BL64="","",INDEX(KPIs!$G$2:$G$71,$BL64)) | H64: =IF($BL64="","",INDEX(KPIs!$H$2:$H$71,$BL64)) | I64: =IF($BL64="","",INDEX(KPIs!$N$2:$N$71,$BL64)) | J64: =IF($BL64="","",INDEX(KPIs!$O$2:$O$71,$BL64)) | K64: =IF($BL64="","",INDEX(KPIs!$I$2:$I$71,$BL64)) | L64: =IF($BL64="","",INDEX(KPIs!$J$2:$J$71,$BL64)) | BL64: =IFERROR(MATCH(8,$BN$2:$BN$71,0),"") | BN64: =IF(AND(KPIs!$A64<>"",OR($C$5="(Todos)",KPIs!$L64=$C$5),OR($C$6="(Todas)",KPIs!$M64=$C$6)),BO64,"") | BO64: =IF(AND(KPIs!$A64<>"",OR($C$5="(Todos)",KPIs!$L64=$C$5),OR($C$6="(Todas)",KPIs!$M64=$C$6)),N(BO63)+1,N(BO63)) | BR64: =IF(AND(Hitos!$A64<>"",OR($C$5="(Todos)",Hitos!$I64=$C$5),OR($C$6="(Todas)",Hitos!$J64=$C$6),OR(Hitos!$L64="Vencido",Hitos!$L64="Esta semana",Hitos!$L64="Próximos 30 días")),BS64,"") | BS64: =IF(AND(Hitos!$A64<>"",OR($C$5="(Todos)",Hitos!$I64=$C$5),OR($C$6="(Todas)",Hitos!$J64=$C$6),OR(Hitos!$L64="Vencido",Hitos!$L64="Esta semana",Hitos!$L64="Próximos 30 días")),N(BS63)+1,N(BS63))
B65: =IF($BL65="","",INDEX(KPIs!$K$2:$K$71,$BL65)) | C65: =IF($BL65="","",INDEX(KPIs!$C$2:$C$71,$BL65)) | D65: =IF($BL65="","",INDEX(KPIs!$D$2:$D$71,$BL65)) | E65: =IF($BL65="","",INDEX(KPIs!$E$2:$E$71,$BL65)) | F65: =IF($BL65="","",INDEX(KPIs!$F$2:$F$71,$BL65)) | G65: =IF($BL65="","",INDEX(KPIs!$G$2:$G$71,$BL65)) | H65: =IF($BL65="","",INDEX(KPIs!$H$2:$H$71,$BL65)) | I65: =IF($BL65="","",INDEX(KPIs!$N$2:$N$71,$BL65)) | J65: =IF($BL65="","",INDEX(KPIs!$O$2:$O$71,$BL65)) | K65: =IF($BL65="","",INDEX(KPIs!$I$2:$I$71,$BL65)) | L65: =IF($BL65="","",INDEX(KPIs!$J$2:$J$71,$BL65)) | BL65: =IFERROR(MATCH(9,$BN$2:$BN$71,0),"") | BN65: =IF(AND(KPIs!$A65<>"",OR($C$5="(Todos)",KPIs!$L65=$C$5),OR($C$6="(Todas)",KPIs!$M65=$C$6)),BO65,"") | BO65: =IF(AND(KPIs!$A65<>"",OR($C$5="(Todos)",KPIs!$L65=$C$5),OR($C$6="(Todas)",KPIs!$M65=$C$6)),N(BO64)+1,N(BO64)) | BR65: =IF(AND(Hitos!$A65<>"",OR($C$5="(Todos)",Hitos!$I65=$C$5),OR($C$6="(Todas)",Hitos!$J65=$C$6),OR(Hitos!$L65="Vencido",Hitos!$L65="Esta semana",Hitos!$L65="Próximos 30 días")),BS65,"") | BS65: =IF(AND(Hitos!$A65<>"",OR($C$5="(Todos)",Hitos!$I65=$C$5),OR($C$6="(Todas)",Hitos!$J65=$C$6),OR(Hitos!$L65="Vencido",Hitos!$L65="Esta semana",Hitos!$L65="Próximos 30 días")),N(BS64)+1,N(BS64))
B66: =IF($BL66="","",INDEX(KPIs!$K$2:$K$71,$BL66)) | C66: =IF($BL66="","",INDEX(KPIs!$C$2:$C$71,$BL66)) | D66: =IF($BL66="","",INDEX(KPIs!$D$2:$D$71,$BL66)) | E66: =IF($BL66="","",INDEX(KPIs!$E$2:$E$71,$BL66)) | F66: =IF($BL66="","",INDEX(KPIs!$F$2:$F$71,$BL66)) | G66: =IF($BL66="","",INDEX(KPIs!$G$2:$G$71,$BL66)) | H66: =IF($BL66="","",INDEX(KPIs!$H$2:$H$71,$BL66)) | I66: =IF($BL66="","",INDEX(KPIs!$N$2:$N$71,$BL66)) | J66: =IF($BL66="","",INDEX(KPIs!$O$2:$O$71,$BL66)) | K66: =IF($BL66="","",INDEX(KPIs!$I$2:$I$71,$BL66)) | L66: =IF($BL66="","",INDEX(KPIs!$J$2:$J$71,$BL66)) | BL66: =IFERROR(MATCH(10,$BN$2:$BN$71,0),"") | BN66: =IF(AND(KPIs!$A66<>"",OR($C$5="(Todos)",KPIs!$L66=$C$5),OR($C$6="(Todas)",KPIs!$M66=$C$6)),BO66,"") | BO66: =IF(AND(KPIs!$A66<>"",OR($C$5="(Todos)",KPIs!$L66=$C$5),OR($C$6="(Todas)",KPIs!$M66=$C$6)),N(BO65)+1,N(BO65)) | BR66: =IF(AND(Hitos!$A66<>"",OR($C$5="(Todos)",Hitos!$I66=$C$5),OR($C$6="(Todas)",Hitos!$J66=$C$6),OR(Hitos!$L66="Vencido",Hitos!$L66="Esta semana",Hitos!$L66="Próximos 30 días")),BS66,"") | BS66: =IF(AND(Hitos!$A66<>"",OR($C$5="(Todos)",Hitos!$I66=$C$5),OR($C$6="(Todas)",Hitos!$J66=$C$6),OR(Hitos!$L66="Vencido",Hitos!$L66="Esta semana",Hitos!$L66="Próximos 30 días")),N(BS65)+1,N(BS65))
B67: =IF($BL67="","",INDEX(KPIs!$K$2:$K$71,$BL67)) | C67: =IF($BL67="","",INDEX(KPIs!$C$2:$C$71,$BL67)) | D67: =IF($BL67="","",INDEX(KPIs!$D$2:$D$71,$BL67)) | E67: =IF($BL67="","",INDEX(KPIs!$E$2:$E$71,$BL67)) | F67: =IF($BL67="","",INDEX(KPIs!$F$2:$F$71,$BL67)) | G67: =IF($BL67="","",INDEX(KPIs!$G$2:$G$71,$BL67)) | H67: =IF($BL67="","",INDEX(KPIs!$H$2:$H$71,$BL67)) | I67: =IF($BL67="","",INDEX(KPIs!$N$2:$N$71,$BL67)) | J67: =IF($BL67="","",INDEX(KPIs!$O$2:$O$71,$BL67)) | K67: =IF($BL67="","",INDEX(KPIs!$I$2:$I$71,$BL67)) | L67: =IF($BL67="","",INDEX(KPIs!$J$2:$J$71,$BL67)) | BL67: =IFERROR(MATCH(11,$BN$2:$BN$71,0),"") | BN67: =IF(AND(KPIs!$A67<>"",OR($C$5="(Todos)",KPIs!$L67=$C$5),OR($C$6="(Todas)",KPIs!$M67=$C$6)),BO67,"") | BO67: =IF(AND(KPIs!$A67<>"",OR($C$5="(Todos)",KPIs!$L67=$C$5),OR($C$6="(Todas)",KPIs!$M67=$C$6)),N(BO66)+1,N(BO66)) | BR67: =IF(AND(Hitos!$A67<>"",OR($C$5="(Todos)",Hitos!$I67=$C$5),OR($C$6="(Todas)",Hitos!$J67=$C$6),OR(Hitos!$L67="Vencido",Hitos!$L67="Esta semana",Hitos!$L67="Próximos 30 días")),BS67,"") | BS67: =IF(AND(Hitos!$A67<>"",OR($C$5="(Todos)",Hitos!$I67=$C$5),OR($C$6="(Todas)",Hitos!$J67=$C$6),OR(Hitos!$L67="Vencido",Hitos!$L67="Esta semana",Hitos!$L67="Próximos 30 días")),N(BS66)+1,N(BS66))
B68: =IF($BL68="","",INDEX(KPIs!$K$2:$K$71,$BL68)) | C68: =IF($BL68="","",INDEX(KPIs!$C$2:$C$71,$BL68)) | D68: =IF($BL68="","",INDEX(KPIs!$D$2:$D$71,$BL68)) | E68: =IF($BL68="","",INDEX(KPIs!$E$2:$E$71,$BL68)) | F68: =IF($BL68="","",INDEX(KPIs!$F$2:$F$71,$BL68)) | G68: =IF($BL68="","",INDEX(KPIs!$G$2:$G$71,$BL68)) | H68: =IF($BL68="","",INDEX(KPIs!$H$2:$H$71,$BL68)) | I68: =IF($BL68="","",INDEX(KPIs!$N$2:$N$71,$BL68)) | J68: =IF($BL68="","",INDEX(KPIs!$O$2:$O$71,$BL68)) | K68: =IF($BL68="","",INDEX(KPIs!$I$2:$I$71,$BL68)) | L68: =IF($BL68="","",INDEX(KPIs!$J$2:$J$71,$BL68)) | BL68: =IFERROR(MATCH(12,$BN$2:$BN$71,0),"") | BN68: =IF(AND(KPIs!$A68<>"",OR($C$5="(Todos)",KPIs!$L68=$C$5),OR($C$6="(Todas)",KPIs!$M68=$C$6)),BO68,"") | BO68: =IF(AND(KPIs!$A68<>"",OR($C$5="(Todos)",KPIs!$L68=$C$5),OR($C$6="(Todas)",KPIs!$M68=$C$6)),N(BO67)+1,N(BO67)) | BR68: =IF(AND(Hitos!$A68<>"",OR($C$5="(Todos)",Hitos!$I68=$C$5),OR($C$6="(Todas)",Hitos!$J68=$C$6),OR(Hitos!$L68="Vencido",Hitos!$L68="Esta semana",Hitos!$L68="Próximos 30 días")),BS68,"") | BS68: =IF(AND(Hitos!$A68<>"",OR($C$5="(Todos)",Hitos!$I68=$C$5),OR($C$6="(Todas)",Hitos!$J68=$C$6),OR(Hitos!$L68="Vencido",Hitos!$L68="Esta semana",Hitos!$L68="Próximos 30 días")),N(BS67)+1,N(BS67))
B69: =IF($BL69="","",INDEX(KPIs!$K$2:$K$71,$BL69)) | C69: =IF($BL69="","",INDEX(KPIs!$C$2:$C$71,$BL69)) | D69: =IF($BL69="","",INDEX(KPIs!$D$2:$D$71,$BL69)) | E69: =IF($BL69="","",INDEX(KPIs!$E$2:$E$71,$BL69)) | F69: =IF($BL69="","",INDEX(KPIs!$F$2:$F$71,$BL69)) | G69: =IF($BL69="","",INDEX(KPIs!$G$2:$G$71,$BL69)) | H69: =IF($BL69="","",INDEX(KPIs!$H$2:$H$71,$BL69)) | I69: =IF($BL69="","",INDEX(KPIs!$N$2:$N$71,$BL69)) | J69: =IF($BL69="","",INDEX(KPIs!$O$2:$O$71,$BL69)) | K69: =IF($BL69="","",INDEX(KPIs!$I$2:$I$71,$BL69)) | L69: =IF($BL69="","",INDEX(KPIs!$J$2:$J$71,$BL69)) | BL69: =IFERROR(MATCH(13,$BN$2:$BN$71,0),"") | BN69: =IF(AND(KPIs!$A69<>"",OR($C$5="(Todos)",KPIs!$L69=$C$5),OR($C$6="(Todas)",KPIs!$M69=$C$6)),BO69,"") | BO69: =IF(AND(KPIs!$A69<>"",OR($C$5="(Todos)",KPIs!$L69=$C$5),OR($C$6="(Todas)",KPIs!$M69=$C$6)),N(BO68)+1,N(BO68)) | BR69: =IF(AND(Hitos!$A69<>"",OR($C$5="(Todos)",Hitos!$I69=$C$5),OR($C$6="(Todas)",Hitos!$J69=$C$6),OR(Hitos!$L69="Vencido",Hitos!$L69="Esta semana",Hitos!$L69="Próximos 30 días")),BS69,"") | BS69: =IF(AND(Hitos!$A69<>"",OR($C$5="(Todos)",Hitos!$I69=$C$5),OR($C$6="(Todas)",Hitos!$J69=$C$6),OR(Hitos!$L69="Vencido",Hitos!$L69="Esta semana",Hitos!$L69="Próximos 30 días")),N(BS68)+1,N(BS68))
B70: =IF($BL70="","",INDEX(KPIs!$K$2:$K$71,$BL70)) | C70: =IF($BL70="","",INDEX(KPIs!$C$2:$C$71,$BL70)) | D70: =IF($BL70="","",INDEX(KPIs!$D$2:$D$71,$BL70)) | E70: =IF($BL70="","",INDEX(KPIs!$E$2:$E$71,$BL70)) | F70: =IF($BL70="","",INDEX(KPIs!$F$2:$F$71,$BL70)) | G70: =IF($BL70="","",INDEX(KPIs!$G$2:$G$71,$BL70)) | H70: =IF($BL70="","",INDEX(KPIs!$H$2:$H$71,$BL70)) | I70: =IF($BL70="","",INDEX(KPIs!$N$2:$N$71,$BL70)) | J70: =IF($BL70="","",INDEX(KPIs!$O$2:$O$71,$BL70)) | K70: =IF($BL70="","",INDEX(KPIs!$I$2:$I$71,$BL70)) | L70: =IF($BL70="","",INDEX(KPIs!$J$2:$J$71,$BL70)) | BL70: =IFERROR(MATCH(14,$BN$2:$BN$71,0),"") | BN70: =IF(AND(KPIs!$A70<>"",OR($C$5="(Todos)",KPIs!$L70=$C$5),OR($C$6="(Todas)",KPIs!$M70=$C$6)),BO70,"") | BO70: =IF(AND(KPIs!$A70<>"",OR($C$5="(Todos)",KPIs!$L70=$C$5),OR($C$6="(Todas)",KPIs!$M70=$C$6)),N(BO69)+1,N(BO69)) | BR70: =IF(AND(Hitos!$A70<>"",OR($C$5="(Todos)",Hitos!$I70=$C$5),OR($C$6="(Todas)",Hitos!$J70=$C$6),OR(Hitos!$L70="Vencido",Hitos!$L70="Esta semana",Hitos!$L70="Próximos 30 días")),BS70,"") | BS70: =IF(AND(Hitos!$A70<>"",OR($C$5="(Todos)",Hitos!$I70=$C$5),OR($C$6="(Todas)",Hitos!$J70=$C$6),OR(Hitos!$L70="Vencido",Hitos!$L70="Esta semana",Hitos!$L70="Próximos 30 días")),N(BS69)+1,N(BS69))
B71: =IF($BL71="","",INDEX(KPIs!$K$2:$K$71,$BL71)) | C71: =IF($BL71="","",INDEX(KPIs!$C$2:$C$71,$BL71)) | D71: =IF($BL71="","",INDEX(KPIs!$D$2:$D$71,$BL71)) | E71: =IF($BL71="","",INDEX(KPIs!$E$2:$E$71,$BL71)) | F71: =IF($BL71="","",INDEX(KPIs!$F$2:$F$71,$BL71)) | G71: =IF($BL71="","",INDEX(KPIs!$G$2:$G$71,$BL71)) | H71: =IF($BL71="","",INDEX(KPIs!$H$2:$H$71,$BL71)) | I71: =IF($BL71="","",INDEX(KPIs!$N$2:$N$71,$BL71)) | J71: =IF($BL71="","",INDEX(KPIs!$O$2:$O$71,$BL71)) | K71: =IF($BL71="","",INDEX(KPIs!$I$2:$I$71,$BL71)) | L71: =IF($BL71="","",INDEX(KPIs!$J$2:$J$71,$BL71)) | BL71: =IFERROR(MATCH(15,$BN$2:$BN$71,0),"") | BN71: =IF(AND(KPIs!$A71<>"",OR($C$5="(Todos)",KPIs!$L71=$C$5),OR($C$6="(Todas)",KPIs!$M71=$C$6)),BO71,"") | BO71: =IF(AND(KPIs!$A71<>"",OR($C$5="(Todos)",KPIs!$L71=$C$5),OR($C$6="(Todas)",KPIs!$M71=$C$6)),N(BO70)+1,N(BO70)) | BR71: =IF(AND(Hitos!$A71<>"",OR($C$5="(Todos)",Hitos!$I71=$C$5),OR($C$6="(Todas)",Hitos!$J71=$C$6),OR(Hitos!$L71="Vencido",Hitos!$L71="Esta semana",Hitos!$L71="Próximos 30 días")),BS71,"") | BS71: =IF(AND(Hitos!$A71<>"",OR($C$5="(Todos)",Hitos!$I71=$C$5),OR($C$6="(Todas)",Hitos!$J71=$C$6),OR(Hitos!$L71="Vencido",Hitos!$L71="Esta semana",Hitos!$L71="Próximos 30 días")),N(BS70)+1,N(BS70))
B72: =IF($BL72="","",INDEX(KPIs!$K$2:$K$71,$BL72)) | C72: =IF($BL72="","",INDEX(KPIs!$C$2:$C$71,$BL72)) | D72: =IF($BL72="","",INDEX(KPIs!$D$2:$D$71,$BL72)) | E72: =IF($BL72="","",INDEX(KPIs!$E$2:$E$71,$BL72)) | F72: =IF($BL72="","",INDEX(KPIs!$F$2:$F$71,$BL72)) | G72: =IF($BL72="","",INDEX(KPIs!$G$2:$G$71,$BL72)) | H72: =IF($BL72="","",INDEX(KPIs!$H$2:$H$71,$BL72)) | I72: =IF($BL72="","",INDEX(KPIs!$N$2:$N$71,$BL72)) | J72: =IF($BL72="","",INDEX(KPIs!$O$2:$O$71,$BL72)) | K72: =IF($BL72="","",INDEX(KPIs!$I$2:$I$71,$BL72)) | L72: =IF($BL72="","",INDEX(KPIs!$J$2:$J$71,$BL72)) | BL72: =IFERROR(MATCH(16,$BN$2:$BN$71,0),"") | BR72: =IF(AND(Hitos!$A72<>"",OR($C$5="(Todos)",Hitos!$I72=$C$5),OR($C$6="(Todas)",Hitos!$J72=$C$6),OR(Hitos!$L72="Vencido",Hitos!$L72="Esta semana",Hitos!$L72="Próximos 30 días")),BS72,"") | BS72: =IF(AND(Hitos!$A72<>"",OR($C$5="(Todos)",Hitos!$I72=$C$5),OR($C$6="(Todas)",Hitos!$J72=$C$6),OR(Hitos!$L72="Vencido",Hitos!$L72="Esta semana",Hitos!$L72="Próximos 30 días")),N(BS71)+1,N(BS71))
B73: =IF($BL73="","",INDEX(KPIs!$K$2:$K$71,$BL73)) | C73: =IF($BL73="","",INDEX(KPIs!$C$2:$C$71,$BL73)) | D73: =IF($BL73="","",INDEX(KPIs!$D$2:$D$71,$BL73)) | E73: =IF($BL73="","",INDEX(KPIs!$E$2:$E$71,$BL73)) | F73: =IF($BL73="","",INDEX(KPIs!$F$2:$F$71,$BL73)) | G73: =IF($BL73="","",INDEX(KPIs!$G$2:$G$71,$BL73)) | H73: =IF($BL73="","",INDEX(KPIs!$H$2:$H$71,$BL73)) | I73: =IF($BL73="","",INDEX(KPIs!$N$2:$N$71,$BL73)) | J73: =IF($BL73="","",INDEX(KPIs!$O$2:$O$71,$BL73)) | K73: =IF($BL73="","",INDEX(KPIs!$I$2:$I$71,$BL73)) | L73: =IF($BL73="","",INDEX(KPIs!$J$2:$J$71,$BL73)) | BL73: =IFERROR(MATCH(17,$BN$2:$BN$71,0),"") | BR73: =IF(AND(Hitos!$A73<>"",OR($C$5="(Todos)",Hitos!$I73=$C$5),OR($C$6="(Todas)",Hitos!$J73=$C$6),OR(Hitos!$L73="Vencido",Hitos!$L73="Esta semana",Hitos!$L73="Próximos 30 días")),BS73,"") | BS73: =IF(AND(Hitos!$A73<>"",OR($C$5="(Todos)",Hitos!$I73=$C$5),OR($C$6="(Todas)",Hitos!$J73=$C$6),OR(Hitos!$L73="Vencido",Hitos!$L73="Esta semana",Hitos!$L73="Próximos 30 días")),N(BS72)+1,N(BS72))
B74: =IF($BL74="","",INDEX(KPIs!$K$2:$K$71,$BL74)) | C74: =IF($BL74="","",INDEX(KPIs!$C$2:$C$71,$BL74)) | D74: =IF($BL74="","",INDEX(KPIs!$D$2:$D$71,$BL74)) | E74: =IF($BL74="","",INDEX(KPIs!$E$2:$E$71,$BL74)) | F74: =IF($BL74="","",INDEX(KPIs!$F$2:$F$71,$BL74)) | G74: =IF($BL74="","",INDEX(KPIs!$G$2:$G$71,$BL74)) | H74: =IF($BL74="","",INDEX(KPIs!$H$2:$H$71,$BL74)) | I74: =IF($BL74="","",INDEX(KPIs!$N$2:$N$71,$BL74)) | J74: =IF($BL74="","",INDEX(KPIs!$O$2:$O$71,$BL74)) | K74: =IF($BL74="","",INDEX(KPIs!$I$2:$I$71,$BL74)) | L74: =IF($BL74="","",INDEX(KPIs!$J$2:$J$71,$BL74)) | BL74: =IFERROR(MATCH(18,$BN$2:$BN$71,0),"") | BR74: =IF(AND(Hitos!$A74<>"",OR($C$5="(Todos)",Hitos!$I74=$C$5),OR($C$6="(Todas)",Hitos!$J74=$C$6),OR(Hitos!$L74="Vencido",Hitos!$L74="Esta semana",Hitos!$L74="Próximos 30 días")),BS74,"") | BS74: =IF(AND(Hitos!$A74<>"",OR($C$5="(Todos)",Hitos!$I74=$C$5),OR($C$6="(Todas)",Hitos!$J74=$C$6),OR(Hitos!$L74="Vencido",Hitos!$L74="Esta semana",Hitos!$L74="Próximos 30 días")),N(BS73)+1,N(BS73))
B75: =IF($BL75="","",INDEX(KPIs!$K$2:$K$71,$BL75)) | C75: =IF($BL75="","",INDEX(KPIs!$C$2:$C$71,$BL75)) | D75: =IF($BL75="","",INDEX(KPIs!$D$2:$D$71,$BL75)) | E75: =IF($BL75="","",INDEX(KPIs!$E$2:$E$71,$BL75)) | F75: =IF($BL75="","",INDEX(KPIs!$F$2:$F$71,$BL75)) | G75: =IF($BL75="","",INDEX(KPIs!$G$2:$G$71,$BL75)) | H75: =IF($BL75="","",INDEX(KPIs!$H$2:$H$71,$BL75)) | I75: =IF($BL75="","",INDEX(KPIs!$N$2:$N$71,$BL75)) | J75: =IF($BL75="","",INDEX(KPIs!$O$2:$O$71,$BL75)) | K75: =IF($BL75="","",INDEX(KPIs!$I$2:$I$71,$BL75)) | L75: =IF($BL75="","",INDEX(KPIs!$J$2:$J$71,$BL75)) | BL75: =IFERROR(MATCH(19,$BN$2:$BN$71,0),"") | BR75: =IF(AND(Hitos!$A75<>"",OR($C$5="(Todos)",Hitos!$I75=$C$5),OR($C$6="(Todas)",Hitos!$J75=$C$6),OR(Hitos!$L75="Vencido",Hitos!$L75="Esta semana",Hitos!$L75="Próximos 30 días")),BS75,"") | BS75: =IF(AND(Hitos!$A75<>"",OR($C$5="(Todos)",Hitos!$I75=$C$5),OR($C$6="(Todas)",Hitos!$J75=$C$6),OR(Hitos!$L75="Vencido",Hitos!$L75="Esta semana",Hitos!$L75="Próximos 30 días")),N(BS74)+1,N(BS74))
B76: =IF($BL76="","",INDEX(KPIs!$K$2:$K$71,$BL76)) | C76: =IF($BL76="","",INDEX(KPIs!$C$2:$C$71,$BL76)) | D76: =IF($BL76="","",INDEX(KPIs!$D$2:$D$71,$BL76)) | E76: =IF($BL76="","",INDEX(KPIs!$E$2:$E$71,$BL76)) | F76: =IF($BL76="","",INDEX(KPIs!$F$2:$F$71,$BL76)) | G76: =IF($BL76="","",INDEX(KPIs!$G$2:$G$71,$BL76)) | H76: =IF($BL76="","",INDEX(KPIs!$H$2:$H$71,$BL76)) | I76: =IF($BL76="","",INDEX(KPIs!$N$2:$N$71,$BL76)) | J76: =IF($BL76="","",INDEX(KPIs!$O$2:$O$71,$BL76)) | K76: =IF($BL76="","",INDEX(KPIs!$I$2:$I$71,$BL76)) | L76: =IF($BL76="","",INDEX(KPIs!$J$2:$J$71,$BL76)) | BL76: =IFERROR(MATCH(20,$BN$2:$BN$71,0),"") | BR76: =IF(AND(Hitos!$A76<>"",OR($C$5="(Todos)",Hitos!$I76=$C$5),OR($C$6="(Todas)",Hitos!$J76=$C$6),OR(Hitos!$L76="Vencido",Hitos!$L76="Esta semana",Hitos!$L76="Próximos 30 días")),BS76,"") | BS76: =IF(AND(Hitos!$A76<>"",OR($C$5="(Todos)",Hitos!$I76=$C$5),OR($C$6="(Todas)",Hitos!$J76=$C$6),OR(Hitos!$L76="Vencido",Hitos!$L76="Esta semana",Hitos!$L76="Próximos 30 días")),N(BS75)+1,N(BS75))
B77: =IF($BL77="","",INDEX(KPIs!$K$2:$K$71,$BL77)) | C77: =IF($BL77="","",INDEX(KPIs!$C$2:$C$71,$BL77)) | D77: =IF($BL77="","",INDEX(KPIs!$D$2:$D$71,$BL77)) | E77: =IF($BL77="","",INDEX(KPIs!$E$2:$E$71,$BL77)) | F77: =IF($BL77="","",INDEX(KPIs!$F$2:$F$71,$BL77)) | G77: =IF($BL77="","",INDEX(KPIs!$G$2:$G$71,$BL77)) | H77: =IF($BL77="","",INDEX(KPIs!$H$2:$H$71,$BL77)) | I77: =IF($BL77="","",INDEX(KPIs!$N$2:$N$71,$BL77)) | J77: =IF($BL77="","",INDEX(KPIs!$O$2:$O$71,$BL77)) | K77: =IF($BL77="","",INDEX(KPIs!$I$2:$I$71,$BL77)) | L77: =IF($BL77="","",INDEX(KPIs!$J$2:$J$71,$BL77)) | BL77: =IFERROR(MATCH(21,$BN$2:$BN$71,0),"") | BR77: =IF(AND(Hitos!$A77<>"",OR($C$5="(Todos)",Hitos!$I77=$C$5),OR($C$6="(Todas)",Hitos!$J77=$C$6),OR(Hitos!$L77="Vencido",Hitos!$L77="Esta semana",Hitos!$L77="Próximos 30 días")),BS77,"") | BS77: =IF(AND(Hitos!$A77<>"",OR($C$5="(Todos)",Hitos!$I77=$C$5),OR($C$6="(Todas)",Hitos!$J77=$C$6),OR(Hitos!$L77="Vencido",Hitos!$L77="Esta semana",Hitos!$L77="Próximos 30 días")),N(BS76)+1,N(BS76))
B78: =IF($BL78="","",INDEX(KPIs!$K$2:$K$71,$BL78)) | C78: =IF($BL78="","",INDEX(KPIs!$C$2:$C$71,$BL78)) | D78: =IF($BL78="","",INDEX(KPIs!$D$2:$D$71,$BL78)) | E78: =IF($BL78="","",INDEX(KPIs!$E$2:$E$71,$BL78)) | F78: =IF($BL78="","",INDEX(KPIs!$F$2:$F$71,$BL78)) | G78: =IF($BL78="","",INDEX(KPIs!$G$2:$G$71,$BL78)) | H78: =IF($BL78="","",INDEX(KPIs!$H$2:$H$71,$BL78)) | I78: =IF($BL78="","",INDEX(KPIs!$N$2:$N$71,$BL78)) | J78: =IF($BL78="","",INDEX(KPIs!$O$2:$O$71,$BL78)) | K78: =IF($BL78="","",INDEX(KPIs!$I$2:$I$71,$BL78)) | L78: =IF($BL78="","",INDEX(KPIs!$J$2:$J$71,$BL78)) | BL78: =IFERROR(MATCH(22,$BN$2:$BN$71,0),"") | BR78: =IF(AND(Hitos!$A78<>"",OR($C$5="(Todos)",Hitos!$I78=$C$5),OR($C$6="(Todas)",Hitos!$J78=$C$6),OR(Hitos!$L78="Vencido",Hitos!$L78="Esta semana",Hitos!$L78="Próximos 30 días")),BS78,"") | BS78: =IF(AND(Hitos!$A78<>"",OR($C$5="(Todos)",Hitos!$I78=$C$5),OR($C$6="(Todas)",Hitos!$J78=$C$6),OR(Hitos!$L78="Vencido",Hitos!$L78="Esta semana",Hitos!$L78="Próximos 30 días")),N(BS77)+1,N(BS77))
B79: =IF($BL79="","",INDEX(KPIs!$K$2:$K$71,$BL79)) | C79: =IF($BL79="","",INDEX(KPIs!$C$2:$C$71,$BL79)) | D79: =IF($BL79="","",INDEX(KPIs!$D$2:$D$71,$BL79)) | E79: =IF($BL79="","",INDEX(KPIs!$E$2:$E$71,$BL79)) | F79: =IF($BL79="","",INDEX(KPIs!$F$2:$F$71,$BL79)) | G79: =IF($BL79="","",INDEX(KPIs!$G$2:$G$71,$BL79)) | H79: =IF($BL79="","",INDEX(KPIs!$H$2:$H$71,$BL79)) | I79: =IF($BL79="","",INDEX(KPIs!$N$2:$N$71,$BL79)) | J79: =IF($BL79="","",INDEX(KPIs!$O$2:$O$71,$BL79)) | K79: =IF($BL79="","",INDEX(KPIs!$I$2:$I$71,$BL79)) | L79: =IF($BL79="","",INDEX(KPIs!$J$2:$J$71,$BL79)) | BL79: =IFERROR(MATCH(23,$BN$2:$BN$71,0),"") | BR79: =IF(AND(Hitos!$A79<>"",OR($C$5="(Todos)",Hitos!$I79=$C$5),OR($C$6="(Todas)",Hitos!$J79=$C$6),OR(Hitos!$L79="Vencido",Hitos!$L79="Esta semana",Hitos!$L79="Próximos 30 días")),BS79,"") | BS79: =IF(AND(Hitos!$A79<>"",OR($C$5="(Todos)",Hitos!$I79=$C$5),OR($C$6="(Todas)",Hitos!$J79=$C$6),OR(Hitos!$L79="Vencido",Hitos!$L79="Esta semana",Hitos!$L79="Próximos 30 días")),N(BS78)+1,N(BS78))
B80: =IF($BL80="","",INDEX(KPIs!$K$2:$K$71,$BL80)) | C80: =IF($BL80="","",INDEX(KPIs!$C$2:$C$71,$BL80)) | D80: =IF($BL80="","",INDEX(KPIs!$D$2:$D$71,$BL80)) | E80: =IF($BL80="","",INDEX(KPIs!$E$2:$E$71,$BL80)) | F80: =IF($BL80="","",INDEX(KPIs!$F$2:$F$71,$BL80)) | G80: =IF($BL80="","",INDEX(KPIs!$G$2:$G$71,$BL80)) | H80: =IF($BL80="","",INDEX(KPIs!$H$2:$H$71,$BL80)) | I80: =IF($BL80="","",INDEX(KPIs!$N$2:$N$71,$BL80)) | J80: =IF($BL80="","",INDEX(KPIs!$O$2:$O$71,$BL80)) | K80: =IF($BL80="","",INDEX(KPIs!$I$2:$I$71,$BL80)) | L80: =IF($BL80="","",INDEX(KPIs!$J$2:$J$71,$BL80)) | BL80: =IFERROR(MATCH(24,$BN$2:$BN$71,0),"") | BR80: =IF(AND(Hitos!$A80<>"",OR($C$5="(Todos)",Hitos!$I80=$C$5),OR($C$6="(Todas)",Hitos!$J80=$C$6),OR(Hitos!$L80="Vencido",Hitos!$L80="Esta semana",Hitos!$L80="Próximos 30 días")),BS80,"") | BS80: =IF(AND(Hitos!$A80<>"",OR($C$5="(Todos)",Hitos!$I80=$C$5),OR($C$6="(Todas)",Hitos!$J80=$C$6),OR(Hitos!$L80="Vencido",Hitos!$L80="Esta semana",Hitos!$L80="Próximos 30 días")),N(BS79)+1,N(BS79))
B81: =IF($BL81="","",INDEX(KPIs!$K$2:$K$71,$BL81)) | C81: =IF($BL81="","",INDEX(KPIs!$C$2:$C$71,$BL81)) | D81: =IF($BL81="","",INDEX(KPIs!$D$2:$D$71,$BL81)) | E81: =IF($BL81="","",INDEX(KPIs!$E$2:$E$71,$BL81)) | F81: =IF($BL81="","",INDEX(KPIs!$F$2:$F$71,$BL81)) | G81: =IF($BL81="","",INDEX(KPIs!$G$2:$G$71,$BL81)) | H81: =IF($BL81="","",INDEX(KPIs!$H$2:$H$71,$BL81)) | I81: =IF($BL81="","",INDEX(KPIs!$N$2:$N$71,$BL81)) | J81: =IF($BL81="","",INDEX(KPIs!$O$2:$O$71,$BL81)) | K81: =IF($BL81="","",INDEX(KPIs!$I$2:$I$71,$BL81)) | L81: =IF($BL81="","",INDEX(KPIs!$J$2:$J$71,$BL81)) | BL81: =IFERROR(MATCH(25,$BN$2:$BN$71,0),"") | BR81: =IF(AND(Hitos!$A81<>"",OR($C$5="(Todos)",Hitos!$I81=$C$5),OR($C$6="(Todas)",Hitos!$J81=$C$6),OR(Hitos!$L81="Vencido",Hitos!$L81="Esta semana",Hitos!$L81="Próximos 30 días")),BS81,"") | BS81: =IF(AND(Hitos!$A81<>"",OR($C$5="(Todos)",Hitos!$I81=$C$5),OR($C$6="(Todas)",Hitos!$J81=$C$6),OR(Hitos!$L81="Vencido",Hitos!$L81="Esta semana",Hitos!$L81="Próximos 30 días")),N(BS80)+1,N(BS80))
B82: =IF($BL82="","",INDEX(KPIs!$K$2:$K$71,$BL82)) | C82: =IF($BL82="","",INDEX(KPIs!$C$2:$C$71,$BL82)) | D82: =IF($BL82="","",INDEX(KPIs!$D$2:$D$71,$BL82)) | E82: =IF($BL82="","",INDEX(KPIs!$E$2:$E$71,$BL82)) | F82: =IF($BL82="","",INDEX(KPIs!$F$2:$F$71,$BL82)) | G82: =IF($BL82="","",INDEX(KPIs!$G$2:$G$71,$BL82)) | H82: =IF($BL82="","",INDEX(KPIs!$H$2:$H$71,$BL82)) | I82: =IF($BL82="","",INDEX(KPIs!$N$2:$N$71,$BL82)) | J82: =IF($BL82="","",INDEX(KPIs!$O$2:$O$71,$BL82)) | K82: =IF($BL82="","",INDEX(KPIs!$I$2:$I$71,$BL82)) | L82: =IF($BL82="","",INDEX(KPIs!$J$2:$J$71,$BL82)) | BL82: =IFERROR(MATCH(26,$BN$2:$BN$71,0),"")
B83: =IF($BL83="","",INDEX(KPIs!$K$2:$K$71,$BL83)) | C83: =IF($BL83="","",INDEX(KPIs!$C$2:$C$71,$BL83)) | D83: =IF($BL83="","",INDEX(KPIs!$D$2:$D$71,$BL83)) | E83: =IF($BL83="","",INDEX(KPIs!$E$2:$E$71,$BL83)) | F83: =IF($BL83="","",INDEX(KPIs!$F$2:$F$71,$BL83)) | G83: =IF($BL83="","",INDEX(KPIs!$G$2:$G$71,$BL83)) | H83: =IF($BL83="","",INDEX(KPIs!$H$2:$H$71,$BL83)) | I83: =IF($BL83="","",INDEX(KPIs!$N$2:$N$71,$BL83)) | J83: =IF($BL83="","",INDEX(KPIs!$O$2:$O$71,$BL83)) | K83: =IF($BL83="","",INDEX(KPIs!$I$2:$I$71,$BL83)) | L83: =IF($BL83="","",INDEX(KPIs!$J$2:$J$71,$BL83)) | BL83: =IFERROR(MATCH(27,$BN$2:$BN$71,0),"")
B84: =IF($BL84="","",INDEX(KPIs!$K$2:$K$71,$BL84)) | C84: =IF($BL84="","",INDEX(KPIs!$C$2:$C$71,$BL84)) | D84: =IF($BL84="","",INDEX(KPIs!$D$2:$D$71,$BL84)) | E84: =IF($BL84="","",INDEX(KPIs!$E$2:$E$71,$BL84)) | F84: =IF($BL84="","",INDEX(KPIs!$F$2:$F$71,$BL84)) | G84: =IF($BL84="","",INDEX(KPIs!$G$2:$G$71,$BL84)) | H84: =IF($BL84="","",INDEX(KPIs!$H$2:$H$71,$BL84)) | I84: =IF($BL84="","",INDEX(KPIs!$N$2:$N$71,$BL84)) | J84: =IF($BL84="","",INDEX(KPIs!$O$2:$O$71,$BL84)) | K84: =IF($BL84="","",INDEX(KPIs!$I$2:$I$71,$BL84)) | L84: =IF($BL84="","",INDEX(KPIs!$J$2:$J$71,$BL84)) | BL84: =IFERROR(MATCH(28,$BN$2:$BN$71,0),"")
B85: =IF($BL85="","",INDEX(KPIs!$K$2:$K$71,$BL85)) | C85: =IF($BL85="","",INDEX(KPIs!$C$2:$C$71,$BL85)) | D85: =IF($BL85="","",INDEX(KPIs!$D$2:$D$71,$BL85)) | E85: =IF($BL85="","",INDEX(KPIs!$E$2:$E$71,$BL85)) | F85: =IF($BL85="","",INDEX(KPIs!$F$2:$F$71,$BL85)) | G85: =IF($BL85="","",INDEX(KPIs!$G$2:$G$71,$BL85)) | H85: =IF($BL85="","",INDEX(KPIs!$H$2:$H$71,$BL85)) | I85: =IF($BL85="","",INDEX(KPIs!$N$2:$N$71,$BL85)) | J85: =IF($BL85="","",INDEX(KPIs!$O$2:$O$71,$BL85)) | K85: =IF($BL85="","",INDEX(KPIs!$I$2:$I$71,$BL85)) | L85: =IF($BL85="","",INDEX(KPIs!$J$2:$J$71,$BL85)) | BL85: =IFERROR(MATCH(29,$BN$2:$BN$71,0),"")
B86: =IF($BL86="","",INDEX(KPIs!$K$2:$K$71,$BL86)) | C86: =IF($BL86="","",INDEX(KPIs!$C$2:$C$71,$BL86)) | D86: =IF($BL86="","",INDEX(KPIs!$D$2:$D$71,$BL86)) | E86: =IF($BL86="","",INDEX(KPIs!$E$2:$E$71,$BL86)) | F86: =IF($BL86="","",INDEX(KPIs!$F$2:$F$71,$BL86)) | G86: =IF($BL86="","",INDEX(KPIs!$G$2:$G$71,$BL86)) | H86: =IF($BL86="","",INDEX(KPIs!$H$2:$H$71,$BL86)) | I86: =IF($BL86="","",INDEX(KPIs!$N$2:$N$71,$BL86)) | J86: =IF($BL86="","",INDEX(KPIs!$O$2:$O$71,$BL86)) | K86: =IF($BL86="","",INDEX(KPIs!$I$2:$I$71,$BL86)) | L86: =IF($BL86="","",INDEX(KPIs!$J$2:$J$71,$BL86)) | BL86: =IFERROR(MATCH(30,$BN$2:$BN$71,0),"")
B87: =IF($BL87="","",INDEX(KPIs!$K$2:$K$71,$BL87)) | C87: =IF($BL87="","",INDEX(KPIs!$C$2:$C$71,$BL87)) | D87: =IF($BL87="","",INDEX(KPIs!$D$2:$D$71,$BL87)) | E87: =IF($BL87="","",INDEX(KPIs!$E$2:$E$71,$BL87)) | F87: =IF($BL87="","",INDEX(KPIs!$F$2:$F$71,$BL87)) | G87: =IF($BL87="","",INDEX(KPIs!$G$2:$G$71,$BL87)) | H87: =IF($BL87="","",INDEX(KPIs!$H$2:$H$71,$BL87)) | I87: =IF($BL87="","",INDEX(KPIs!$N$2:$N$71,$BL87)) | J87: =IF($BL87="","",INDEX(KPIs!$O$2:$O$71,$BL87)) | K87: =IF($BL87="","",INDEX(KPIs!$I$2:$I$71,$BL87)) | L87: =IF($BL87="","",INDEX(KPIs!$J$2:$J$71,$BL87)) | BL87: =IFERROR(MATCH(31,$BN$2:$BN$71,0),"")
B88: =IF($BL88="","",INDEX(KPIs!$K$2:$K$71,$BL88)) | C88: =IF($BL88="","",INDEX(KPIs!$C$2:$C$71,$BL88)) | D88: =IF($BL88="","",INDEX(KPIs!$D$2:$D$71,$BL88)) | E88: =IF($BL88="","",INDEX(KPIs!$E$2:$E$71,$BL88)) | F88: =IF($BL88="","",INDEX(KPIs!$F$2:$F$71,$BL88)) | G88: =IF($BL88="","",INDEX(KPIs!$G$2:$G$71,$BL88)) | H88: =IF($BL88="","",INDEX(KPIs!$H$2:$H$71,$BL88)) | I88: =IF($BL88="","",INDEX(KPIs!$N$2:$N$71,$BL88)) | J88: =IF($BL88="","",INDEX(KPIs!$O$2:$O$71,$BL88)) | K88: =IF($BL88="","",INDEX(KPIs!$I$2:$I$71,$BL88)) | L88: =IF($BL88="","",INDEX(KPIs!$J$2:$J$71,$BL88)) | BL88: =IFERROR(MATCH(32,$BN$2:$BN$71,0),"")
B89: =IF($BL89="","",INDEX(KPIs!$K$2:$K$71,$BL89)) | C89: =IF($BL89="","",INDEX(KPIs!$C$2:$C$71,$BL89)) | D89: =IF($BL89="","",INDEX(KPIs!$D$2:$D$71,$BL89)) | E89: =IF($BL89="","",INDEX(KPIs!$E$2:$E$71,$BL89)) | F89: =IF($BL89="","",INDEX(KPIs!$F$2:$F$71,$BL89)) | G89: =IF($BL89="","",INDEX(KPIs!$G$2:$G$71,$BL89)) | H89: =IF($BL89="","",INDEX(KPIs!$H$2:$H$71,$BL89)) | I89: =IF($BL89="","",INDEX(KPIs!$N$2:$N$71,$BL89)) | J89: =IF($BL89="","",INDEX(KPIs!$O$2:$O$71,$BL89)) | K89: =IF($BL89="","",INDEX(KPIs!$I$2:$I$71,$BL89)) | L89: =IF($BL89="","",INDEX(KPIs!$J$2:$J$71,$BL89)) | BL89: =IFERROR(MATCH(33,$BN$2:$BN$71,0),"")
B90: =IF($BL90="","",INDEX(KPIs!$K$2:$K$71,$BL90)) | C90: =IF($BL90="","",INDEX(KPIs!$C$2:$C$71,$BL90)) | D90: =IF($BL90="","",INDEX(KPIs!$D$2:$D$71,$BL90)) | E90: =IF($BL90="","",INDEX(KPIs!$E$2:$E$71,$BL90)) | F90: =IF($BL90="","",INDEX(KPIs!$F$2:$F$71,$BL90)) | G90: =IF($BL90="","",INDEX(KPIs!$G$2:$G$71,$BL90)) | H90: =IF($BL90="","",INDEX(KPIs!$H$2:$H$71,$BL90)) | I90: =IF($BL90="","",INDEX(KPIs!$N$2:$N$71,$BL90)) | J90: =IF($BL90="","",INDEX(KPIs!$O$2:$O$71,$BL90)) | K90: =IF($BL90="","",INDEX(KPIs!$I$2:$I$71,$BL90)) | L90: =IF($BL90="","",INDEX(KPIs!$J$2:$J$71,$BL90)) | BL90: =IFERROR(MATCH(34,$BN$2:$BN$71,0),"")
B91: =IF($BL91="","",INDEX(KPIs!$K$2:$K$71,$BL91)) | C91: =IF($BL91="","",INDEX(KPIs!$C$2:$C$71,$BL91)) | D91: =IF($BL91="","",INDEX(KPIs!$D$2:$D$71,$BL91)) | E91: =IF($BL91="","",INDEX(KPIs!$E$2:$E$71,$BL91)) | F91: =IF($BL91="","",INDEX(KPIs!$F$2:$F$71,$BL91)) | G91: =IF($BL91="","",INDEX(KPIs!$G$2:$G$71,$BL91)) | H91: =IF($BL91="","",INDEX(KPIs!$H$2:$H$71,$BL91)) | I91: =IF($BL91="","",INDEX(KPIs!$N$2:$N$71,$BL91)) | J91: =IF($BL91="","",INDEX(KPIs!$O$2:$O$71,$BL91)) | K91: =IF($BL91="","",INDEX(KPIs!$I$2:$I$71,$BL91)) | L91: =IF($BL91="","",INDEX(KPIs!$J$2:$J$71,$BL91)) | BL91: =IFERROR(MATCH(35,$BN$2:$BN$71,0),"")
B92: =IF($BL92="","",INDEX(KPIs!$K$2:$K$71,$BL92)) | C92: =IF($BL92="","",INDEX(KPIs!$C$2:$C$71,$BL92)) | D92: =IF($BL92="","",INDEX(KPIs!$D$2:$D$71,$BL92)) | E92: =IF($BL92="","",INDEX(KPIs!$E$2:$E$71,$BL92)) | F92: =IF($BL92="","",INDEX(KPIs!$F$2:$F$71,$BL92)) | G92: =IF($BL92="","",INDEX(KPIs!$G$2:$G$71,$BL92)) | H92: =IF($BL92="","",INDEX(KPIs!$H$2:$H$71,$BL92)) | I92: =IF($BL92="","",INDEX(KPIs!$N$2:$N$71,$BL92)) | J92: =IF($BL92="","",INDEX(KPIs!$O$2:$O$71,$BL92)) | K92: =IF($BL92="","",INDEX(KPIs!$I$2:$I$71,$BL92)) | L92: =IF($BL92="","",INDEX(KPIs!$J$2:$J$71,$BL92)) | BL92: =IFERROR(MATCH(36,$BN$2:$BN$71,0),"")
B93: =IF($BL93="","",INDEX(KPIs!$K$2:$K$71,$BL93)) | C93: =IF($BL93="","",INDEX(KPIs!$C$2:$C$71,$BL93)) | D93: =IF($BL93="","",INDEX(KPIs!$D$2:$D$71,$BL93)) | E93: =IF($BL93="","",INDEX(KPIs!$E$2:$E$71,$BL93)) | F93: =IF($BL93="","",INDEX(KPIs!$F$2:$F$71,$BL93)) | G93: =IF($BL93="","",INDEX(KPIs!$G$2:$G$71,$BL93)) | H93: =IF($BL93="","",INDEX(KPIs!$H$2:$H$71,$BL93)) | I93: =IF($BL93="","",INDEX(KPIs!$N$2:$N$71,$BL93)) | J93: =IF($BL93="","",INDEX(KPIs!$O$2:$O$71,$BL93)) | K93: =IF($BL93="","",INDEX(KPIs!$I$2:$I$71,$BL93)) | L93: =IF($BL93="","",INDEX(KPIs!$J$2:$J$71,$BL93)) | BL93: =IFERROR(MATCH(37,$BN$2:$BN$71,0),"")
B94: =IF($BL94="","",INDEX(KPIs!$K$2:$K$71,$BL94)) | C94: =IF($BL94="","",INDEX(KPIs!$C$2:$C$71,$BL94)) | D94: =IF($BL94="","",INDEX(KPIs!$D$2:$D$71,$BL94)) | E94: =IF($BL94="","",INDEX(KPIs!$E$2:$E$71,$BL94)) | F94: =IF($BL94="","",INDEX(KPIs!$F$2:$F$71,$BL94)) | G94: =IF($BL94="","",INDEX(KPIs!$G$2:$G$71,$BL94)) | H94: =IF($BL94="","",INDEX(KPIs!$H$2:$H$71,$BL94)) | I94: =IF($BL94="","",INDEX(KPIs!$N$2:$N$71,$BL94)) | J94: =IF($BL94="","",INDEX(KPIs!$O$2:$O$71,$BL94)) | K94: =IF($BL94="","",INDEX(KPIs!$I$2:$I$71,$BL94)) | L94: =IF($BL94="","",INDEX(KPIs!$J$2:$J$71,$BL94)) | BL94: =IFERROR(MATCH(38,$BN$2:$BN$71,0),"")
B95: =IF($BL95="","",INDEX(KPIs!$K$2:$K$71,$BL95)) | C95: =IF($BL95="","",INDEX(KPIs!$C$2:$C$71,$BL95)) | D95: =IF($BL95="","",INDEX(KPIs!$D$2:$D$71,$BL95)) | E95: =IF($BL95="","",INDEX(KPIs!$E$2:$E$71,$BL95)) | F95: =IF($BL95="","",INDEX(KPIs!$F$2:$F$71,$BL95)) | G95: =IF($BL95="","",INDEX(KPIs!$G$2:$G$71,$BL95)) | H95: =IF($BL95="","",INDEX(KPIs!$H$2:$H$71,$BL95)) | I95: =IF($BL95="","",INDEX(KPIs!$N$2:$N$71,$BL95)) | J95: =IF($BL95="","",INDEX(KPIs!$O$2:$O$71,$BL95)) | K95: =IF($BL95="","",INDEX(KPIs!$I$2:$I$71,$BL95)) | L95: =IF($BL95="","",INDEX(KPIs!$J$2:$J$71,$BL95)) | BL95: =IFERROR(MATCH(39,$BN$2:$BN$71,0),"")
